Workbook
Name Ad_Month: Market!$A$2:$A$553
Name Ad_Region: Market!$D$2:$D$553
Name Ad_Spend: Market!$F$2:$F$553
Name Ad_State: Market!$B$2:$B$553
Name Ad_State_Code: Market!$C$2:$C$553
Name Ad_Year: Market!$E$2:$E$553
Name Category: Orders!$O$2:$O$4834
Name cCat: Analysis!$B$7
Name cChannel: Analysis!$B$6
Name City: Orders!$K$2:$K$4834
Name COGS: Orders!$W$2:$W$4834
Name cRegion: Analysis!$B$5
Name Customer_ID: Orders!$F$2:$F$4834
Name Customer_Rating: Orders!$AE$2:$AE$4834
Name Customer_Type: Orders!$G$2:$G$4834
Name cYear: Analysis!$B$4
Name Delivery_Date: Orders!$AB$2:$AB$4834
Name Delivery_Days: Orders!$AC$2:$AC$4834
Name Delivery_Speed: Orders!$AD$2:$AD$4834
Name Discount_Amount: Orders!$T$2:$T$4834
Name Discount_Clean2: Orders!$R$2:$R$4834
Name Gross_Sale: Orders!$S$2:$S$4834
Name Margin: Orders!$Z$2:$Z$4834
Name Month: Orders!$D$2:$D$4834
Name Month_No: Orders!$E$2:$E$4834
Name Net_Revenue: Orders!$U$2:$U$4834
Name Order_Date: Orders!$B$2:$B$4834
Name Order_ID: Orders!$A$2:$A$4834
Name Payment_Method: Orders!$AA$2:$AA$4834
Name Product_ID: Orders!$M$2:$M$4834
Name Product_Name: Orders!$N$2:$N$4834
Name Profit: Orders!$Y$2:$Y$4834
Name Quantity: Orders!$P$2:$P$4834
Name Region: Orders!$J$2:$J$4834
Name Returned: Orders!$AF$2:$AF$4834
Name Sales_Channel: Orders!$L$2:$L$4834
Name selCategory: Dashboard!$P$5
Name selChannel: Dashboard!$L$5
Name selMetric: Dashboard!$T$5
Name selRegion: Dashboard!$H$5
Name selTopN: Dashboard!$X$5
Name selYear: Dashboard!$D$5
Name Shipping_Cost: Orders!$X$2:$X$4834
Name Slicer_Category: #N/A
Name Slicer_Region: #N/A
Name Slicer_Sales_Channel: #N/A
Name State: Orders!$H$2:$H$4834
Name State_Code: Orders!$I$2:$I$4834
Name Unit_Cost: Orders!$V$2:$V$4834
Name Unit_Price: Orders!$Q$2:$Q$4834
Name Year: Orders!$C$2:$C$4834

Sheet Detail2
A1: Details for Sum of Net Revenue - Months (Order Date): Mar, Quarters (Order Date): Qtr1, Years (Order Date): 2024
A3: Order ID | B3: Order Date | C3: Year | D3: Month | E3: Month No | F3: Customer ID | G3: Customer Type | H3: State | I3: State Code | J3: Region | K3: City | L3: Sales Channel | M3: Product ID | N3: Product Name | O3: Category | P3: Quantity | Q3: Unit Price | R3: Discount % | S3: Gross Sale | T3: Discount Amount | U3: Net Revenue | V3: Unit Cost | W3: COGS | X3: Shipping Cost | Y3: Profit Margin | Z3: Margin % | AA3: Payment Method | AB3: Delivery Date | AC3: Delivery Days | AD3: Delivery Speed | AE3: Customer Rating | AF3: Returned
A4: ORD-100297 | B4: 45352 | C4: 2024 | D4: 45352 | E4: 3 | F4: CUST-00404 | G4: New | H4: Karnataka | I4: KA | J4: South | K4: Mysuru | L4: Flipkart | M4: P404 | N4: Flip Flops | O4: Footwear | P4: 1 | Q4: 399 | R4: 0.05 | S4: 399 | T4: 19.95 | U4: 379.05 | V4: 152 | W4: 152 | X4: 60 | Y4: 167.05 | Z4: 0.44070703 | AA4: Credit Card | AB4: 45355 | AC4: 3 | AD4: Standard (3-4d) | AE4: 5 | AF4: 0
A5: ORD-100296 | B5: 45352 | C5: 2024 | D5: 45352 | E5: 3 | F5: CUST-00103 | G5: New | H5: Odisha | I5: OD | J5: East | K5: Bhubaneswar | L5: Amazon | M5: P101 | N5: Vitamin C Face Serum | O5: Skincare | P5: 2 | Q5: 599 | R5: 0.2 | S5: 1198 | T5: 239.6 | U5: 958.4 | V5: 180 | W5: 360 | X5: 60 | Y5: 538.4 | Z5: 0.56176962 | AA5: UPI | AB5: 45355 | AC5: 3 | AD5: Standard (3-4d) | AE5: 4 | AF5: 0
A6: ORD-100295 | B6: 45352 | C6: 2024 | D6: 45352 | E6: 3 | F6: CUST-01121 | G6: New | H6: Telangana | I6: TG | J6: South | K6: Hyderabad | L6: Amazon | M6: P203 | N6: Keratin Hair Mask | O6: Haircare | P6: 1 | Q6: 549 | R6: 0.2 | S6: 549 | T6: 109.8 | U6: 439.2 | V6: 170 | W6: 170 | X6: 60 | Y6: 209.2 | Z6: 0.47632058 | AA6: COD | AB6: 45354 | AC6: 2 | AD6: Express (≤2d) | AE6: 4 | AF6: 0
A7: ORD-100294 | B7: 45352 | C7: 2024 | D7: 45352 | E7: 3 | F7: CUST-01990 | G7: New | H7: Maharashtra | I7: MH | J7: West | K7: Mumbai | L7: Myntra | M7: P301 | N7: Cotton Oversized T-Shirt | O7: Apparel | P7: 1 | Q7: 799 | R7: 0.1 | S7: 799 | T7: 79.9 | U7: 719.1 | V7: 320 | W7: 320 | X7: 60 | Y7: 339.1 | Z7: 0.47156167 | AA7: Wallet | AB7: 45353 | AC7: 1 | AD7: Express (≤2d) | AE7: 4 | AF7: 0
A8: ORD-100293 | B8: 45352 | C8: 2024 | D8: 45352 | E8: 3 | F8: CUST-01052 | G8: New | H8: West Bengal | I8: WB | J8: East | K8: Kolkata | L8: Flipkart | M8: P303 | N8: Joggers | O8: Apparel | P8: 1 | Q8: 1199 | R8: 0.05 | S8: 1199 | T8: 59.95 | U8: 1139.05 | V8: 492 | W8: 492 | X8: 120 | Y8: 527.05 | Z8: 0.46271015 | AA8: COD | AB8: 45353 | AC8: 1 | AD8: Express (≤2d) | AF8: 1
A9: ORD-100292 | B9: 45352 | C9: 2024 | D9: 45352 | E9: 3 | F9: CUST-03067 | G9: New | H9: Madhya Pradesh | I9: MP | J9: West | K9: Bhopal | L9: Website | M9: P702 | N9: Whey Protein 1kg | O9: Wellness | P9: 1 | Q9: 2299 | R9: 0.25 | S9: 2299 | T9: 574.75 | U9: 1724.25 | V9: 1333 | W9: 1333 | X9: 60 | Y9: 331.25 | Z9: 0.19211251 | AA9: Wallet | AB9: 45356 | AC9: 4 | AD9: Standard (3-4d) | AE9: 4 | AF9: 0
A10: ORD-100300 | B10: 45353 | C10: 2024 | D10: 45352 | E10: 3 | F10: CUST-00943 | G10: New | H10: Tamil Nadu | I10: TN | J10: South | K10: Chennai | L10: Myntra | M10: P404 | N10: Flip Flops | O10: Footwear | P10: 1 | Q10: 399 | R10: 0.15 | S10: 399 | T10: 59.85 | U10: 339.15 | V10: 152 | W10: 152 | X10: 60 | Y10: 127.15 | Z10: 0.37490786 | AA10: UPI | AB10: 45355 | AC10: 2 | AD10: Express (≤2d) | AE10: 5 | AF10: 0
A11: ORD-100299 | B11: 45353 | C11: 2024 | D11: 45352 | E11: 3 | F11: CUST-01058 | G11: New | H11: Kerala | I11: KL | J11: South | K11: Thiruvananthapuram | L11: Amazon | M11: P501 | N11: Copper Water Bottle | O11: Home & Kitchen | P11: 1 | Q11: 899 | R11: 0.05 | S11: 899 | T11: 44.95 | U11: 854.05 | V11: 378 | W11: 378 | X11: 120 | Y11: 356.05 | Z11: 0.41689597 | AA11: COD | AB11: 45357 | AC11: 4 | AD11: Standard (3-4d) | AE11: 4 | AF11: 1
A12: ORD-100298 | B12: 45353 | C12: 2024 | D12: 45352 | E12: 3 | F12: CUST-00530 | G12: New | H12: Maharashtra | I12: MH | J12: West | K12: Pune | L12: Flipkart | M12: P303 | N12: Joggers | O12: Apparel | P12: 1 | Q12: 1199 | R12: 0.2 | S12: 1199 | T12: 239.8 | U12: 959.2 | V12: 492 | W12: 492 | X12: 60 | Y12: 407.2 | Z12: 0.42452043 | AA12: UPI | AB12: 45355 | AC12: 2 | AD12: Express (≤2d) | AE12: 3 | AF12: 0
A13: ORD-100304 | B13: 45354 | C13: 2024 | D13: 45352 | E13: 3 | F13: CUST-00728 | G13: New | H13: Karnataka | I13: KA | J13: South | K13: Bengaluru | L13: Nykaa | M13: P701 | N13: Ashwagandha Capsules | O13: Wellness | P13: 1 | Q13: 499 | R13: 0 | S13: 499 | T13: 0 | U13: 499 | V13: 150 | W13: 150 | X13: 60 | Y13: 289 | Z13: 0.57915832 | AA13: COD | AB13: 45357 | AC13: 3 | AD13: Standard (3-4d) | AE13: 4 | AF13: 0
A14: ORD-100303 | B14: 45354 | C14: 2024 | D14: 45352 | E14: 3 | F14: CUST-00295 | G14: New | H14: Maharashtra | I14: MH | J14: West | K14: Pune | L14: Myntra | M14: P303 | N14: Joggers | O14: Apparel | P14: 2 | Q14: 1199 | R14: 0.15 | S14: 2398 | T14: 359.7 | U14: 2038.3 | V14: 492 | W14: 984 | X14: 60 | Y14: 994.3 | Z14: 0.48780847 | AA14: Credit Card | AB14: 45357 | AC14: 3 | AD14: Standard (3-4d) | AE14: 4 | AF14: 0
A15: ORD-100302 | B15: 45354 | C15: 2024 | D15: 45352 | E15: 3 | F15: CUST-02092 | G15: New | H15: West Bengal | I15: WB | J15: East | K15: Kolkata | L15: Amazon | M15: P303 | N15: Joggers | O15: Apparel | P15: 3 | Q15: 1199 | R15: 0.2 | S15: 3597 | T15: 719.4 | U15: 2877.6 | V15: 492 | W15: 1476 | X15: 120 | Y15: 1281.6 | Z15: 0.44537114 | AA15: Debit Card | AB15: 45356 | AC15: 2 | AD15: Express (≤2d) | AF15: 1
A16: ORD-100301 | B16: 45354 | C16: 2024 | D16: 45352 | E16: 3 | F16: CUST-00832 | G16: New | H16: Delhi | I16: DL | J16: North | K16: New Delhi | L16: Myntra | M16: P401 | N16: Running Shoes | O16: Footwear | P16: 1 | Q16: 2999 | R16: 0.2 | S16: 2999 | T16: 599.8 | U16: 2399.2 | V16: 1440 | W16: 1440 | X16: 60 | Y16: 899.2 | Z16: 0.3747916 | AA16: Debit Card | AB16: 45356 | AC16: 2 | AD16: Express (≤2d) | AE16: 4 | AF16: 0
A17: ORD-100308 | B17: 45355 | C17: 2024 | D17: 45352 | E17: 3 | F17: CUST-02052 | G17: New | H17: West Bengal | I17: WB | J17: East | K17: Kolkata | L17: Myntra | M17: P302 | N17: Linen Kurta | O17: Apparel | P17: 2 | Q17: 1499 | R17: 0.4 | S17: 2998 | T17: 1199.2 | U17: 1798.8 | V17: 630 | W17: 1260 | X17: 60 | Y17: 478.8 | Z17: 0.26617745 | AA17: Debit Card | AB17: 45359 | AC17: 4 | AD17: Standard (3-4d) | AE17: 3 | AF17: 0
A18: ORD-100307 | B18: 45355 | C18: 2024 | D18: 45352 | E18: 3 | F18: CUST-00021 | G18: New | H18: Chhattisgarh | I18: CG | J18: East | K18: Raipur | L18: Website | M18: P602 | N18: Fast Charger 33W | O18: Electronics | P18: 1 | Q18: 899 | R18: 0 | S18: 899 | T18: 0 | U18: 899 | V18: 494 | W18: 494 | X18: 60 | Y18: 345 | Z18: 0.38375973 | AA18: COD | AB18: 45359 | AC18: 4 | AD18: Standard (3-4d) | AE18: 4 | AF18: 0
A19: ORD-100306 | B19: 45355 | C19: 2024 | D19: 45352 | E19: 3 | F19: CUST-00831 | G19: Repeat | H19: Uttar Pradesh | I19: UP | J19: North | K19: Lucknow | L19: Amazon | M19: P501 | N19: Copper Water Bottle | O19: Home & Kitchen | P19: 2 | Q19: 899 | R19: 0.05 | S19: 1798 | T19: 89.9 | U19: 1708.1 | V19: 378 | W19: 756 | X19: 120 | Y19: 832.1 | Z19: 0.48714946 | AA19: UPI | AB19: 45359 | AC19: 4 | AD19: Standard (3-4d) | AF19: 1
A20: ORD-100305 | B20: 45355 | C20: 2024 | D20: 45352 | E20: 3 | F20: CUST-01098 | G20: New | H20: Rajasthan | I20: RJ | J20: North | K20: Udaipur | L20: Amazon | M20: P702 | N20: Whey Protein 1kg | O20: Wellness | P20: 2 | Q20: 2299 | R20: 0.4 | S20: 4598 | T20: 1839.2 | U20: 2758.8 | V20: 1333 | W20: 2666 | X20: 60 | Y20: 32.8 | Z20: 0.011889227 | AA20: COD | AB20: 45360 | AC20: 5 | AD20: Delayed (5d+) | AE20: 3 | AF20: 0
A21: ORD-100311 | B21: 45356 | C21: 2024 | D21: 45352 | E21: 3 | F21: CUST-03156 | G21: New | H21: West Bengal | I21: WB | J21: East | K21: Kolkata | L21: Flipkart | M21: P404 | N21: Flip Flops | O21: Footwear | P21: 1 | Q21: 399 | R21: 0.1 | S21: 399 | T21: 39.9 | U21: 359.1 | V21: 152 | W21: 152 | X21: 60 | Y21: 147.1 | Z21: 0.4096352 | AA21: Credit Card | AB21: 45361 | AC21: 5 | AD21: Delayed (5d+) | AE21: 3 | AF21: 0
A22: ORD-100310 | B22: 45356 | C22: 2024 | D22: 45352 | E22: 3 | F22: CUST-00628 | G22: New | H22: Madhya Pradesh | I22: MP | J22: West | K22: Indore | L22: Myntra | M22: P302 | N22: Linen Kurta | O22: Apparel | P22: 2 | Q22: 1499 | R22: 0.4 | S22: 2998 | T22: 1199.2 | U22: 1798.8 | V22: 630 | W22: 1260 | X22: 60 | Y22: 478.8 | Z22: 0.26617745 | AA22: COD | AB22: 45359 | AC22: 3 | AD22: Standard (3-4d) | AF22: 0
A23: ORD-100309 | B23: 45356 | C23: 2024 | D23: 45352 | E23: 3 | F23: CUST-01054 | G23: New | H23: Delhi | I23: DL | J23: North | K23: New Delhi | L23: Amazon | M23: P603 | N23: Smartwatch Strap | O23: Electronics | P23: 1 | Q23: 499 | R23: 0.05 | S23: 499 | T23: 24.95 | U23: 474.05 | V23: 200 | W23: 200 | X23: 60 | Y23: 214.05 | Z23: 0.45153465 | AA23: Credit Card | AB23: 45359 | AC23: 3 | AD23: Standard (3-4d) | AE23: 3 | AF23: 0
A24: ORD-100316 | B24: 45357 | C24: 2024 | D24: 45352 | E24: 3 | F24: CUST-02384 | G24: New | H24: Maharashtra | I24: MH | J24: West | K24: Nagpur | L24: Amazon | M24: P104 | N24: Hydrating Face Wash | O24: Skincare | P24: 3 | Q24: 299 | R24: 0 | S24: 897 | T24: 0 | U24: 897 | V24: 90 | W24: 270 | X24: 60 | Y24: 567 | Z24: 0.63210702 | AA24: UPI | AB24: 45358 | AC24: 1 | AD24: Express (≤2d) | AE24: 5 | AF24: 0
A25: ORD-100315 | B25: 45357 | C25: 2024 | D25: 45352 | E25: 3 | F25: CUST-00390 | G25: New | H25: West Bengal | I25: WB | J25: East | K25: Kolkata | L25: Nykaa | M25: P701 | N25: Ashwagandha Capsules | O25: Wellness | P25: 2 | Q25: 499 | R25: 0.05 | S25: 998 | T25: 49.9 | U25: 948.1 | V25: 150 | W25: 300 | X25: 60 | Y25: 588.1 | Z25: 0.62029322 | AA25: UPI | AB25: 45360 | AC25: 3 | AD25: Standard (3-4d) | AE25: 5 | AF25: 0
A26: ORD-100314 | B26: 45357 | C26: 2024 | D26: 45352 | E26: 3 | F26: CUST-00141 | G26: New | H26: Uttar Pradesh | I26: UP | J26: North | K26: Kanpur | L26: Website | M26: P103 | N26: Niacinamide Toner | O26: Skincare | P26: 1 | Q26: 399 | R26: 0.15 | S26: 399 | T26: 59.85 | U26: 339.15 | V26: 112 | W26: 112 | X26: 60 | Y26: 167.15 | Z26: 0.49284977 | AA26: Credit Card | AB26: 45362 | AC26: 5 | AD26: Delayed (5d+) | AE26: 4 | AF26: 0
A27: ORD-100313 | B27: 45357 | C27: 2024 | D27: 45352 | E27: 3 | F27: CUST-00182 | G27: Repeat | H27: Delhi | I27: DL | J27: North | K27: New Delhi | L27: Flipkart | M27: P105 | N27: Retinol Night Cream | O27: Skincare | P27: 1 | Q27: 799 | R27: 0.1 | S27: 799 | T27: 79.9 | U27: 719.1 | V27: 216 | W27: 216 | X27: 60 | Y27: 443.1 | Z27: 0.6161869 | AA27: Debit Card | AB27: 45358 | AC27: 1 | AD27: Express (≤2d) | AE27: 4 | AF27: 0
A28: ORD-100312 | B28: 45357 | C28: 2024 | D28: 45352 | E28: 3 | F28: CUST-02085 | G28: New | H28: Himachal Pradesh | I28: HP | J28: North | K28: Shimla | L28: Amazon | M28: P204 | N28: Anti-Dandruff Conditioner | O28: Haircare | P28: 2 | Q28: 399 | R28: 0.3 | S28: 798 | T28: 239.4 | U28: 558.6 | V28: 136 | W28: 272 | X28: 60 | Y28: 226.6 | Z28: 0.405657 | AA28: UPI | AB28: 45360 | AC28: 3 | AD28: Standard (3-4d) | AE28: 4 | AF28: 0
A29: ORD-100321 | B29: 45358 | C29: 2024 | D29: 45352 | E29: 3 | F29: CUST-00602 | G29: New | H29: Gujarat | I29: GJ | J29: West | K29: Surat | L29: Flipkart | M29: P602 | N29: Fast Charger 33W | O29: Electronics | P29: 2 | Q29: 899 | R29: 0.05 | S29: 1798 | T29: 89.9 | U29: 1708.1 | V29: 494 | W29: 988 | X29: 60 | Y29: 660.1 | Z29: 0.38645278 | AA29: COD | AB29: 45361 | AC29: 3 | AD29: Standard (3-4d) | AE29: 5 | AF29: 0
A30: ORD-100320 | B30: 45358 | C30: 2024 | D30: 45352 | E30: 3 | F30: CUST-00297 | G30: Repeat | H30: Delhi | I30: DL | J30: North | K30: New Delhi | L30: Amazon | M30: P102 | N30: Sunscreen SPF 50 | O30: Skincare | P30: 1 | Q30: 449 | R30: 0.1 | S30: 449 | T30: 44.9 | U30: 404.1 | V30: 144 | W30: 144 | X30: 60 | Y30: 200.1 | Z30: 0.49517446 | AA30: UPI | AB30: 45359 | AC30: 1 | AD30: Express (≤2d) | AF30: 0
A31: ORD-100319 | B31: 45358 | C31: 2024 | D31: 45352 | E31: 3 | F31: CUST-01047 | G31: New | H31: Delhi | I31: DL | J31: North | K31: New Delhi | L31: Nykaa | M31: P102 | N31: Sunscreen SPF 50 | O31: Skincare | P31: 1 | Q31: 449 | R31: 0.05 | S31: 449 | T31: 22.45 | U31: 426.55 | V31: 144 | W31: 144 | X31: 60 | Y31: 222.55 | Z31: 0.52174423 | AA31: Debit Card | AB31: 45359 | AC31: 1 | AD31: Express (≤2d) | AE31: 5 | AF31: 0
A32: ORD-100318 | B32: 45358 | C32: 2024 | D32: 45352 | E32: 3 | F32: CUST-02389 | G32: New | H32: Haryana | I32: HR | J32: North | K32: Faridabad | L32: Amazon | M32: P404 | N32: Flip Flops | O32: Footwear | P32: 1 | Q32: 399 | R32: 0.15 | S32: 399 | T32: 59.85 | U32: 339.15 | V32: 152 | W32: 152 | X32: 120 | Y32: 67.15 | Z32: 0.19799499 | AA32: UPI | AB32: 45360 | AC32: 2 | AD32: Express (≤2d) | AE32: 5 | AF32: 1
A33: ORD-100317 | B33: 45358 | C33: 2024 | D33: 45352 | E33: 3 | F33: CUST-00991 | G33: Repeat | H33: Rajasthan | I33: RJ | J33: North | K33: Udaipur | L33: Flipkart | M33: P404 | N33: Flip Flops | O33: Footwear | P33: 4 | Q33: 399 | R33: 0.05 | S33: 1596 | T33: 79.8 | U33: 1516.2 | V33: 152 | W33: 608 | X33: 60 | Y33: 848.2 | Z33: 0.55942488 | AA33: UPI | AB33: 45362 | AC33: 4 | AD33: Standard (3-4d) | AF33: 0
A34: ORD-100325 | B34: 45359 | C34: 2024 | D34: 45352 | E34: 3 | F34: CUST-01148 | G34: New | H34: Telangana | I34: TG | J34: South | K34: Hyderabad | L34: Website | M34: P704 | N34: Multivitamin Gummies | O34: Wellness | P34: 2 | Q34: 699 | R34: 0.15 | S34: 1398 | T34: 209.7 | U34: 1188.3 | V34: 238 | W34: 476 | X34: 60 | Y34: 652.3 | Z34: 0.54893545 | AA34: UPI | AB34: 45363 | AC34: 4 | AD34: Standard (3-4d) | AF34: 0
A35: ORD-100324 | B35: 45359 | C35: 2024 | D35: 45352 | E35: 3 | F35: CUST-00170 | G35: New | H35: West Bengal | I35: WB | J35: East | K35: Kolkata | L35: Nykaa | M35: P701 | N35: Ashwagandha Capsules | O35: Wellness | P35: 3 | Q35: 499 | R35: 0.1 | S35: 1497 | T35: 149.7 | U35: 1347.3 | V35: 150 | W35: 450 | X35: 60 | Y35: 837.3 | Z35: 0.62146515 | AA35: COD | AB35: 45362 | AC35: 3 | AD35: Standard (3-4d) | AE35: 4 | AF35: 0
A36: ORD-100323 | B36: 45359 | C36: 2024 | D36: 45352 | E36: 3 | F36: CUST-01664 | G36: New | H36: West Bengal | I36: WB | J36: East | K36: Kolkata | L36: Website | M36: P105 | N36: Retinol Night Cream | O36: Skincare | P36: 1 | Q36: 799 | R36: 0 | S36: 799 | T36: 0 | U36: 799 | V36: 216 | W36: 216 | X36: 60 | Y36: 523 | Z36: 0.65456821 | AA36: COD | AB36: 45361 | AC36: 2 | AD36: Express (≤2d) | AE36: 4 | AF36: 0
A37: ORD-100322 | B37: 45359 | C37: 2024 | D37: 45352 | E37: 3 | F37: CUST-00687 | G37: New | H37: Assam | I37: AS | J37: East | K37: Guwahati | L37: Myntra | M37: P302 | N37: Linen Kurta | O37: Apparel | P37: 1 | Q37: 1499 | R37: 0.4 | S37: 1499 | T37: 599.6 | U37: 899.4 | V37: 630 | W37: 630 | X37: 60 | Y37: 209.4 | Z37: 0.23282188 | AA37: UPI | AB37: 45364 | AC37: 5 | AD37: Delayed (5d+) | AE37: 2 | AF37: 0
A38: ORD-100329 | B38: 45360 | C38: 2024 | D38: 45352 | E38: 3 | F38: CUST-02065 | G38: New | H38: Andhra Pradesh | I38: AP | J38: South | K38: Visakhapatnam | L38: Amazon | M38: P701 | N38: Ashwagandha Capsules | O38: Wellness | P38: 1 | Q38: 499 | R38: 0 | S38: 499 | T38: 0 | U38: 499 | V38: 150 | W38: 150 | X38: 120 | Y38: 229 | Z38: 0.45891784 | AA38: COD | AB38: 45365 | AC38: 5 | AD38: Delayed (5d+) | AE38: 4 | AF38: 1
A39: ORD-100328 | B39: 45360 | C39: 2024 | D39: 45352 | E39: 3 | F39: CUST-02148 | G39: New | H39: Telangana | I39: TG | J39: South | K39: Hyderabad | L39: Amazon | M39: P302 | N39: Linen Kurta | O39: Apparel | P39: 2 | Q39: 1499 | R39: 0.4 | S39: 2998 | T39: 1199.2 | U39: 1798.8 | V39: 630 | W39: 1260 | X39: 60 | Y39: 478.8 | Z39: 0.26617745 | AA39: Credit Card | AB39: 45361 | AC39: 1 | AD39: Express (≤2d) | AE39: 5 | AF39: 0
A40: ORD-100327 | B40: 45360 | C40: 2024 | D40: 45352 | E40: 3 | F40: CUST-03160 | G40: New | H40: West Bengal | I40: WB | J40: East | K40: Kolkata | L40: Myntra | M40: P301 | N40: Cotton Oversized T-Shirt | O40: Apparel | P40: 1 | Q40: 799 | R40: 0 | S40: 799 | T40: 0 | U40: 799 | V40: 320 | W40: 320 | X40: 60 | Y40: 419 | Z40: 0.52440551 | AA40: UPI | AB40: 45361 | AC40: 1 | AD40: Express (≤2d) | AE40: 5 | AF40: 0
A41: ORD-100326 | B41: 45360 | C41: 2024 | D41: 45352 | E41: 3 | F41: CUST-02599 | G41: New | H41: Delhi | I41: DL | J41: North | K41: New Delhi | L41: Amazon | M41: P402 | N41: Casual Sneakers | O41: Footwear | P41: 1 | Q41: 2199 | R41: 0.2 | S41: 2199 | T41: 439.8 | U41: 1759.2 | V41: 1034 | W41: 1034 | X41: 60 | Y41: 665.2 | Z41: 0.37812642 | AA41: Debit Card | AB41: 45363 | AC41: 3 | AD41: Standard (3-4d) | AE41: 4 | AF41: 0
A42: ORD-100337 | B42: 45361 | C42: 2024 | D42: 45352 | E42: 3 | F42: CUST-00404 | G42: Repeat | H42: Tamil Nadu | I42: TN | J42: South | K42: Chennai | L42: Amazon | M42: P401 | N42: Running Shoes | O42: Footwear | P42: 1 | Q42: 2999 | R42: 0.15 | S42: 2999 | T42: 449.85 | U42: 2549.15 | V42: 1440 | W42: 1440 | X42: 120 | Y42: 989.15 | Z42: 0.3880313 | AA42: COD | AB42: 45362 | AC42: 1 | AD42: Express (≤2d) | AE42: 4 | AF42: 1
A43: ORD-100336 | B43: 45361 | C43: 2024 | D43: 45352 | E43: 3 | F43: CUST-00505 | G43: New | H43: Maharashtra | I43: MH | J43: West | K43: Pune | L43: Website | M43: P404 | N43: Flip Flops | O43: Footwear | P43: 1 | Q43: 399 | R43: 0.1 | S43: 399 | T43: 39.9 | U43: 359.1 | V43: 152 | W43: 152 | X43: 60 | Y43: 147.1 | Z43: 0.4096352 | AA43: UPI | AB43: 45366 | AC43: 5 | AD43: Delayed (5d+) | AE43: 4 | AF43: 0
A44: ORD-100335 | B44: 45361 | C44: 2024 | D44: 45352 | E44: 3 | F44: CUST-00399 | G44: New | H44: Maharashtra | I44: MH | J44: West | K44: Mumbai | L44: Myntra | M44: P303 | N44: Joggers | O44: Apparel | P44: 1 | Q44: 1199 | R44: 0.15 | S44: 1199 | T44: 179.85 | U44: 1019.15 | V44: 492 | W44: 492 | X44: 120 | Y44: 407.15 | Z44: 0.39949958 | AA44: UPI | AB44: 45362 | AC44: 1 | AD44: Express (≤2d) | AE44: 5 | AF44: 1
A45: ORD-100334 | B45: 45361 | C45: 2024 | D45: 45352 | E45: 3 | F45: CUST-00555 | G45: New | H45: Assam | I45: AS | J45: East | K45: Guwahati | L45: Nykaa | M45: P103 | N45: Niacinamide Toner | O45: Skincare | P45: 4 | Q45: 399 | R45: 0.2 | S45: 1596 | T45: 319.2 | U45: 1276.8 | V45: 112 | W45: 448 | X45: 60 | Y45: 768.8 | Z45: 0.60213033 | AA45: UPI | AB45: 45367 | AC45: 6 | AD45: Delayed (5d+) | AE45: 3 | AF45: 0
A46: ORD-100333 | B46: 45361 | C46: 2024 | D46: 45352 | E46: 3 | F46: CUST-00618 | G46: New | H46: Delhi | I46: DL | J46: North | K46: New Delhi | L46: Flipkart | M46: P701 | N46: Ashwagandha Capsules | O46: Wellness | P46: 3 | Q46: 499 | R46: 0 | S46: 1497 | T46: 0 | U46: 1497 | V46: 150 | W46: 450 | X46: 60 | Y46: 987 | Z46: 0.65931864 | AA46: COD | AB46: 45363 | AC46: 2 | AD46: Express (≤2d) | AE46: 5 | AF46: 0
... A55: ORD-100338 | B55: 45362 | C55: 2024 | D55: 45352 | E55: 3 | F55: CUST-00267 | G55: New | H55: Jammu & Kashmir | I55: JK | J55: North | K55: Srinagar | L55: Flipkart | M55: P404 | N55: Flip Flops | O55: Footwear | P55: 2 | Q55: 399 | R55: 0.2 | S55: 798 | T55: 159.6 | U55: 638.4 | V55: 152 | W55: 304 | X55: 120 | Y55: 214.4 | Z55: 0.3358396 | AA55: UPI | AB55: 45368 | AC55: 6 | AD55: Delayed (5d+) | AE55: 4 | AF55: 1
A56: ORD-100347 | B56: 45363 | C56: 2024 | D56: 45352 | E56: 3 | F56: CUST-00927 | G56: New | H56: Karnataka | I56: KA | J56: South | K56: Bengaluru | L56: Website | M56: P103 | N56: Niacinamide Toner | O56: Skincare | P56: 3 | Q56: 399 | R56: 0.25 | S56: 1197 | T56: 299.25 | U56: 897.75 | V56: 112 | W56: 336 | X56: 60 | Y56: 501.75 | Z56: 0.55889724 | AA56: UPI | AB56: 45366 | AC56: 3 | AD56: Standard (3-4d) | AF56: 0
A57: ORD-100346 | B57: 45363 | C57: 2024 | D57: 45352 | E57: 3 | F57: CUST-00677 | G57: Repeat | H57: Telangana | I57: TG | J57: South | K57: Hyderabad | L57: Flipkart | M57: P603 | N57: Smartwatch Strap | O57: Electronics | P57: 2 | Q57: 499 | R57: 0.15 | S57: 998 | T57: 149.7 | U57: 848.3 | V57: 200 | W57: 400 | X57: 60 | Y57: 388.3 | Z57: 0.45773901 | AA57: UPI | AB57: 45367 | AC57: 4 | AD57: Standard (3-4d) | AF57: 0
A58: ORD-100345 | B58: 45363 | C58: 2024 | D58: 45352 | E58: 3 | F58: CUST-00703 | G58: New | H58: Gujarat | I58: GJ | J58: West | K58: Surat | L58: Website | M58: P704 | N58: Multivitamin Gummies | O58: Wellness | P58: 1 | Q58: 699 | R58: 0.2 | S58: 699 | T58: 139.8 | U58: 559.2 | V58: 238 | W58: 238 | X58: 60 | Y58: 261.2 | Z58: 0.46709585 | AA58: UPI | AB58: 45366 | AC58: 3 | AD58: Standard (3-4d) | AF58: 0
A59: ORD-100344 | B59: 45363 | C59: 2024 | D59: 45352 | E59: 3 | F59: CUST-02373 | G59: New | H59: Assam | I59: AS | J59: East | K59: Guwahati | L59: Amazon | M59: P603 | N59: Smartwatch Strap | O59: Electronics | P59: 1 | Q59: 499 | R59: 0.15 | S59: 499 | T59: 74.85 | U59: 424.15 | V59: 200 | W59: 200 | X59: 60 | Y59: 164.15 | Z59: 0.38700931 | AA59: Credit Card | AB59: 45370 | AC59: 7 | AD59: Delayed (5d+) | AE59: 3 | AF59: 0
A60: ORD-100351 | B60: 45364 | C60: 2024 | D60: 45352 | E60: 3 | F60: CUST-00017 | G60: New | H60: Andhra Pradesh | I60: AP | J60: South | K60: Visakhapatnam | L60: Nykaa | M60: P202 | N60: Argan Shampoo | O60: Haircare | P60: 1 | Q60: 449 | R60: 0.15 | S60: 449 | T60: 67.35 | U60: 381.65 | V60: 148 | W60: 148 | X60: 60 | Y60: 173.65 | Z60: 0.45499803 | AA60: Credit Card | AB60: 45367 | AC60: 3 | AD60: Standard (3-4d) | AE60: 5 | AF60: 0
A61: ORD-100350 | B61: 45364 | C61: 2024 | D61: 45352 | E61: 3 | F61: CUST-00231 | G61: New | H61: Haryana | I61: HR | J61: North | K61: Faridabad | L61: Amazon | M61: P304 | N61: Denim Jacket | O61: Apparel | P61: 1 | Q61: 2499 | R61: 0.05 | S61: 2499 | T61: 124.95 | U61: 2374.05 | V61: 1125 | W61: 1125 | X61: 60 | Y61: 1189.05 | Z61: 0.50085297 | AA61: COD | AB61: 45365 | AC61: 1 | AD61: Express (≤2d) | AE61: 5 | AF61: 0
A62: ORD-100349 | B62: 45364 | C62: 2024 | D62: 45352 | E62: 3 | F62: CUST-01026 | G62: New | H62: Himachal Pradesh | I62: HP | J62: North | K62: Shimla | L62: Amazon | M62: P101 | N62: Vitamin C Face Serum | O62: Skincare | P62: 1 | Q62: 599 | R62: 0.15 | S62: 599 | T62: 89.85 | U62: 509.15 | V62: 180 | W62: 180 | X62: 60 | Y62: 269.15 | Z62: 0.52862614 | AA62: UPI | AB62: 45368 | AC62: 4 | AD62: Standard (3-4d) | AE62: 5 | AF62: 0
A63: ORD-100348 | B63: 45364 | C63: 2024 | D63: 45352 | E63: 3 | F63: CUST-01075 | G63: New | H63: Punjab | I63: PB | J63: North | K63: Amritsar | L63: Amazon | M63: P503 | N63: Scented Candle Set | O63: Home & Kitchen | P63: 2 | Q63: 699 | R63: 0.2 | S63: 1398 | T63: 279.6 | U63: 1118.4 | V63: 245 | W63: 490 | X63: 60 | Y63: 568.4 | Z63: 0.50822604 | AA63: Wallet | AB63: 45367 | AC63: 3 | AD63: Standard (3-4d) | AE63: 4 | AF63: 0
A64: ORD-100352 | B64: 45365 | C64: 2024 | D64: 45352 | E64: 3 | F64: CUST-00094 | G64: New | H64: Kerala | I64: KL | J64: South | K64: Thiruvananthapuram | L64: Amazon | M64: P101 | N64: Vitamin C Face Serum | O64: Skincare | P64: 1 | Q64: 599 | R64: 0.25 | S64: 599 | T64: 149.75 | U64: 449.25 | V64: 180 | W64: 180 | X64: 60 | Y64: 209.25 | Z64: 0.46577629 | AA64: UPI | AB64: 45368 | AC64: 3 | AD64: Standard (3-4d) | AF64: 0
A65: ORD-100357 | B65: 45366 | C65: 2024 | D65: 45352 | E65: 3 | F65: CUST-00001 | G65: Repeat | H65: Tamil Nadu | I65: TN | J65: South | K65: Chennai | L65: Myntra | M65: P302 | N65: Linen Kurta | O65: Apparel | P65: 1 | Q65: 1499 | R65: 0.25 | S65: 1499 | T65: 374.75 | U65: 1124.25 | V65: 630 | W65: 630 | X65: 60 | Y65: 434.25 | Z65: 0.38625751 | AA65: UPI | AB65: 45367 | AC65: 1 | AD65: Express (≤2d) | AE65: 4 | AF65: 0
A66: ORD-100356 | B66: 45366 | C66: 2024 | D66: 45352 | E66: 3 | F66: CUST-02787 | G66: New | H66: Kerala | I66: KL | J66: South | K66: Kochi | L66: Website | M66: P203 | N66: Keratin Hair Mask | O66: Haircare | P66: 1 | Q66: 549 | R66: 0.1 | S66: 549 | T66: 54.9 | U66: 494.1 | V66: 170 | W66: 170 | X66: 120 | Y66: 204.1 | Z66: 0.41307428 | AA66: UPI | AB66: 45371 | AC66: 5 | AD66: Delayed (5d+) | AF66: 1
A67: ORD-100355 | B67: 45366 | C67: 2024 | D67: 45352 | E67: 3 | F67: CUST-02170 | G67: New | H67: Telangana | I67: TG | J67: South | K67: Hyderabad | L67: Amazon | M67: P701 | N67: Ashwagandha Capsules | O67: Wellness | P67: 2 | Q67: 499 | R67: 0.1 | S67: 998 | T67: 99.8 | U67: 898.2 | V67: 150 | W67: 300 | X67: 60 | Y67: 538.2 | Z67: 0.5991984 | AA67: COD | AB67: 45369 | AC67: 3 | AD67: Standard (3-4d) | AE67: 3 | AF67: 0
A68: ORD-100354 | B68: 45366 | C68: 2024 | D68: 45352 | E68: 3 | F68: CUST-01765 | G68: New | H68: Jharkhand | I68: JH | J68: East | K68: Ranchi | L68: Amazon | M68: P404 | N68: Flip Flops | O68: Footwear | P68: 2 | Q68: 399 | R68: 0.1 | S68: 798 | T68: 79.8 | U68: 718.2 | V68: 152 | W68: 304 | X68: 120 | Y68: 294.2 | Z68: 0.4096352 | AA68: UPI | AB68: 45370 | AC68: 4 | AD68: Standard (3-4d) | AE68: 4 | AF68: 1
A69: ORD-100353 | B69: 45366 | C69: 2024 | D69: 45352 | E69: 3 | F69: CUST-00556 | G69: New | H69: Rajasthan | I69: RJ | J69: North | K69: Jaipur | L69: Amazon | M69: P305 | N69: Printed Saree | O69: Apparel | P69: 2 | Q69: 1999 | R69: 0.05 | S69: 3998 | T69: 199.9 | U69: 3798.1 | V69: 880 | W69: 1760 | X69: 120 | Y69: 1918.1 | Z69: 0.50501567 | AA69: Credit Card | AB69: 45371 | AC69: 5 | AD69: Delayed (5d+) | AE69: 4 | AF69: 1
A70: ORD-100362 | B70: 45367 | C70: 2024 | D70: 45352 | E70: 3 | F70: CUST-00324 | G70: New | H70: Kerala | I70: KL | J70: South | K70: Kochi | L70: Website | M70: P201 | N70: Onion Hair Oil | O70: Haircare | P70: 2 | Q70: 349 | R70: 0.35 | S70: 698 | T70: 244.3 | U70: 453.7 | V70: 105 | W70: 210 | X70: 60 | Y70: 183.7 | Z70: 0.4048931 | AA70: UPI | AB70: 45371 | AC70: 4 | AD70: Standard (3-4d) | AE70: 4 | AF70: 0
A71: ORD-100361 | B71: 45367 | C71: 2024 | D71: 45352 | E71: 3 | F71: CUST-00243 | G71: New | H71: Andhra Pradesh | I71: AP | J71: South | K71: Vijayawada | L71: Flipkart | M71: P103 | N71: Niacinamide Toner | O71: Skincare | P71: 3 | Q71: 399 | R71: 0.3 | S71: 1197 | T71: 359.1 | U71: 837.9 | V71: 112 | W71: 336 | X71: 60 | Y71: 441.9 | Z71: 0.5273899 | AA71: COD | AB71: 45369 | AC71: 2 | AD71: Express (≤2d) | AE71: 4 | AF71: 0
A72: ORD-100360 | B72: 45367 | C72: 2024 | D72: 45352 | E72: 3 | F72: CUST-00864 | G72: New | H72: Madhya Pradesh | I72: MP | J72: West | K72: Bhopal | L72: Amazon | M72: P104 | N72: Hydrating Face Wash | O72: Skincare | P72: 1 | Q72: 299 | R72: 0.1 | S72: 299 | T72: 29.9 | U72: 269.1 | V72: 90 | W72: 90 | X72: 60 | Y72: 119.1 | Z72: 0.4425864 | AA72: Credit Card | AB72: 45371 | AC72: 4 | AD72: Standard (3-4d) | AE72: 3 | AF72: 0
A73: ORD-100359 | B73: 45367 | C73: 2024 | D73: 45352 | E73: 3 | F73: CUST-00050 | G73: New | H73: Delhi | I73: DL | J73: North | K73: New Delhi | L73: Nykaa | M73: P703 | N73: Green Tea (100 bags) | O73: Wellness | P73: 1 | Q73: 399 | R73: 0.45 | S73: 399 | T73: 179.55 | U73: 219.45 | V73: 128 | W73: 128 | X73: 60 | Y73: 31.45 | Z73: 0.14331283 | AA73: UPI | AB73: 45368 | AC73: 1 | AD73: Express (≤2d) | AE73: 4 | AF73: 0
A74: ORD-100358 | B74: 45367 | C74: 2024 | D74: 45352 | E74: 3 | F74: CUST-00823 | G74: New | H74: Jammu & Kashmir | I74: JK | J74: North | K74: Jammu | L74: Website | M74: P602 | N74: Fast Charger 33W | O74: Electronics | P74: 2 | Q74: 899 | R74: 0 | S74: 1798 | T74: 0 | U74: 1798 | V74: 494 | W74: 988 | X74: 60 | Y74: 750 | Z74: 0.41713014 | AA74: UPI | AB74: 45374 | AC74: 7 | AD74: Delayed (5d+) | AE74: 3 | AF74: 0
A75: ORD-100369 | B75: 45368 | C75: 2024 | D75: 45352 | E75: 3 | F75: CUST-00738 | G75: Repeat | H75: Tamil Nadu | I75: TN | J75: South | K75: Coimbatore | L75: Website | M75: P202 | N75: Argan Shampoo | O75: Haircare | P75: 1 | Q75: 449 | R75: 0.1 | S75: 449 | T75: 44.9 | U75: 404.1 | V75: 148 | W75: 148 | X75: 60 | Y75: 196.1 | Z75: 0.48527592 | AA75: Wallet | AB75: 45372 | AC75: 4 | AD75: Standard (3-4d) | AE75: 4 | AF75: 0
A76: ORD-100368 | B76: 45368 | C76: 2024 | D76: 45352 | E76: 3 | F76: CUST-00004 | G76: New | H76: Tamil Nadu | I76: TN | J76: South | K76: Chennai | L76: Flipkart | M76: P701 | N76: Ashwagandha Capsules | O76: Wellness | P76: 3 | Q76: 499 | R76: 0 | S76: 1497 | T76: 0 | U76: 1497 | V76: 150 | W76: 450 | X76: 60 | Y76: 987 | Z76: 0.65931864 | AA76: UPI | AB76: 45370 | AC76: 2 | AD76: Express (≤2d) | AF76: 0
A77: ORD-100367 | B77: 45368 | C77: 2024 | D77: 45352 | E77: 3 | F77: CUST-01694 | G77: New | H77: Andhra Pradesh | I77: AP | J77: South | K77: Vijayawada | L77: Amazon | M77: P703 | N77: Green Tea (100 bags) | O77: Wellness | P77: 3 | Q77: 399 | R77: 0.35 | S77: 1197 | T77: 418.95 | U77: 778.05 | V77: 128 | W77: 384 | X77: 60 | Y77: 334.05 | Z77: 0.42934259 | AA77: Wallet | AB77: 45371 | AC77: 3 | AD77: Standard (3-4d) | AF77: 0
A78: ORD-100366 | B78: 45368 | C78: 2024 | D78: 45352 | E78: 3 | F78: CUST-01031 | G78: New | H78: Assam | I78: AS | J78: East | K78: Guwahati | L78: Nykaa | M78: P202 | N78: Argan Shampoo | O78: Haircare | P78: 1 | Q78: 449 | R78: 0.05 | S78: 449 | T78: 22.45 | U78: 426.55 | V78: 148 | W78: 148 | X78: 60 | Y78: 218.55 | Z78: 0.51236666 | AA78: Wallet | AB78: 45373 | AC78: 5 | AD78: Delayed (5d+) | AE78: 3 | AF78: 0
A79: ORD-100365 | B79: 45368 | C79: 2024 | D79: 45352 | E79: 3 | F79: CUST-00806 | G79: New | H79: Uttar Pradesh | I79: UP | J79: North | K79: Lucknow | L79: Amazon | M79: P503 | N79: Scented Candle Set | O79: Home & Kitchen | P79: 1 | Q79: 699 | R79: 0.25 | S79: 699 | T79: 174.75 | U79: 524.25 | V79: 245 | W79: 245 | X79: 60 | Y79: 219.25 | Z79: 0.4182165 | AA79: UPI | AB79: 45374 | AC79: 6 | AD79: Delayed (5d+) | AE79: 3 | AF79: 0
A80: ORD-100364 | B80: 45368 | C80: 2024 | D80: 45352 | E80: 3 | F80: CUST-01052 | G80: Repeat | H80: Uttar Pradesh | I80: UP | J80: North | K80: Noida | L80: Flipkart | M80: P303 | N80: Joggers | O80: Apparel | P80: 3 | Q80: 1199 | R80: 0.05 | S80: 3597 | T80: 179.85 | U80: 3417.15 | V80: 492 | W80: 1476 | X80: 60 | Y80: 1881.15 | Z80: 0.55050261 | AA80: UPI | AB80: 45371 | AC80: 3 | AD80: Standard (3-4d) | AE80: 4 | AF80: 0
A81: ORD-100363 | B81: 45368 | C81: 2024 | D81: 45352 | E81: 3 | F81: CUST-00281 | G81: Repeat | H81: Delhi | I81: DL | J81: North | K81: New Delhi | L81: Amazon | M81: P202 | N81: Argan Shampoo | O81: Haircare | P81: 2 | Q81: 449 | R81: 0.1 | S81: 898 | T81: 89.8 | U81: 808.2 | V81: 148 | W81: 296 | X81: 60 | Y81: 452.2 | Z81: 0.55951497 | AA81: COD | AB81: 45369 | AC81: 1 | AD81: Express (≤2d) | AE81: 4 | AF81: 0
A82: ORD-100375 | B82: 45369 | C82: 2024 | D82: 45352 | E82: 3 | F82: CUST-00701 | G82: New | H82: Karnataka | I82: KA | J82: South | K82: Bengaluru | L82: Flipkart | M82: P204 | N82: Anti-Dandruff Conditioner | O82: Haircare | P82: 2 | Q82: 399 | R82: 0.45 | S82: 798 | T82: 359.1 | U82: 438.9 | V82: 136 | W82: 272 | X82: 60 | Y82: 106.9 | Z82: 0.24356345 | AA82: UPI | AB82: 45371 | AC82: 2 | AD82: Express (≤2d) | AE82: 4 | AF82: 0
A83: ORD-100374 | B83: 45369 | C83: 2024 | D83: 45352 | E83: 3 | F83: CUST-00371 | G83: New | H83: Karnataka | I83: KA | J83: South | K83: Mysuru | L83: Nykaa | M83: P704 | N83: Multivitamin Gummies | O83: Wellness | P83: 1 | Q83: 699 | R83: 0.3 | S83: 699 | T83: 209.7 | U83: 489.3 | V83: 238 | W83: 238 | X83: 60 | Y83: 191.3 | Z83: 0.39096669 | AA83: UPI | AB83: 45370 | AC83: 1 | AD83: Express (≤2d) | AE83: 4 | AF83: 0
A84: ORD-100373 | B84: 45369 | C84: 2024 | D84: 45352 | E84: 3 | F84: CUST-02259 | G84: New | H84: Maharashtra | I84: MH | J84: West | K84: Mumbai | L84: Website | M84: P102 | N84: Sunscreen SPF 50 | O84: Skincare | P84: 1 | Q84: 449 | R84: 0 | S84: 449 | T84: 0 | U84: 449 | V84: 144 | W84: 144 | X84: 60 | Y84: 245 | Z84: 0.54565702 | AA84: UPI | AB84: 45374 | AC84: 5 | AD84: Delayed (5d+) | AE84: 3 | AF84: 0
A85: ORD-100372 | B85: 45369 | C85: 2024 | D85: 45352 | E85: 3 | F85: CUST-00975 | G85: New | H85: West Bengal | I85: WB | J85: East | K85: Kolkata | L85: Myntra | M85: P401 | N85: Running Shoes | O85: Footwear | P85: 1 | Q85: 2999 | R85: 0.25 | S85: 2999 | T85: 749.75 | U85: 2249.25 | V85: 1440 | W85: 1440 | X85: 120 | Y85: 689.25 | Z85: 0.30643548 | AA85: UPI | AB85: 45371 | AC85: 2 | AD85: Express (≤2d) | AF85: 1
A86: ORD-100371 | B86: 45369 | C86: 2024 | D86: 45352 | E86: 3 | F86: CUST-00278 | G86: New | H86: Jharkhand | I86: JH | J86: East | K86: Ranchi | L86: Flipkart | M86: P703 | N86: Green Tea (100 bags) | O86: Wellness | P86: 2 | Q86: 399 | R86: 0.4 | S86: 798 | T86: 319.2 | U86: 478.8 | V86: 128 | W86: 256 | X86: 60 | Y86: 162.8 | Z86: 0.34001671 | AA86: UPI | AB86: 45372 | AC86: 3 | AD86: Standard (3-4d) | AE86: 4 | AF86: 0
A87: ORD-100370 | B87: 45369 | C87: 2024 | D87: 45352 | E87: 3 | F87: CUST-00955 | G87: Repeat | H87: Delhi | I87: DL | J87: North | K87: New Delhi | L87: Myntra | M87: P301 | N87: Cotton Oversized T-Shirt | O87: Apparel | P87: 1 | Q87: 799 | R87: 0.1 | S87: 799 | T87: 79.9 | U87: 719.1 | V87: 320 | W87: 320 | X87: 60 | Y87: 339.1 | Z87: 0.47156167 | AA87: Debit Card | AB87: 45370 | AC87: 1 | AD87: Express (≤2d) | AE87: 5 | AF87: 0
A88: ORD-100379 | B88: 45370 | C88: 2024 | D88: 45352 | E88: 3 | F88: CUST-00414 | G88: New | H88: Odisha | I88: OD | J88: East | K88: Bhubaneswar | L88: Myntra | M88: P301 | N88: Cotton Oversized T-Shirt | O88: Apparel | P88: 2 | Q88: 799 | R88: 0.1 | S88: 1598 | T88: 159.8 | U88: 1438.2 | V88: 320 | W88: 640 | X88: 60 | Y88: 738.2 | Z88: 0.51328049 | AA88: UPI | AB88: 45375 | AC88: 5 | AD88: Delayed (5d+) | AE88: 3 | AF88: 0
A89: ORD-100378 | B89: 45370 | C89: 2024 | D89: 45352 | E89: 3 | F89: CUST-02611 | G89: New | H89: Madhya Pradesh | I89: MP | J89: West | K89: Indore | L89: Flipkart | M89: P104 | N89: Hydrating Face Wash | O89: Skincare | P89: 3 | Q89: 299 | R89: 0 | S89: 897 | T89: 0 | U89: 897 | V89: 90 | W89: 270 | X89: 60 | Y89: 567 | Z89: 0.63210702 | AA89: UPI | AB89: 45374 | AC89: 4 | AD89: Standard (3-4d) | AE89: 3 | AF89: 0
A90: ORD-100377 | B90: 45370 | C90: 2024 | D90: 45352 | E90: 3 | F90: CUST-00224 | G90: New | H90: Gujarat | I90: GJ | J90: West | K90: Surat | L90: Website | M90: P704 | N90: Multivitamin Gummies | O90: Wellness | P90: 3 | Q90: 699 | R90: 0.15 | S90: 2097 | T90: 314.55 | U90: 1782.45 | V90: 238 | W90: 714 | X90: 60 | Y90: 1008.45 | Z90: 0.56576622 | AA90: UPI | AB90: 45373 | AC90: 3 | AD90: Standard (3-4d) | AF90: 0
A91: ORD-100376 | B91: 45370 | C91: 2024 | D91: 45352 | E91: 3 | F91: CUST-01248 | G91: New | H91: Himachal Pradesh | I91: HP | J91: North | K91: Shimla | L91: Nykaa | M91: P203 | N91: Keratin Hair Mask | O91: Haircare | P91: 1 | Q91: 549 | R91: 0.1 | S91: 549 | T91: 54.9 | U91: 494.1 | V91: 170 | W91: 170 | X91: 120 | Y91: 204.1 | Z91: 0.41307428 | AA91: UPI | AB91: 45375 | AC91: 5 | AD91: Delayed (5d+) | AE91: 3 | AF91: 1
A92: ORD-100383 | B92: 45371 | C92: 2024 | D92: 45352 | E92: 3 | F92: CUST-03084 | G92: New | H92: Tamil Nadu | I92: TN | J92: South | K92: Chennai | L92: Flipkart | M92: P602 | N92: Fast Charger 33W | O92: Electronics | P92: 1 | Q92: 899 | R92: 0.05 | S92: 899 | T92: 44.95 | U92: 854.05 | V92: 494 | W92: 494 | X92: 60 | Y92: 300.05 | Z92: 0.35132603 | AA92: UPI | AB92: 45375 | AC92: 4 | AD92: Standard (3-4d) | AF92: 0
A93: ORD-100382 | B93: 45371 | C93: 2024 | D93: 45352 | E93: 3 | F93: CUST-01239 | G93: New | H93: Telangana | I93: TG | J93: South | K93: Hyderabad | L93: Amazon | M93: P201 | N93: Onion Hair Oil | O93: Haircare | P93: 1 | Q93: 349 | R93: 0.3 | S93: 349 | T93: 104.7 | U93: 244.3 | V93: 105 | W93: 105 | X93: 60 | Y93: 79.3 | Z93: 0.3246009 | AA93: UPI | AB93: 45373 | AC93: 2 | AD93: Express (≤2d) | AE93: 5 | AF93: 0
A94: ORD-100381 | B94: 45371 | C94: 2024 | D94: 45352 | E94: 3 | F94: CUST-00015 | G94: Repeat | H94: Madhya Pradesh | I94: MP | J94: West | K94: Indore | L94: Nykaa | M94: P103 | N94: Niacinamide Toner | O94: Skincare | P94: 1 | Q94: 399 | R94: 0.2 | S94: 399 | T94: 79.8 | U94: 319.2 | V94: 112 | W94: 112 | X94: 60 | Y94: 147.2 | Z94: 0.46115288 | AA94: COD | AB94: 45373 | AC94: 2 | AD94: Express (≤2d) | AE94: 3 | AF94: 0
A95: ORD-100380 | B95: 45371 | C95: 2024 | D95: 45352 | E95: 3 | F95: CUST-01407 | G95: Repeat | H95: Gujarat | I95: GJ | J95: West | K95: Surat | L95: Flipkart | M95: P701 | N95: Ashwagandha Capsules | O95: Wellness | P95: 2 | Q95: 499 | R95: 0 | S95: 998 | T95: 0 | U95: 998 | V95: 150 | W95: 300 | X95: 60 | Y95: 638 | Z95: 0.63927856 | AA95: COD | AB95: 45374 | AC95: 3 | AD95: Standard (3-4d) | AF95: 0
A96: ORD-100388 | B96: 45372 | C96: 2024 | D96: 45352 | E96: 3 | F96: CUST-01125 | G96: New | H96: Goa | I96: GA | J96: West | K96: Panaji | L96: Myntra | M96: P403 | N96: Kolhapuri Sandals | O96: Footwear | P96: 1 | Q96: 999 | R96: 0.1 | S96: 999 | T96: 99.9 | U96: 899.1 | V96: 400 | W96: 400 | X96: 60 | Y96: 439.1 | Z96: 0.48837727 | AA96: UPI | AB96: 45374 | AC96: 2 | AD96: Express (≤2d) | AE96: 4 | AF96: 0
A97: ORD-100387 | B97: 45372 | C97: 2024 | D97: 45352 | E97: 3 | F97: CUST-01031 | G97: Repeat | H97: Odisha | I97: OD | J97: East | K97: Bhubaneswar | L97: Amazon | M97: P403 | N97: Kolhapuri Sandals | O97: Footwear | P97: 1 | Q97: 999 | R97: 0.1 | S97: 999 | T97: 99.9 | U97: 899.1 | V97: 400 | W97: 400 | X97: 60 | Y97: 439.1 | Z97: 0.48837727 | AA97: Debit Card | AB97: 45378 | AC97: 6 | AD97: Delayed (5d+) | AE97: 4 | AF97: 0
A98: ORD-100386 | B98: 45372 | C98: 2024 | D98: 45352 | E98: 3 | F98: CUST-02584 | G98: New | H98: Madhya Pradesh | I98: MP | J98: West | K98: Indore | L98: Website | M98: P402 | N98: Casual Sneakers | O98: Footwear | P98: 1 | Q98: 2199 | R98: 0.15 | S98: 2199 | T98: 329.85 | U98: 1869.15 | V98: 1034 | W98: 1034 | X98: 60 | Y98: 775.15 | Z98: 0.41470722 | AA98: COD | AB98: 45378 | AC98: 6 | AD98: Delayed (5d+) | AE98: 3 | AF98: 0
A99: ORD-100385 | B99: 45372 | C99: 2024 | D99: 45352 | E99: 3 | F99: CUST-00437 | G99: New | H99: Himachal Pradesh | I99: HP | J99: North | K99: Shimla | L99: Website | M99: P202 | N99: Argan Shampoo | O99: Haircare | P99: 1 | Q99: 449 | R99: 0.1 | S99: 449 | T99: 44.9 | U99: 404.1 | V99: 148 | W99: 148 | X99: 60 | Y99: 196.1 | Z99: 0.48527592 | AA99: Debit Card | AB99: 45375 | AC99: 3 | AD99: Standard (3-4d) | AE99: 4 | AF99: 0
A100: ORD-100384 | B100: 45372 | C100: 2024 | D100: 45352 | E100: 3 | F100: CUST-01407 | G100: Repeat | H100: Himachal Pradesh | I100: HP | J100: North | K100: Shimla | L100: Flipkart | M100: P403 | N100: Kolhapuri Sandals | O100: Footwear | P100: 3 | Q100: 999 | R100: 0.05 | S100: 2997 | T100: 149.85 | U100: 2847.15 | V100: 400 | W100: 1200 | X100: 60 | Y100: 1587.15 | Z100: 0.55745219 | AA100: COD | AB100: 45374 | AC100: 2 | AD100: Express (≤2d) | AE100: 3 | AF100: 0
A101: ORD-100395 | B101: 45373 | C101: 2024 | D101: 45352 | E101: 3 | F101: CUST-00457 | G101: Repeat | H101: Tamil Nadu | I101: TN | J101: South | K101: Chennai | L101: Flipkart | M101: P402 | N101: Casual Sneakers | O101: Footwear | P101: 1 | Q101: 2199 | R101: 0.3 | S101: 2199 | T101: 659.7 | U101: 1539.3 | V101: 1034 | W101: 1034 | X101: 60 | Y101: 445.3 | Z101: 0.28928734 | AA101: Credit Card | AB101: 45376 | AC101: 3 | AD101: Standard (3-4d) | AE101: 5 | AF101: 0
A102: ORD-100394 | B102: 45373 | C102: 2024 | D102: 45352 | E102: 3 | F102: CUST-00142 | G102: New | H102: Kerala | I102: KL | J102: South | K102: Thiruvananthapuram | L102: Amazon | M102: P204 | N102: Anti-Dandruff Conditioner | O102: Haircare | P102: 1 | Q102: 399 | R102: 0.45 | S102: 399 | T102: 179.55 | U102: 219.45 | V102: 136 | W102: 136 | X102: 60 | Y102: 23.45 | Z102: 0.10685805 | AA102: Debit Card | AB102: 45376 | AC102: 3 | AD102: Standard (3-4d) | AF102: 0
A103: ORD-100393 | B103: 45373 | C103: 2024 | D103: 45352 | E103: 3 | F103: CUST-01005 | G103: New | H103: Telangana | I103: TG | J103: South | K103: Hyderabad | L103: Nykaa | M103: P201 | N103: Onion Hair Oil | O103: Haircare | P103: 1 | Q103: 349 | R103: 0.3 | S103: 349 | T103: 104.7 | U103: 244.3 | V103: 105 | W103: 105 | X103: 60 | Y103: 79.3 | Z103: 0.3246009 | AA103: COD | AB103: 45375 | AC103: 2 | AD103: Express (≤2d) | AF103: 0
A104: ORD-100392 | B104: 45373 | C104: 2024 | D104: 45352 | E104: 3 | F104: CUST-00569 | G104: New | H104: Madhya Pradesh | I104: MP | J104: West | K104: Bhopal | L104: Nykaa | M104: P102 | N104: Sunscreen SPF 50 | O104: Skincare | P104: 1 | Q104: 449 | R104: 0.1 | S104: 449 | T104: 44.9 | U104: 404.1 | V104: 144 | W104: 144 | X104: 60 | Y104: 200.1 | Z104: 0.49517446 | AA104: UPI | AB104: 45376 | AC104: 3 | AD104: Standard (3-4d) | AF104: 0
A105: ORD-100391 | B105: 45373 | C105: 2024 | D105: 45352 | E105: 3 | F105: CUST-02681 | G105: New | H105: Haryana | I105: HR | J105: North | K105: Faridabad | L105: Amazon | M105: P103 | N105: Niacinamide Toner | O105: Skincare | P105: 3 | Q105: 399 | R105: 0.2 | S105: 1197 | T105: 239.4 | U105: 957.6 | V105: 112 | W105: 336 | X105: 60 | Y105: 561.6 | Z105: 0.58646617 | AA105: Credit Card | AB105: 45374 | AC105: 1 | AD105: Express (≤2d) | AE105: 3 | AF105: 0
A106: ORD-100390 | B106: 45373 | C106: 2024 | D106: 45352 | E106: 3 | F106: CUST-00249 | G106: New | H106: Rajasthan | I106: RJ | J106: North | K106: Udaipur | L106: Flipkart | M106: P503 | N106: Scented Candle Set | O106: Home & Kitchen | P106: 1 | Q106: 699 | R106: 0.15 | S106: 699 | T106: 104.85 | U106: 594.15 | V106: 245 | W106: 245 | X106: 60 | Y106: 289.15 | Z106: 0.48666162 | AA106: UPI | AB106: 45377 | AC106: 4 | AD106: Standard (3-4d) | AE106: 3 | AF106: 0
A107: ORD-100389 | B107: 45373 | C107: 2024 | D107: 45352 | E107: 3 | F107: CUST-00421 | G107: New | H107: Uttarakhand | I107: UK | J107: North | K107: Dehradun | L107: Amazon | M107: P704 | N107: Multivitamin Gummies | O107: Wellness | P107: 1 | Q107: 699 | R107: 0.25 | S107: 699 | T107: 174.75 | U107: 524.25 | V107: 238 | W107: 238 | X107: 60 | Y107: 226.25 | Z107: 0.43156891 | AA107: Debit Card | AB107: 45378 | AC107: 5 | AD107: Delayed (5d+) | AF107: 0
A108: ORD-100399 | B108: 45374 | C108: 2024 | D108: 45352 | E108: 3 | F108: CUST-01298 | G108: New | H108: Telangana | I108: TG | J108: South | K108: Hyderabad | L108: Nykaa | M108: P203 | N108: Keratin Hair Mask | O108: Haircare | P108: 1 | Q108: 549 | R108: 0.15 | S108: 549 | T108: 82.35 | U108: 466.65 | V108: 170 | W108: 170 | X108: 60 | Y108: 236.65 | Z108: 0.50712525 | AA108: UPI | AB108: 45376 | AC108: 2 | AD108: Express (≤2d) | AE108: 5 | AF108: 0
A109: ORD-100398 | B109: 45374 | C109: 2024 | D109: 45352 | E109: 3 | F109: CUST-00817 | G109: New | H109: Assam | I109: AS | J109: East | K109: Guwahati | L109: Website | M109: P501 | N109: Copper Water Bottle | O109: Home & Kitchen | P109: 2 | Q109: 899 | R109: 0 | S109: 1798 | T109: 0 | U109: 1798 | V109: 378 | W109: 756 | X109: 60 | Y109: 982 | Z109: 0.5461624 | AA109: UPI | AB109: 45380 | AC109: 6 | AD109: Delayed (5d+) | AF109: 0
...

Sheet Dashboard
B1: SHOPKART D2C | E-COMMERCE SALES & CUSTOMER ANALYTICS DASHBOARD (2024–2025)
B3: ="Showing: "&IF(selYear="All","2024–2025",selYear)&" • Region: "&selRegion&" • Channel: "&selChannel&" • Category: "&selCategory&" • "&TEXT(Analysis!B14,"#,##0")&" orders" -> Showing: 2024–2025 • Region: All • Channel: All • Category: All • 4,833 orders
D4: ▼ YEAR | H4: ▼REGION | L4: ▼SALES CHANNEL | P4: ▼CATEGORY | T4: ▼MAP METRIC | X4: ▼TOP N PRODUCTS
D5: All | H5: All | L5: All | P5: All | T5: Return Rate % | X5: 15
B7: REVENUE | E7: PROFIT | H7: PROFIT MARGIN | K7: ORDERS | N7: AVG ORDER VALUE | Q7: AVG RATING ★ | T7: RETURN RATE | W7: AVG DELIVERY (DAYS)
B8: =Analysis!B11 -> 5156142.5 | E8: =Analysis!B12 -> 2083254.5 | H8: =Analysis!B13 -> 0.40403353 | K8: =Analysis!B14 -> 4833 | N8: =Analysis!B16 -> 1066.8617 | Q8: =Analysis!B17 -> 3.9144603 | T8: =Analysis!B18 -> 0.10407614 | W8: =Analysis!B19 -> 3.3279537
B10: =IF(Analysis!E11="","",Analysis!E11) -> 0.28487949 | E10: =Analysis!E12 -> 0.29280918 | H10: =Analysis!E13 -> 0.002484889 | K10: =Analysis!E14 -> 0.27328316 | N10: =Analysis!E16 -> 0.0091074218 | Q10: =Analysis!E17 -> -0.010029005 | T10: =Analysis!E18 -> -0.0081745143 | W10: =Analysis!E19 -> -0.0048459779
B12: ▲▼ = 2025 vs 2024 for the same Region/Channel/Category
B13: SALES TREND
B31: PRODUCT & CHANNEL MIX
B49: GEOGRAPHY – INDIA TILE MAP & MARKETING EFFICIENCY
B50: ="India map – "&selMetric&" " -> India map – Return Rate %
G51: =INDEX(Analysis!$L$122:$L$144,MATCH("JK",Analysis!$B$122:$B$144,0)) -> 15.625
F52: =INDEX(Analysis!$L$122:$L$144,MATCH("PB",Analysis!$B$122:$B$144,0)) -> 11.363636 | G52: =INDEX(Analysis!$L$122:$L$144,MATCH("HP",Analysis!$B$122:$B$144,0)) -> 20 | H52: =INDEX(Analysis!$L$122:$L$144,MATCH("UK",Analysis!$B$122:$B$144,0)) -> 1.5151515
E53: =INDEX(Analysis!$L$122:$L$144,MATCH("RJ",Analysis!$B$122:$B$144,0)) -> 9.9236641 | F53: =INDEX(Analysis!$L$122:$L$144,MATCH("HR",Analysis!$B$122:$B$144,0)) -> 9.1954023 | G53: =INDEX(Analysis!$L$122:$L$144,MATCH("DL",Analysis!$B$122:$B$144,0)) -> 9.3150685 | H53: =INDEX(Analysis!$L$122:$L$144,MATCH("UP",Analysis!$B$122:$B$144,0)) -> 10.364146 | I53: =INDEX(Analysis!$L$122:$L$144,MATCH("BR",Analysis!$B$122:$B$144,0)) -> 8.3333333 | K53: =INDEX(Analysis!$L$122:$L$144,MATCH("AS",Analysis!$B$122:$B$144,0)) -> 12.987013
D54: =INDEX(Analysis!$L$122:$L$144,MATCH("GJ",Analysis!$B$122:$B$144,0)) -> 14.114114 | F54: =INDEX(Analysis!$L$122:$L$144,MATCH("MP",Analysis!$B$122:$B$144,0)) -> 12.062257 | G54: =INDEX(Analysis!$L$122:$L$144,MATCH("CG",Analysis!$B$122:$B$144,0)) -> 15.584416 | H54: =INDEX(Analysis!$L$122:$L$144,MATCH("JH",Analysis!$B$122:$B$144,0)) -> 12.345679 | I54: =INDEX(Analysis!$L$122:$L$144,MATCH("WB",Analysis!$B$122:$B$144,0)) -> 8.3601286
E55: =INDEX(Analysis!$L$122:$L$144,MATCH("MH",Analysis!$B$122:$B$144,0)) -> 10.344828 | F55: =INDEX(Analysis!$L$122:$L$144,MATCH("TG",Analysis!$B$122:$B$144,0)) -> 11.067194 | H55: =INDEX(Analysis!$L$122:$L$144,MATCH("OD",Analysis!$B$122:$B$144,0)) -> 10.11236
E56: =INDEX(Analysis!$L$122:$L$144,MATCH("GA",Analysis!$B$122:$B$144,0)) -> 8.6206897 | F56: =INDEX(Analysis!$L$122:$L$144,MATCH("KA",Analysis!$B$122:$B$144,0)) -> 7.3417722 | G56: =INDEX(Analysis!$L$122:$L$144,MATCH("AP",Analysis!$B$122:$B$144,0)) -> 11.27451
F57: =INDEX(Analysis!$L$122:$L$144,MATCH("KL",Analysis!$B$122:$B$144,0)) -> 8.7912088 | G57: =INDEX(Analysis!$L$122:$L$144,MATCH("TN",Analysis!$B$122:$B$144,0)) -> 11.111111
C58: ="🏆 Highest "&selMetric&": "&INDEX(Analysis!$A$122:$A$144,MATCH(MAX(Analysis!$L$122:$L$144),Analysis!$L$122:$L$144,0))&" ⚠ Lowest "&selMetric&": "&INDEX(Analysis!$A$122:$A$144,MATCH(MIN(Analysis!$L$122:$L$144),Analysis!$L$122:$L$144,0)) -> 🏆 Highest Return Rate %: Himachal Pradesh ⚠ Lowest Return Rate %: Uttarakhand | M58: =IF(OR(selChannel<>"All",selCategory<>"All"),"Select All channels and categories for overall advertising analysis.",IFERROR("Across states, each additional ₹1 of ad spend is associated with ₹"&TEXT(Analysis!B147,"0.00")&" of revenue change. R² = "&TEXT(Analysis!B149,"0.00")&"; r = "&TEXT(Analysis!B150,"0.00")&". Region filter ignored.","Insufficient data for advertising analysis.")) -> Across states, each additional ₹1 of ad spend is associated with ₹4.38 of revenue change. R² = 0.99; r = 0.99. Region filter ignored.
B59: CUSTOMER EXPERIENCE – DELIVERY, RATINGS & RETURNS
B81: PROFITABILITY – DISCOUNTS & PAYMENT BEHAVIOUR
B101: =IF(OR(Analysis!B190="",Analysis!B191=""),"Insufficient data to estimate the discount–margin relationship.","Each +10 percentage points of discount is associated with "&TEXT(Analysis!B190*10,"+0.0;-0.0;0.0")&" margin points (R² "&TEXT(Analysis!B191,"0.00")&").") -> Each +10 percentage points of discount is associated with -10.5 margin points (R² 0.59).
B102: CATEGORY - MONTH & CHANNEL SCORECARD
B103: Category | D103: Jan | E103: Feb | F103: Mar | G103: Apr | H103: May | I103: Jun | J103: Jul | K103: Aug | L103: Sep | M103: Oct | N103: Nov | O103: Dec | Q103: =Analysis!A79 -> Channel | R103: =Analysis!B79 -> Revenue | S103: =Analysis!H79 -> Share % | T103: =Analysis!D79 -> Margin % | U103: Return % | V103: Rating | W103: Avg Disc %
B104: Skincare | D104: =Analysis!B96 -> 56494.2 | E104: =Analysis!C96 -> 44310.05 | F104: =Analysis!D96 -> 43426.05 | G104: =Analysis!E96 -> 56952.45 | H104: =Analysis!F96 -> 40215.3 | I104: =Analysis!G96 -> 42008.25 | J104: =Analysis!H96 -> 45046.95 | K104: =Analysis!I96 -> 47870 | ... O104: =Analysis!M96 -> 51003.35 | Q104: =Analysis!A80 -> Amazon | R104: =Analysis!B80 -> 1447389.7 | S104: =Analysis!H80 -> 0.28071174 | T104: =Analysis!D80 -> 0.38105612 | U104: =Analysis!F80 -> 0.11072423 | V104: =Analysis!G80 -> 3.9414683 | W104: =Analysis!I80 -> 0.23660599
B105: Haircare | C105: Haircare | D105: =Analysis!B97 -> 24364.15 | E105: =Analysis!C97 -> 27617.2 | F105: =Analysis!D97 -> 25422.3 | G105: =Analysis!E97 -> 34087.5 | H105: =Analysis!F97 -> 27512.8 | I105: =Analysis!G97 -> 32450.4 | J105: =Analysis!H97 -> 30616.3 | K105: =Analysis!I97 -> 38731.9 | ... O105: =Analysis!M97 -> 45629.8 | Q105: =Analysis!A81 -> Flipkart | R105: =Analysis!B81 -> 1180727.3 | S105: =Analysis!H81 -> 0.22899432 | T105: =Analysis!D81 -> 0.39024704 | U105: =Analysis!F81 -> 0.094405594 | V105: =Analysis!G81 -> 3.9167658 | W105: =Analysis!I81 -> 0.22718366
B106: Apparel | C106: Apparel | D106: =Analysis!B98 -> 136340 | E106: =Analysis!C98 -> 86478.95 | F106: =Analysis!D98 -> 140923.35 | G106: =Analysis!E98 -> 115921.2 | H106: =Analysis!F98 -> 98493.35 | I106: =Analysis!G98 -> 117220.7 | J106: =Analysis!H98 -> 99421.05 | K106: =Analysis!I98 -> 82505.7 | ... O106: =Analysis!M98 -> 117284.95 | Q106: =Analysis!A82 -> Website | R106: =Analysis!B82 -> 914734.45 | S106: =Analysis!H82 -> 0.17740675 | T106: =Analysis!D82 -> 0.42344688 | U106: =Analysis!F82 -> 0.094951923 | V106: =Analysis!G82 -> 3.8010471 | W106: =Analysis!I82 -> 0.17940355
B107: Footwear | C107: Footwear | D107: =Analysis!B99 -> 93629.8 | E107: =Analysis!C99 -> 52408 | F107: =Analysis!D99 -> 68164.9 | G107: =Analysis!E99 -> 62253.4 | H107: =Analysis!F99 -> 64323.8 | I107: =Analysis!G99 -> 73525.15 | J107: =Analysis!H99 -> 70950.35 | K107: =Analysis!I99 -> 76241 | ... O107: =Analysis!M99 -> 91036.95 | Q107: =Analysis!A83 -> Myntra | R107: =Analysis!B83 -> 1162695.9 | S107: =Analysis!H83 -> 0.22549723 | T107: =Analysis!D83 -> 0.41746932 | U107: =Analysis!F83 -> 0.14049587 | V107: =Analysis!G83 -> 4 | W107: =Analysis!I83 -> 0.1975935
B108: Home & Kitchen | C108: Home & Kitchen | D108: =Analysis!B100 -> 57522.55 | E108: =Analysis!C100 -> 35114.3 | F108: =Analysis!D100 -> 57594.35 | G108: =Analysis!E100 -> 61113.65 | H108: =Analysis!F100 -> 41554 | I108: =Analysis!G100 -> 34798.3 | J108: =Analysis!H100 -> 29631.65 | K108: =Analysis!I100 -> 36695.1 | ... O108: =Analysis!M100 -> 42850.7 | Q108: =Analysis!A84 -> Nykaa | R108: =Analysis!B84 -> 450595.1 | S108: =Analysis!H84 -> 0.087389963 | T108: =Analysis!D84 -> 0.43988738 | U108: =Analysis!F84 -> 0.079136691 | V108: =Analysis!G84 -> 3.8969697 | W108: =Analysis!I84 -> 0.24173387
B109: Electronics | C109: Electronics | D109: =Analysis!B101 -> 41145.15 | E109: =Analysis!C101 -> 20743.45 | F109: =Analysis!D101 -> 30318.35 | G109: =Analysis!E101 -> 26749.7 | H109: =Analysis!F101 -> 32747.55 | I109: =Analysis!G101 -> 36285.25 | J109: =Analysis!H101 -> 39309.75 | K109: =Analysis!I101 -> 46878.75 | ... O109: =Analysis!M101 -> 28466.5
B110: Wellness | C110: Wellness | D110: =Analysis!B102 -> 61986.55 | E110: =Analysis!C102 -> 21309.15 | F110: =Analysis!D102 -> 48593.4 | G110: =Analysis!E102 -> 56784.5 | H110: =Analysis!F102 -> 36962.8 | I110: =Analysis!G102 -> 55240.2 | J110: =Analysis!H102 -> 46515.3 | K110: =Analysis!I102 -> 50153.7 | ... O110: =Analysis!M102 -> 68061.95
B112: TOP PRODUCTS PERFORMANCE & LEADERBOARD
B113: # | C113: Product | F113: Category | H113: Revenue | J113: Profit | K113: Margin % | L113: Units | M113: Rating | N113: Return % | O113: 24-Month Revenue Trend | R113: Monthly revenue
B114: =IF(Analysis!$K195,Analysis!A195,"") -> 1 | C114: =IF(Analysis!$K195,Analysis!B195,"") -> Linen Kurta | F114: =IF(Analysis!$K195,Analysis!C195,"") -> Apparel | H114: =IF(Analysis!$K195,Analysis!D195,"") -> 361333.95 | J114: =IF(Analysis!$K195,Analysis!E195,"") -> 111673.95 | K114: =IF(Analysis!$K195,Analysis!F195,"") -> 0.30906022 | L114: =IF(Analysis!$K195,Analysis!G195,"") -> 374 | M114: =IF(Analysis!$K195,Analysis!H195,"") -> 3.8407643 | N114: =IF(Analysis!$K195,Analysis!I195,"") -> 0.125
B115: =IF(Analysis!$K196,Analysis!A196,"") -> 2 | C115: =IF(Analysis!$K196,Analysis!B196,"") -> Running Shoes | F115: =IF(Analysis!$K196,Analysis!C196,"") -> Footwear | H115: =IF(Analysis!$K196,Analysis!D196,"") -> 346234.55 | J115: =IF(Analysis!$K196,Analysis!E196,"") -> 118354.55 | K115: =IF(Analysis!$K196,Analysis!F196,"") -> 0.34183345 | L115: =IF(Analysis!$K196,Analysis!G196,"") -> 153 | M115: =IF(Analysis!$K196,Analysis!H196,"") -> 3.8536585 | N115: =IF(Analysis!$K196,Analysis!I196,"") -> 0.18867925
B116: =IF(Analysis!$K197,Analysis!A197,"") -> 3 | C116: =IF(Analysis!$K197,Analysis!B197,"") -> Denim Jacket | F116: =IF(Analysis!$K197,Analysis!C197,"") -> Apparel | H116: =IF(Analysis!$K197,Analysis!D197,"") -> 310500.75 | J116: =IF(Analysis!$K197,Analysis!E197,"") -> 153795.75 | K116: =IF(Analysis!$K197,Analysis!F197,"") -> 0.49531523 | L116: =IF(Analysis!$K197,Analysis!G197,"") -> 133 | M116: =IF(Analysis!$K197,Analysis!H197,"") -> 3.9864865 | N116: =IF(Analysis!$K197,Analysis!I197,"") -> 0.18
B117: =IF(Analysis!$K198,Analysis!A198,"") -> 4 | C117: =IF(Analysis!$K198,Analysis!B198,"") -> Joggers | F117: =IF(Analysis!$K198,Analysis!C198,"") -> Apparel | H117: =IF(Analysis!$K198,Analysis!D198,"") -> 301908.2 | J117: =IF(Analysis!$K198,Analysis!E198,"") -> 142644.2 | K117: =IF(Analysis!$K198,Analysis!F198,"") -> 0.47247541 | L117: =IF(Analysis!$K198,Analysis!G198,"") -> 297 | M117: =IF(Analysis!$K198,Analysis!H198,"") -> 3.9007092 | N117: =IF(Analysis!$K198,Analysis!I198,"") -> 0.14659686
B118: =IF(Analysis!$K199,Analysis!A199,"") -> 5 | C118: =IF(Analysis!$K199,Analysis!B199,"") -> Printed Saree | F118: =IF(Analysis!$K199,Analysis!C199,"") -> Apparel | H118: =IF(Analysis!$K199,Analysis!D199,"") -> 253073.4 | J118: =IF(Analysis!$K199,Analysis!E199,"") -> 123033.4 | K118: =IF(Analysis!$K199,Analysis!F199,"") -> 0.48615698 | L118: =IF(Analysis!$K199,Analysis!G199,"") -> 140 | M118: =IF(Analysis!$K199,Analysis!H199,"") -> 4 | N118: =IF(Analysis!$K199,Analysis!I199,"") -> 0.21276596
B119: =IF(Analysis!$K200,Analysis!A200,"") -> 6 | C119: =IF(Analysis!$K200,Analysis!B200,"") -> Kolhapuri Sandals | F119: =IF(Analysis!$K200,Analysis!C200,"") -> Footwear | H119: =IF(Analysis!$K200,Analysis!D200,"") -> 246453.3 | J119: =IF(Analysis!$K200,Analysis!E200,"") -> 124153.3 | K119: =IF(Analysis!$K200,Analysis!F200,"") -> 0.50375994 | L119: =IF(Analysis!$K200,Analysis!G200,"") -> 272 | M119: =IF(Analysis!$K200,Analysis!H200,"") -> 4.0273973 | N119: =IF(Analysis!$K200,Analysis!I200,"") -> 0.14795918
B120: =IF(Analysis!$K201,Analysis!A201,"") -> 7 | C120: =IF(Analysis!$K201,Analysis!B201,"") -> Casual Sneakers | F120: =IF(Analysis!$K201,Analysis!C201,"") -> Footwear | H120: =IF(Analysis!$K201,Analysis!D201,"") -> 223858.2 | J120: =IF(Analysis!$K201,Analysis!E201,"") -> 75406.2 | K120: =IF(Analysis!$K201,Analysis!F201,"") -> 0.33684806 | L120: =IF(Analysis!$K201,Analysis!G201,"") -> 138 | M120: =IF(Analysis!$K201,Analysis!H201,"") -> 3.9206349 | N120: =IF(Analysis!$K201,Analysis!I201,"") -> 0.10344828
B121: =IF(Analysis!$K202,Analysis!A202,"") -> 8 | C121: =IF(Analysis!$K202,Analysis!B202,"") -> Cotton Oversized T-Shirt | F121: =IF(Analysis!$K202,Analysis!C202,"") -> Apparel | H121: =IF(Analysis!$K202,Analysis!D202,"") -> 206421.65 | J121: =IF(Analysis!$K202,Analysis!E202,"") -> 104021.65 | K121: =IF(Analysis!$K202,Analysis!F202,"") -> 0.503928 | L121: =IF(Analysis!$K202,Analysis!G202,"") -> 275 | M121: =IF(Analysis!$K202,Analysis!H202,"") -> 4.006993 | N121: =IF(Analysis!$K202,Analysis!I202,"") -> 0.15384615
B122: =IF(Analysis!$K203,Analysis!A203,"") -> 9 | C122: =IF(Analysis!$K203,Analysis!B203,"") -> Whey Protein 1kg | F122: =IF(Analysis!$K203,Analysis!C203,"") -> Wellness | H122: =IF(Analysis!$K203,Analysis!D203,"") -> 202426.95 | J122: =IF(Analysis!$K203,Analysis!E203,"") -> 4401.95 | K122: =IF(Analysis!$K203,Analysis!F203,"") -> 0.021745869 | L122: =IF(Analysis!$K203,Analysis!G203,"") -> 145 | M122: =IF(Analysis!$K203,Analysis!H203,"") -> 3.8269231 | N122: =IF(Analysis!$K203,Analysis!I203,"") -> 0.11267606
B123: =IF(Analysis!$K204,Analysis!A204,"") -> 10 | C123: =IF(Analysis!$K204,Analysis!B204,"") -> Cotton Bedsheet | F123: =IF(Analysis!$K204,Analysis!C204,"") -> Home & Kitchen | H123: =IF(Analysis!$K204,Analysis!D204,"") -> 193291.2 | J123: =IF(Analysis!$K204,Analysis!E204,"") -> 93946.2 | K123: =IF(Analysis!$K204,Analysis!F204,"") -> 0.48603454 | L123: =IF(Analysis!$K204,Analysis!G204,"") -> 157 | M123: =IF(Analysis!$K204,Analysis!H204,"") -> 3.9444444 | N123: =IF(Analysis!$K204,Analysis!I204,"") -> 0.15740741
B124: =IF(Analysis!$K205,Analysis!A205,"") -> 11 | C124: =IF(Analysis!$K205,Analysis!B205,"") -> Multivitamin Gummies | F124: =IF(Analysis!$K205,Analysis!C205,"") -> Wellness | H124: =IF(Analysis!$K205,Analysis!D205,"") -> 178314.9 | J124: =IF(Analysis!$K205,Analysis!E205,"") -> 83950.9 | K124: =IF(Analysis!$K205,Analysis!F205,"") -> 0.47080137 | L124: =IF(Analysis!$K205,Analysis!G205,"") -> 338 | M124: =IF(Analysis!$K205,Analysis!H205,"") -> 3.9259259 | N124: =IF(Analysis!$K205,Analysis!I205,"") -> 0.069124424
B125: =IF(Analysis!$K206,Analysis!A206,"") -> 12 | C125: =IF(Analysis!$K206,Analysis!B206,"") -> Ashwagandha Capsules | F125: =IF(Analysis!$K206,Analysis!C206,"") -> Wellness | H125: =IF(Analysis!$K206,Analysis!D206,"") -> 163347.65 | J125: =IF(Analysis!$K206,Analysis!E206,"") -> 96597.65 | K125: =IF(Analysis!$K206,Analysis!F206,"") -> 0.59136235 | L125: =IF(Analysis!$K206,Analysis!G206,"") -> 347 | M125: =IF(Analysis!$K206,Analysis!H206,"") -> 4.0308642 | N125: =IF(Analysis!$K206,Analysis!I206,"") -> 0.079295154
... B128: =IF(Analysis!$K209,Analysis!A209,"") -> 15 | C128: =IF(Analysis!$K209,Analysis!B209,"") -> Flip Flops | F128: =IF(Analysis!$K209,Analysis!C209,"") -> Footwear | H128: =IF(Analysis!$K209,Analysis!D209,"") -> 152338.2 | J128: =IF(Analysis!$K209,Analysis!E209,"") -> 61926.2 | K128: =IF(Analysis!$K209,Analysis!F209,"") -> 0.40650474 | L128: =IF(Analysis!$K209,Analysis!G209,"") -> 446 | M128: =IF(Analysis!$K209,Analysis!H209,"") -> 3.9525862 | N128: =IF(Analysis!$K209,Analysis!I209,"") -> 0.18927445
B129: KEY INSIGHTS
B130: ="1. Revenue ₹"&TEXT(Analysis!B11/100000,"0.0")&" lakh with "&TEXT(Analysis!B13,"0.0%")&" profit margin. "&IF(Analysis!E11="","YoY comparison unavailable.","2025 revenue "&IF(Analysis!E11>=0,"grew ","declined ")&TEXT(ABS(Analysis!E11),"0.0%")&" versus 2024.") -> 1. Revenue ₹51.6 lakh with 40.4% profit margin. 2025 revenue grew 28.5% versus 2024.
B131: =IF(Analysis!B11=0,"2. No revenue for the selected filters.","2. Top channel: "&INDEX(Analysis!A80:A84,MATCH(MAX(Analysis!B80:B84),Analysis!B80:B84,0))&". Top product: "&Analysis!B195&", contributing "&TEXT(Analysis!D195/Analysis!B11,"0.0%")&" of selected revenue.") -> 2. Top channel: Amazon. Top product: Linen Kurta, contributing 7.0% of selected revenue.
B132: =IF(OR(selChannel<>"All",selCategory<>"All"),"3. Select All channels and categories for a comparable state advertising analysis.",IFERROR("3. Across states, each additional ₹1 of ad spend is associated with ₹"&TEXT(Analysis!B147,"0.00")&" of revenue change (R² "&TEXT(Analysis!B149,"0.00")&"). Region filter ignored.","3. Insufficient data for advertising analysis.")) -> 3. Across states, each additional ₹1 of ad spend is associated with ₹4.38 of revenue change (R² 0.99). Region filter ignored.
B133: =IF(OR(Analysis!B116=0,Analysis!B118=0),"4. Insufficient orders to compare Express and Delayed deliveries.","4. Express deliveries average "&TEXT(Analysis!C116,"0.00")&" stars versus "&TEXT(Analysis!C118,"0.00")&" for 5+ day deliveries. Return rates are "&TEXT(Analysis!D116,"0.0%")&" versus "&TEXT(Analysis!D118,"0.0%")&".") -> 4. Express deliveries average 4.29 stars versus 3.45 for 5+ day deliveries. Return rates are 10.1% versus 12.6%.
B134: =IFERROR("5. Each +10 percentage points of discount is associated with "&TEXT(Analysis!B190*10,"+0.0;-0.0;0.0")&" margin points (R² "&TEXT(Analysis!B191,"0.00")&"). Top 15 products contribute "&TEXT(Analysis!J209,"0.0%")&" of selected revenue.","5. Insufficient data for discount or product concentration analysis.") -> 5. Each +10 percentage points of discount is associated with -10.5 margin points (R² 0.59). Top 15 products contribute 67.0% of selected revenue.
B135: =IF(Analysis!B14=0,"6. No orders for the selected filters.","6. Repeat customers contribute "&TEXT(Analysis!B20,"0.0%")&" of revenue. Average order value is ₹"&TEXT(Analysis!B16,"#,##0")&" across "&TEXT(Analysis!B14,"#,##0")&" orders.") -> 6. Repeat customers contribute 53.1% of revenue. Average order value is ₹1,067 across 4,833 orders.

Sheet Detail1
A1: Details for Revenue by Region and Year - State: Odisha, Region: East, Year: 2024
A3: Order ID | B3: Order Date | C3: Year | D3: Month | E3: Month No | F3: Customer ID | G3: Customer Type | H3: State | I3: State Code | J3: Region | K3: City | L3: Sales Channel | M3: Product ID | N3: Product Name | O3: Category | P3: Quantity | Q3: Unit Price | R3: Discount % | S3: Gross Sale | T3: Discount Amount | U3: Net Revenue | V3: Unit Cost | W3: COGS | X3: Shipping Cost | Y3: Profit Margin | Z3: Margin % | AA3: Payment Method | AB3: Delivery Date | AC3: Delivery Days | AD3: Delivery Speed | AE3: Customer Rating | AF3: Returned
A4: ORD-101965 | B4: 45636 | C4: 2024 | D4: 45627 | E4: 12 | F4: CUST-00064 | G4: New | H4: Odisha | I4: OD | J4: East | K4: Bhubaneswar | L4: Myntra | M4: P402 | N4: Casual Sneakers | O4: Footwear | P4: 1 | Q4: 2199 | R4: 0.25 | S4: 2199 | T4: 549.75 | U4: 1649.25 | V4: 1034 | W4: 1034 | X4: 60 | Y4: 555.25 | Z4: 0.33666818 | AA4: Debit Card | AB4: 45640 | AC4: 4 | AD4: Standard (3-4d) | AF4: 0
A5: ORD-101812 | B5: 45613 | C5: 2024 | D5: 45597 | E5: 11 | F5: CUST-01039 | G5: New | H5: Odisha | I5: OD | J5: East | K5: Bhubaneswar | L5: Amazon | M5: P203 | N5: Keratin Hair Mask | O5: Haircare | P5: 1 | Q5: 549 | R5: 0.4 | S5: 549 | T5: 219.6 | U5: 329.4 | V5: 170 | W5: 170 | X5: 60 | Y5: 99.4 | Z5: 0.30176078 | AA5: UPI | AB5: 45618 | AC5: 5 | AD5: Delayed (5d+) | AE5: 4 | AF5: 0
A6: ORD-101718 | B6: 45601 | C6: 2024 | D6: 45597 | E6: 11 | F6: CUST-00149 | G6: New | H6: Odisha | I6: OD | J6: East | K6: Bhubaneswar | L6: Website | M6: P304 | N6: Denim Jacket | O6: Apparel | P6: 1 | Q6: 2499 | R6: 0.1 | S6: 2499 | T6: 249.9 | U6: 2249.1 | V6: 1125 | W6: 1125 | X6: 60 | Y6: 1064.1 | Z6: 0.47312258 | AA6: UPI | AB6: 45604 | AC6: 3 | AD6: Standard (3-4d) | AE6: 4 | AF6: 0
A7: ORD-101705 | B7: 45600 | C7: 2024 | D7: 45597 | E7: 11 | F7: CUST-01532 | G7: New | H7: Odisha | I7: OD | J7: East | K7: Bhubaneswar | L7: Myntra | M7: P301 | N7: Cotton Oversized T-Shirt | O7: Apparel | P7: 1 | Q7: 799 | R7: 0.15 | S7: 799 | T7: 119.85 | U7: 679.15 | V7: 320 | W7: 320 | X7: 120 | Y7: 239.15 | Z7: 0.35213134 | AA7: UPI | AB7: 45604 | AC7: 4 | AD7: Standard (3-4d) | AF7: 1
A8: ORD-100005 | B8: 45292 | C8: 2024 | D8: 45292 | E8: 1 | F8: CUST-01769 | G8: New | H8: Odisha | I8: OD | J8: East | K8: Bhubaneswar | L8: Website | M8: P303 | N8: Joggers | O8: Apparel | P8: 1 | Q8: 1199 | R8: 0.15 | S8: 1199 | T8: 179.85 | U8: 1019.15 | V8: 492 | W8: 492 | X8: 60 | Y8: 467.15 | Z8: 0.45837217 | AA8: Credit Card | AB8: 45298 | AC8: 6 | AD8: Delayed (5d+) | AE8: 3 | AF8: 0
A9: ORD-101651 | B9: 45593 | C9: 2024 | D9: 45566 | E9: 10 | F9: CUST-01243 | G9: New | H9: Odisha | I9: OD | J9: East | K9: Bhubaneswar | L9: Flipkart | M9: P503 | N9: Scented Candle Set | O9: Home & Kitchen | P9: 2 | Q9: 699 | R9: 0.4 | S9: 1398 | T9: 559.2 | U9: 838.8 | V9: 245 | W9: 490 | X9: 60 | Y9: 288.8 | Z9: 0.34430138 | AA9: Wallet | AB9: 45598 | AC9: 5 | AD9: Delayed (5d+) | AE9: 4 | AF9: 0
A10: ORD-101650 | B10: 45593 | C10: 2024 | D10: 45566 | E10: 10 | F10: CUST-01319 | G10: New | H10: Odisha | I10: OD | J10: East | K10: Bhubaneswar | L10: Flipkart | M10: P603 | N10: Smartwatch Strap | O10: Electronics | P10: 1 | Q10: 499 | R10: 0.15 | S10: 499 | T10: 74.85 | U10: 424.15 | V10: 200 | W10: 200 | X10: 60 | Y10: 164.15 | Z10: 0.38700931 | AA10: UPI | AB10: 45598 | AC10: 5 | AD10: Delayed (5d+) | AE10: 4 | AF10: 0
A11: ORD-101517 | B11: 45579 | C11: 2024 | D11: 45566 | E11: 10 | F11: CUST-00121 | G11: Repeat | H11: Odisha | I11: OD | J11: East | K11: Bhubaneswar | L11: Website | M11: P503 | N11: Scented Candle Set | O11: Home & Kitchen | P11: 2 | Q11: 699 | R11: 0.25 | S11: 1398 | T11: 349.5 | U11: 1048.5 | V11: 245 | W11: 490 | X11: 60 | Y11: 498.5 | Z11: 0.47544111 | AA11: UPI | AB11: 45582 | AC11: 3 | AD11: Standard (3-4d) | AE11: 4 | AF11: 0
A12: ORD-101450 | B12: 45572 | C12: 2024 | D12: 45566 | E12: 10 | F12: CUST-02935 | G12: New | H12: Odisha | I12: OD | J12: East | K12: Bhubaneswar | L12: Flipkart | M12: P202 | N12: Argan Shampoo | O12: Haircare | P12: 2 | Q12: 449 | R12: 0.3 | S12: 898 | T12: 269.4 | U12: 628.6 | V12: 148 | W12: 296 | X12: 60 | Y12: 272.6 | Z12: 0.43366211 | AA12: UPI | AB12: 45576 | AC12: 4 | AD12: Standard (3-4d) | AF12: 0
A13: ORD-101369 | B13: 45563 | C13: 2024 | D13: 45536 | E13: 9 | F13: CUST-00535 | G13: Repeat | H13: Odisha | I13: OD | J13: East | K13: Bhubaneswar | L13: Amazon | M13: P105 | N13: Retinol Night Cream | O13: Skincare | P13: 2 | Q13: 799 | R13: 0.05 | S13: 1598 | T13: 79.9 | U13: 1518.1 | V13: 216 | W13: 432 | X13: 60 | Y13: 1026.1 | Z13: 0.67591068 | AA13: UPI | AB13: 45568 | AC13: 5 | AD13: Delayed (5d+) | AE13: 3 | AF13: 0
A14: ORD-101360 | B14: 45562 | C14: 2024 | D14: 45536 | E14: 9 | F14: CUST-01104 | G14: New | H14: Odisha | I14: OD | J14: East | K14: Bhubaneswar | L14: Amazon | M14: P302 | N14: Linen Kurta | O14: Apparel | P14: 2 | Q14: 1499 | R14: 0.3 | S14: 2998 | T14: 899.4 | U14: 2098.6 | V14: 630 | W14: 1260 | X14: 60 | Y14: 778.6 | Z14: 0.37100924 | AA14: UPI | AB14: 45568 | AC14: 6 | AD14: Delayed (5d+) | AE14: 3 | AF14: 0
A15: ORD-101328 | B15: 45556 | C15: 2024 | D15: 45536 | E15: 9 | F15: CUST-01770 | G15: New | H15: Odisha | I15: OD | J15: East | K15: Bhubaneswar | L15: Website | M15: P104 | N15: Hydrating Face Wash | O15: Skincare | P15: 3 | Q15: 299 | R15: 0 | S15: 897 | T15: 0 | U15: 897 | V15: 90 | W15: 270 | X15: 60 | Y15: 567 | Z15: 0.63210702 | AA15: Wallet | AB15: 45559 | AC15: 3 | AD15: Standard (3-4d) | AE15: 3 | AF15: 0
A16: ORD-101178 | B16: 45530 | C16: 2024 | D16: 45505 | E16: 8 | F16: CUST-00940 | G16: Repeat | H16: Odisha | I16: OD | J16: East | K16: Bhubaneswar | L16: Flipkart | M16: P603 | N16: Smartwatch Strap | O16: Electronics | P16: 4 | Q16: 499 | R16: 0.1 | S16: 1996 | T16: 199.6 | U16: 1796.4 | V16: 200 | W16: 800 | X16: 60 | Y16: 936.4 | Z16: 0.52126475 | AA16: Credit Card | AB16: 45533 | AC16: 3 | AD16: Standard (3-4d) | AF16: 0
A17: ORD-101059 | B17: 45505 | C17: 2024 | D17: 45505 | E17: 8 | F17: CUST-00522 | G17: New | H17: Odisha | I17: OD | J17: East | K17: Bhubaneswar | L17: Myntra | M17: P301 | N17: Cotton Oversized T-Shirt | O17: Apparel | P17: 1 | Q17: 799 | R17: 0 | S17: 799 | T17: 0 | U17: 799 | V17: 320 | W17: 320 | X17: 60 | Y17: 419 | Z17: 0.52440551 | AA17: Credit Card | AB17: 45509 | AC17: 4 | AD17: Standard (3-4d) | AE17: 4 | AF17: 0
A18: ORD-100015 | B18: 45294 | C18: 2024 | D18: 45292 | E18: 1 | F18: CUST-00711 | G18: New | H18: Odisha | I18: OD | J18: East | K18: Bhubaneswar | L18: Myntra | M18: P402 | N18: Casual Sneakers | O18: Footwear | P18: 1 | Q18: 2199 | R18: 0.25 | S18: 2199 | T18: 549.75 | U18: 1649.25 | V18: 1034 | W18: 1034 | X18: 60 | Y18: 555.25 | Z18: 0.33666818 | AA18: UPI | AB18: 45300 | AC18: 6 | AD18: Delayed (5d+) | AE18: 4 | AF18: 0
A19: ORD-101007 | B19: 45493 | C19: 2024 | D19: 45474 | E19: 7 | F19: CUST-01084 | G19: Repeat | H19: Odisha | I19: OD | J19: East | K19: Bhubaneswar | L19: Myntra | M19: P403 | N19: Kolhapuri Sandals | O19: Footwear | P19: 1 | Q19: 999 | R19: 0.05 | S19: 999 | T19: 49.95 | U19: 949.05 | V19: 400 | W19: 400 | X19: 60 | Y19: 489.05 | Z19: 0.51530478 | AA19: COD | AB19: 45496 | AC19: 3 | AD19: Standard (3-4d) | AE19: 4 | AF19: 0
A20: ORD-100986 | B20: 45490 | C20: 2024 | D20: 45474 | E20: 7 | F20: CUST-00407 | G20: New | H20: Odisha | I20: OD | J20: East | K20: Bhubaneswar | L20: Nykaa | M20: P204 | N20: Anti-Dandruff Conditioner | O20: Haircare | P20: 2 | Q20: 399 | R20: 0.35 | S20: 798 | T20: 279.3 | U20: 518.7 | V20: 136 | W20: 272 | X20: 60 | Y20: 186.7 | Z20: 0.35993831 | AA20: UPI | AB20: 45493 | AC20: 3 | AD20: Standard (3-4d) | AE20: 3 | AF20: 0
A21: ORD-100985 | B21: 45490 | C21: 2024 | D21: 45474 | E21: 7 | F21: CUST-00709 | G21: New | H21: Odisha | I21: OD | J21: East | K21: Bhubaneswar | L21: Myntra | M21: P302 | N21: Linen Kurta | O21: Apparel | P21: 4 | Q21: 1499 | R21: 0.4 | S21: 5996 | T21: 2398.4 | U21: 3597.6 | V21: 630 | W21: 2520 | X21: 60 | Y21: 1017.6 | Z21: 0.28285524 | AA21: UPI | AB21: 45494 | AC21: 4 | AD21: Standard (3-4d) | AE21: 3 | AF21: 0
A22: ORD-100961 | B22: 45486 | C22: 2024 | D22: 45474 | E22: 7 | F22: CUST-00070 | G22: Repeat | H22: Odisha | I22: OD | J22: East | K22: Bhubaneswar | L22: Website | M22: P604 | N22: Power Bank 20000mAh | O22: Electronics | P22: 1 | Q22: 1799 | R22: 0.35 | S22: 1799 | T22: 629.65 | U22: 1169.35 | V22: 1079 | W22: 1079 | X22: 60 | Y22: 30.35 | Z22: 0.02595459 | AA22: UPI | AB22: 45491 | AC22: 5 | AD22: Delayed (5d+) | AF22: 0
A23: ORD-100924 | B23: 45480 | C23: 2024 | D23: 45474 | E23: 7 | F23: CUST-00809 | G23: Repeat | H23: Odisha | I23: OD | J23: East | K23: Bhubaneswar | L23: Nykaa | M23: P104 | N23: Hydrating Face Wash | O23: Skincare | P23: 1 | Q23: 299 | R23: 0 | S23: 299 | T23: 0 | U23: 299 | V23: 90 | W23: 90 | X23: 60 | Y23: 149 | Z23: 0.49832776 | AA23: UPI | AB23: 45485 | AC23: 5 | AD23: Delayed (5d+) | AE23: 5 | AF23: 0
A24: ORD-100021 | B24: 45295 | C24: 2024 | D24: 45292 | E24: 1 | F24: CUST-00348 | G24: New | H24: Odisha | I24: OD | J24: East | K24: Bhubaneswar | L24: Amazon | M24: P703 | N24: Green Tea (100 bags) | O24: Wellness | P24: 1 | Q24: 399 | R24: 0.3 | S24: 399 | T24: 119.7 | U24: 279.3 | V24: 128 | W24: 128 | X24: 60 | Y24: 91.3 | Z24: 0.32688865 | AA24: UPI | AB24: 45298 | AC24: 3 | AD24: Standard (3-4d) | AE24: 5 | AF24: 0
A25: ORD-100913 | B25: 45479 | C25: 2024 | D25: 45474 | E25: 7 | F25: CUST-00580 | G25: New | H25: Odisha | I25: OD | J25: East | K25: Bhubaneswar | L25: Website | M25: P602 | N25: Fast Charger 33W | O25: Electronics | P25: 2 | Q25: 899 | R25: 0 | S25: 1798 | T25: 0 | U25: 1798 | V25: 494 | W25: 988 | X25: 60 | Y25: 750 | Z25: 0.41713014 | AA25: UPI | AB25: 45484 | AC25: 5 | AD25: Delayed (5d+) | AE25: 3 | AF25: 0
A26: ORD-100808 | B26: 45457 | C26: 2024 | D26: 45444 | E26: 6 | F26: CUST-01100 | G26: New | H26: Odisha | I26: OD | J26: East | K26: Bhubaneswar | L26: Amazon | M26: P103 | N26: Niacinamide Toner | O26: Skincare | P26: 3 | Q26: 399 | R26: 0.15 | S26: 1197 | T26: 179.55 | U26: 1017.45 | V26: 112 | W26: 336 | X26: 60 | Y26: 621.45 | Z26: 0.61079169 | AA26: UPI | AB26: 45463 | AC26: 6 | AD26: Delayed (5d+) | AE26: 3 | AF26: 0
A27: ORD-100766 | B27: 45449 | C27: 2024 | D27: 45444 | E27: 6 | F27: CUST-01116 | G27: Repeat | H27: Odisha | I27: OD | J27: East | K27: Bhubaneswar | L27: Nykaa | M27: P701 | N27: Ashwagandha Capsules | O27: Wellness | P27: 1 | Q27: 499 | R27: 0 | S27: 499 | T27: 0 | U27: 499 | V27: 150 | W27: 150 | X27: 60 | Y27: 289 | Z27: 0.57915832 | AA27: COD | AB27: 45454 | AC27: 5 | AD27: Delayed (5d+) | AE27: 4 | AF27: 0
A28: ORD-100669 | B28: 45430 | C28: 2024 | D28: 45413 | E28: 5 | F28: CUST-03110 | G28: Repeat | H28: Odisha | I28: OD | J28: East | K28: Bhubaneswar | L28: Nykaa | M28: P102 | N28: Sunscreen SPF 50 | O28: Skincare | P28: 3 | Q28: 449 | R28: 0.15 | S28: 1347 | T28: 202.05 | U28: 1144.95 | V28: 144 | W28: 432 | X28: 60 | Y28: 652.95 | Z28: 0.57028691 | AA28: UPI | AB28: 45432 | AC28: 2 | AD28: Express (≤2d) | AF28: 0
A29: ORD-100580 | B29: 45413 | C29: 2024 | D29: 45413 | E29: 5 | F29: CUST-00243 | G29: Repeat | H29: Odisha | I29: OD | J29: East | K29: Bhubaneswar | L29: Nykaa | M29: P104 | N29: Hydrating Face Wash | O29: Skincare | P29: 1 | Q29: 299 | R29: 0.05 | S29: 299 | T29: 14.95 | U29: 284.05 | V29: 90 | W29: 90 | X29: 60 | Y29: 134.05 | Z29: 0.47192396 | AA29: UPI | AB29: 45417 | AC29: 4 | AD29: Standard (3-4d) | AE29: 4 | AF29: 0
A30: ORD-100549 | B30: 45407 | C30: 2024 | D30: 45383 | E30: 4 | F30: CUST-00668 | G30: New | H30: Odisha | I30: OD | J30: East | K30: Bhubaneswar | L30: Myntra | M30: P302 | N30: Linen Kurta | O30: Apparel | P30: 1 | Q30: 1499 | R30: 0.25 | S30: 1499 | T30: 374.75 | U30: 1124.25 | V30: 630 | W30: 630 | X30: 60 | Y30: 434.25 | Z30: 0.38625751 | AA30: UPI | AB30: 45410 | AC30: 3 | AD30: Standard (3-4d) | AF30: 0
A31: ORD-100488 | B31: 45395 | C31: 2024 | D31: 45383 | E31: 4 | F31: CUST-01189 | G31: Repeat | H31: Odisha | I31: OD | J31: East | K31: Bhubaneswar | L31: Website | M31: P601 | N31: Wireless Earbuds | O31: Electronics | P31: 4 | Q31: 1999 | R31: 0.25 | S31: 7996 | T31: 1999 | U31: 5997 | V31: 1239 | W31: 4956 | X31: 60 | Y31: 981 | Z31: 0.16358179 | AA31: Credit Card | AB31: 45401 | AC31: 6 | AD31: Delayed (5d+) | AE31: 3 | AF31: 0
A32: ORD-100465 | B32: 45390 | C32: 2024 | D32: 45383 | E32: 4 | F32: CUST-00597 | G32: Repeat | H32: Odisha | I32: OD | J32: East | K32: Bhubaneswar | L32: Flipkart | M32: P501 | N32: Copper Water Bottle | O32: Home & Kitchen | P32: 1 | Q32: 899 | R32: 0 | S32: 899 | T32: 0 | U32: 899 | V32: 378 | W32: 378 | X32: 60 | Y32: 461 | Z32: 0.51279199 | AA32: Credit Card | AB32: 45395 | AC32: 5 | AD32: Delayed (5d+) | AE32: 4 | AF32: 0
A33: ORD-100456 | B33: 45388 | C33: 2024 | D33: 45383 | E33: 4 | F33: CUST-01527 | G33: New | H33: Odisha | I33: OD | J33: East | K33: Bhubaneswar | L33: Amazon | M33: P703 | N33: Green Tea (100 bags) | O33: Wellness | P33: 2 | Q33: 399 | R33: 0.45 | S33: 798 | T33: 359.1 | U33: 438.9 | V33: 128 | W33: 256 | X33: 60 | Y33: 122.9 | Z33: 0.28001823 | AA33: COD | AB33: 45395 | AC33: 7 | AD33: Delayed (5d+) | AE33: 4 | AF33: 0
A34: ORD-100443 | B34: 45385 | C34: 2024 | D34: 45383 | E34: 4 | F34: CUST-00953 | G34: New | H34: Odisha | I34: OD | J34: East | K34: Bhubaneswar | L34: Flipkart | M34: P702 | N34: Whey Protein 1kg | O34: Wellness | P34: 4 | Q34: 2299 | R34: 0.4 | S34: 9196 | T34: 3678.4 | U34: 5517.6 | V34: 1333 | W34: 5332 | X34: 60 | Y34: 125.6 | Z34: 0.02276352 | AA34: COD | AB34: 45389 | AC34: 4 | AD34: Standard (3-4d) | AE34: 4 | AF34: 0
A35: ORD-100442 | B35: 45385 | C35: 2024 | D35: 45383 | E35: 4 | F35: CUST-00798 | G35: New | H35: Odisha | I35: OD | J35: East | K35: Bhubaneswar | L35: Amazon | M35: P503 | N35: Scented Candle Set | O35: Home & Kitchen | P35: 2 | Q35: 699 | R35: 0.2 | S35: 1398 | T35: 279.6 | U35: 1118.4 | V35: 245 | W35: 490 | X35: 60 | Y35: 568.4 | Z35: 0.50822604 | AA35: UPI | AB35: 45388 | AC35: 3 | AD35: Standard (3-4d) | AE35: 4 | AF35: 0
A36: ORD-100387 | B36: 45372 | C36: 2024 | D36: 45352 | E36: 3 | F36: CUST-01031 | G36: Repeat | H36: Odisha | I36: OD | J36: East | K36: Bhubaneswar | L36: Amazon | M36: P403 | N36: Kolhapuri Sandals | O36: Footwear | P36: 1 | Q36: 999 | R36: 0.1 | S36: 999 | T36: 99.9 | U36: 899.1 | V36: 400 | W36: 400 | X36: 60 | Y36: 439.1 | Z36: 0.48837727 | AA36: Debit Card | AB36: 45378 | AC36: 6 | AD36: Delayed (5d+) | AE36: 4 | AF36: 0
A37: ORD-100379 | B37: 45370 | C37: 2024 | D37: 45352 | E37: 3 | F37: CUST-00414 | G37: New | H37: Odisha | I37: OD | J37: East | K37: Bhubaneswar | L37: Myntra | M37: P301 | N37: Cotton Oversized T-Shirt | O37: Apparel | P37: 2 | Q37: 799 | R37: 0.1 | S37: 1598 | T37: 159.8 | U37: 1438.2 | V37: 320 | W37: 640 | X37: 60 | Y37: 738.2 | Z37: 0.51328049 | AA37: UPI | AB37: 45375 | AC37: 5 | AD37: Delayed (5d+) | AE37: 3 | AF37: 0
A38: ORD-100296 | B38: 45352 | C38: 2024 | D38: 45352 | E38: 3 | F38: CUST-00103 | G38: New | H38: Odisha | I38: OD | J38: East | K38: Bhubaneswar | L38: Amazon | M38: P101 | N38: Vitamin C Face Serum | O38: Skincare | P38: 2 | Q38: 599 | R38: 0.2 | S38: 1198 | T38: 239.6 | U38: 958.4 | V38: 180 | W38: 360 | X38: 60 | Y38: 538.4 | Z38: 0.56176962 | AA38: UPI | AB38: 45355 | AC38: 3 | AD38: Standard (3-4d) | AE38: 4 | AF38: 0
A39: ORD-100188 | B39: 45323 | C39: 2024 | D39: 45323 | E39: 2 | F39: CUST-02705 | G39: New | H39: Odisha | I39: OD | J39: East | K39: Bhubaneswar | L39: Flipkart | M39: P701 | N39: Ashwagandha Capsules | O39: Wellness | P39: 1 | Q39: 499 | R39: 0.05 | S39: 499 | T39: 24.95 | U39: 474.05 | V39: 150 | W39: 150 | X39: 60 | Y39: 264.05 | Z39: 0.55700875 | AA39: UPI | AB39: 45328 | AC39: 5 | AD39: Delayed (5d+) | AF39: 0
A40: ORD-100178 | B40: 45321 | C40: 2024 | D40: 45292 | E40: 1 | F40: CUST-00001 | G40: New | H40: Odisha | I40: OD | J40: East | K40: Bhubaneswar | L40: Amazon | M40: P202 | N40: Argan Shampoo | O40: Haircare | P40: 1 | Q40: 449 | R40: 0.05 | S40: 449 | T40: 22.45 | U40: 426.55 | V40: 148 | W40: 148 | X40: 60 | Y40: 218.55 | Z40: 0.51236666 | AA40: UPI | AB40: 45324 | AC40: 3 | AD40: Standard (3-4d) | AE40: 4 | AF40: 0
A41: ORD-100169 | B41: 45319 | C41: 2024 | D41: 45292 | E41: 1 | F41: CUST-00312 | G41: New | H41: Odisha | I41: OD | J41: East | K41: Bhubaneswar | L41: Myntra | M41: P301 | N41: Cotton Oversized T-Shirt | O41: Apparel | P41: 1 | Q41: 799 | R41: 0.1 | S41: 799 | T41: 79.9 | U41: 719.1 | V41: 320 | W41: 320 | X41: 120 | Y41: 279.1 | Z41: 0.38812404 | AA41: COD | AB41: 45323 | AC41: 4 | AD41: Standard (3-4d) | AE41: 4 | AF41: 1
A42: ORD-100158 | B42: 45317 | C42: 2024 | D42: 45292 | E42: 1 | F42: CUST-00666 | G42: New | H42: Odisha | I42: OD | J42: East | K42: Bhubaneswar | L42: Amazon | M42: P403 | N42: Kolhapuri Sandals | O42: Footwear | P42: 1 | Q42: 999 | R42: 0 | S42: 999 | T42: 0 | U42: 999 | V42: 400 | W42: 400 | X42: 120 | Y42: 479 | Z42: 0.47947948 | AA42: Debit Card | AB42: 45322 | AC42: 5 | AD42: Delayed (5d+) | AF42: 1
A43: ORD-100102 | B43: 45309 | C43: 2024 | D43: 45292 | E43: 1 | F43: CUST-00007 | G43: New | H43: Odisha | I43: OD | J43: East | K43: Bhubaneswar | L43: Flipkart | M43: P103 | N43: Niacinamide Toner | O43: Skincare | P43: 1 | Q43: 399 | R43: 0.2 | S43: 399 | T43: 79.8 | U43: 319.2 | V43: 112 | W43: 112 | X43: 120 | Y43: 87.2 | Z43: 0.27318296 | AA43: Credit Card | AB43: 45312 | AC43: 3 | AD43: Standard (3-4d) | AE43: 3 | AF43: 1
A44: ORD-100101 | B44: 45309 | C44: 2024 | D44: 45292 | E44: 1 | F44: CUST-00905 | G44: New | H44: Odisha | I44: OD | J44: East | K44: Bhubaneswar | L44: Amazon | M44: P105 | N44: Retinol Night Cream | O44: Skincare | P44: 2 | Q44: 799 | R44: 0.15 | S44: 1598 | T44: 239.7 | U44: 1358.3 | V44: 216 | W44: 432 | X44: 60 | Y44: 866.3 | Z44: 0.63778252 | AA44: UPI | AB44: 45315 | AC44: 6 | AD44: Delayed (5d+) | AF44: 0
A45: ORD-100075 | B45: 45303 | C45: 2024 | D45: 45292 | E45: 1 | F45: CUST-00154 | G45: New | H45: Odisha | I45: OD | J45: East | K45: Bhubaneswar | L45: Amazon | M45: P603 | N45: Smartwatch Strap | O45: Electronics | P45: 1 | Q45: 499 | R45: 0.1 | S45: 499 | T45: 49.9 | U45: 449.1 | V45: 200 | W45: 200 | X45: 60 | Y45: 189.1 | Z45: 0.42106435 | AA45: Debit Card | AB45: 45308 | AC45: 5 | AD45: Delayed (5d+) | AE45: 4 | AF45: 0
A46: ORD-100071 | B46: 45302 | C46: 2024 | D46: 45292 | E46: 1 | F46: CUST-02632 | G46: New | H46: Odisha | I46: OD | J46: East | K46: Bhubaneswar | L46: Flipkart | M46: P704 | N46: Multivitamin Gummies | O46: Wellness | P46: 3 | Q46: 699 | R46: 0.3 | S46: 2097 | T46: 629.1 | U46: 1467.9 | V46: 238 | W46: 714 | X46: 60 | Y46: 693.9 | Z46: 0.47271613 | AA46: UPI | AB46: 45307 | AC46: 5 | AD46: Delayed (5d+) | AE46: 2 | AF46: 0

Sheet Analysis
A1: ANALYSIS ENGINE
A3: Filter criteria
A4: cYear | B4: =IF(OR(selYear="All",selYear=""),"<>",selYear) -> <>
A5: cRegion | B5: =IF(OR(selRegion="All",selRegion=""),"<>",selRegion) -> <>
A6: cChannel | B6: =IF(OR(selChannel="All",selChannel=""),"<>",selChannel) -> <>
A7: cCat | B7: =IF(OR(selCategory="All",selCategory=""),"<>",selCategory) -> <>
A9: KPIs
A10: KPI | B10: Selected | C10: 2024 | D10: 2025 | E10: YoY %
A11: Revenue | B11: =SUMIFS(Net_Revenue,Year,cYear,Region,cRegion,Sales_Channel,cChannel,Category,cCat) -> 5156142.5 | C11: =SUMIFS(Net_Revenue,Year,C$10,Region,cRegion,Sales_Channel,cChannel,Category,cCat) -> 2256636.5 | D11: =SUMIFS(Net_Revenue,Year,D$10,Region,cRegion,Sales_Channel,cChannel,Category,cCat) -> 2899506 | E11: =IF(C11=0,"",D11/C11-1) -> 0.28487949
A12: Profit | B12: =SUMIFS(Profit,Year,cYear,Region,cRegion,Sales_Channel,cChannel,Category,cCat) -> 2083254.5 | C12: =SUMIFS(Profit,Year,C$10,Region,cRegion,Sales_Channel,cChannel,Category,cCat) -> 908603.5 | D12: =SUMIFS(Profit,Year,D$10,Region,cRegion,Sales_Channel,cChannel,Category,cCat) -> 1174650.9 | E12: =IF(C12=0,"",D12/C12-1) -> 0.29280918
A13: Margin % | B13: =IFERROR(B12/B11,0) -> 0.40403353 | C13: =IFERROR(C12/C11,0) -> 0.40263618 | D13: =IFERROR(D12/D11,0) -> 0.40512107 | E13: =D13-C13 -> 0.002484889
A14: Orders | B14: =COUNTIFS(Year,cYear,Region,cRegion,Sales_Channel,cChannel,Category,cCat) -> 4833 | C14: =COUNTIFS(Year,C$10,Region,cRegion,Sales_Channel,cChannel,Category,cCat) -> 2126 | D14: =COUNTIFS(Year,D$10,Region,cRegion,Sales_Channel,cChannel,Category,cCat) -> 2707 | E14: =IF(C14=0,"",D14/C14-1) -> 0.27328316
A15: Units | B15: =SUMIFS(Quantity,Year,cYear,Region,cRegion,Sales_Channel,cChannel,Category,cCat) -> 7559 | C15: =SUMIFS(Quantity,Year,C$10,Region,cRegion,Sales_Channel,cChannel,Category,cCat) -> 3303 | D15: =SUMIFS(Quantity,Year,D$10,Region,cRegion,Sales_Channel,cChannel,Category,cCat) -> 4256 | E15: =IF(C15=0,"",D15/C15-1) -> 0.28852558
A16: Avg Order Value | B16: =IFERROR(B11/B14,0) -> 1066.8617 | C16: =IFERROR(C11/C14,0) -> 1061.4471 | D16: =IFERROR(D11/D14,0) -> 1071.1141 | E16: =IF(C16=0,"",D16/C16-1) -> 0.0091074218
A17: Avg Rating | B17: =IFERROR(AVERAGEIFS(Customer_Rating,Year,cYear,Region,cRegion,Sales_Channel,cChannel,Category,cCat),0) -> 3.9144603 | C17: =IFERROR(AVERAGEIFS(Customer_Rating,Year,C$10,Region,cRegion,Sales_Channel,cChannel,Category,cCat),0) -> 3.9201065 | D17: =IFERROR(AVERAGEIFS(Customer_Rating,Year,D$10,Region,cRegion,Sales_Channel,cChannel,Category,cCat),0) -> 3.9100775 | E17: =D17-C17 -> -0.010029005
A18: Return Rate | B18: =IFERROR(SUMIFS(Returned,Year,cYear,Region,cRegion,Sales_Channel,cChannel,Category,cCat)/B14,0) -> 0.10407614 | C18: =IFERROR(SUMIFS(Returned,Year,C$10,Region,cRegion,Sales_Channel,cChannel,Category,cCat)/C14,0) -> 0.10865475 | D18: =IFERROR(SUMIFS(Returned,Year,D$10,Region,cRegion,Sales_Channel,cChannel,Category,cCat)/D14,0) -> 0.10048024 | E18: =D18-C18 -> -0.0081745143 | G18: =IF($K210,$B210,"")
A19: Avg Delivery Days | B19: =IFERROR(AVERAGEIFS(Delivery_Days,Year,cYear,Region,cRegion,Sales_Channel,cChannel,Category,cCat),0) -> 3.3279537 | C19: =IFERROR(AVERAGEIFS(Delivery_Days,Year,C$10,Region,cRegion,Sales_Channel,cChannel,Category,cCat),0) -> 3.3306679 | D19: =IFERROR(AVERAGEIFS(Delivery_Days,Year,D$10,Region,cRegion,Sales_Channel,cChannel,Category,cCat),0) -> 3.3258219 | E19: =D19-C19 -> -0.0048459779
A20: Repeat Customer Revenue % | B20: =IFERROR(SUMIFS(Net_Revenue,Year,cYear,Region,cRegion,Sales_Channel,cChannel,Category,cCat,Customer_Type,"Repeat")/B11,0) -> 0.53148685 | C20: =IFERROR(SUMIFS(Net_Revenue,Year,C$10,Region,cRegion,Sales_Channel,cChannel,Category,cCat,Customer_Type,"Repeat")/C11,0) -> 0.32793192 | D20: =IFERROR(SUMIFS(Net_Revenue,Year,D$10,Region,cRegion,Sales_Channel,cChannel,Category,cCat,Customer_Type,"Repeat")/D11,0) -> 0.68991021 | E20: =D20-C20 -> 0.36197828
A21: Avg Discount % | B21: =IFERROR(SUMIFS(Discount_Amount,Year,cYear,Region,cRegion,Sales_Channel,cChannel,Category,cCat)/SUMIFS(Gross_Sale,Year,cYear,Region,cRegion,Sales_Channel,cChannel,Category,cCat),0) -> 0.21660496 | C21: =IFERROR(SUMIFS(Discount_Amount,Year,C$10,Region,cRegion,Sales_Channel,cChannel,Category,cCat)/SUMIFS(Gross_Sale,Year,C$10,Region,cRegion,Sales_Channel,cChannel,Category,cCat),0) -> 0.21530049 | D21: =IFERROR(SUMIFS(Discount_Amount,Year,D$10,Region,cRegion,Sales_Channel,cChannel,Category,cCat)/SUMIFS(Gross_Sale,Year,D$10,Region,cRegion,Sales_Channel,cChannel,Category,cCat),0) -> 0.2176172 | E21: =D21-C21 -> 0.0023167145
A24: Monthly trend
A25: Month | B25: Revenue | C25: Profit | D25: Margin % | E25: Orders | F25: Avg Order Value | G25: Avg Rating | H25: Return Rate | I25: Avg Delivery Days | J25: Units | K25: Ad Spend
A26: =DATE(2024,1,1) -> 45292 | B26: =SUMIFS(Net_Revenue,Order_Date,">="&$A26,Order_Date,"<"&EDATE($A26,1),Year,cYear,Region,cRegion,Sales_Channel,cChannel,Category,cCat) -> 219793.3 | C26: =SUMIFS(Profit,Order_Date,">="&$A26,Order_Date,"<"&EDATE($A26,1),Year,cYear,Region,cRegion,Sales_Channel,cChannel,Category,cCat) -> 98308.3 | D26: =IFERROR(C26/B26,0) -> 0.44727615 | E26: =COUNTIFS(Order_Date,">="&$A26,Order_Date,"<"&EDATE($A26,1),Year,cYear,Region,cRegion,Sales_Channel,cChannel,Category,cCat) -> 184 | F26: =IFERROR(B26/E26,0) -> 1194.5288 | G26: =IFERROR(AVERAGEIFS(Customer_Rating,Order_Date,">="&$A26,Order_Date,"<"&EDATE($A26,1),Year,cYear,Region,cRegion,Sales_Channel,cChannel,Category,cCat),0) -> 3.9259259 | H26: =IFERROR(SUMIFS(Returned,Order_Date,">="&$A26,Order_Date,"<"&EDATE($A26,1),Year,cYear,Region,cRegion,Sales_Channel,cChannel,Category,cCat)/COUNTIFS(Order_Date,">="&$A26,Order_Date,"<"&EDATE($A26,1),Year,cYear,Region,cRegion,Sales_Channel,cChannel,Category,cCat),0) -> 0.11413043 | I26: =IFERROR(AVERAGEIFS(Delivery_Days,Order_Date,">="&$A26,Order_Date,"<"&EDATE($A26,1),Year,cYear,Region,cRegion,Sales_Channel,cChannel,Category,cCat),0) -> 3.298913 | J26: =SUMIFS(Quantity,Order_Date,">="&$A26,Order_Date,"<"&EDATE($A26,1),Year,cYear,Region,cRegion,Sales_Channel,cChannel,Category,cCat) -> 290 | K26: =SUMIFS(Ad_Spend,Ad_Month,">="&$A26,Ad_Month,"<"&EDATE($A26,1),Ad_Year,cYear,Ad_Region,cRegion) -> 42510
A27: =EDATE(A26,1) -> 45323 | B27: =SUMIFS(Net_Revenue,Order_Date,">="&$A27,Order_Date,"<"&EDATE($A27,1),Year,cYear,Region,cRegion,Sales_Channel,cChannel,Category,cCat) -> 97871.1 | C27: =SUMIFS(Profit,Order_Date,">="&$A27,Order_Date,"<"&EDATE($A27,1),Year,cYear,Region,cRegion,Sales_Channel,cChannel,Category,cCat) -> 43244.1 | D27: =IFERROR(C27/B27,0) -> 0.44184749 | E27: =COUNTIFS(Order_Date,">="&$A27,Order_Date,"<"&EDATE($A27,1),Year,cYear,Region,cRegion,Sales_Channel,cChannel,Category,cCat) -> 107 | F27: =IFERROR(B27/E27,0) -> 914.68318 | G27: =IFERROR(AVERAGEIFS(Customer_Rating,Order_Date,">="&$A27,Order_Date,"<"&EDATE($A27,1),Year,cYear,Region,cRegion,Sales_Channel,cChannel,Category,cCat),0) -> 4 | H27: =IFERROR(SUMIFS(Returned,Order_Date,">="&$A27,Order_Date,"<"&EDATE($A27,1),Year,cYear,Region,cRegion,Sales_Channel,cChannel,Category,cCat)/COUNTIFS(Order_Date,">="&$A27,Order_Date,"<"&EDATE($A27,1),Year,cYear,Region,cRegion,Sales_Channel,cChannel,Category,cCat),0) -> 0.12149533 | I27: =IFERROR(AVERAGEIFS(Delivery_Days,Order_Date,">="&$A27,Order_Date,"<"&EDATE($A27,1),Year,cYear,Region,cRegion,Sales_Channel,cChannel,Category,cCat),0) -> 3.0747664 | J27: =SUMIFS(Quantity,Order_Date,">="&$A27,Order_Date,"<"&EDATE($A27,1),Year,cYear,Region,cRegion,Sales_Channel,cChannel,Category,cCat) -> 162 | K27: =SUMIFS(Ad_Spend,Ad_Month,">="&$A27,Ad_Month,"<"&EDATE($A27,1),Ad_Year,cYear,Ad_Region,cRegion) -> 28210
A28: =EDATE(A27,1) -> 45352 | B28: =SUMIFS(Net_Revenue,Order_Date,">="&$A28,Order_Date,"<"&EDATE($A28,1),Year,cYear,Region,cRegion,Sales_Channel,cChannel,Category,cCat) -> 150200.35 | C28: =SUMIFS(Profit,Order_Date,">="&$A28,Order_Date,"<"&EDATE($A28,1),Year,cYear,Region,cRegion,Sales_Channel,cChannel,Category,cCat) -> 65213.35 | D28: =IFERROR(C28/B28,0) -> 0.43417575 | E28: =COUNTIFS(Order_Date,">="&$A28,Order_Date,"<"&EDATE($A28,1),Year,cYear,Region,cRegion,Sales_Channel,cChannel,Category,cCat) -> 138 | F28: =IFERROR(B28/E28,0) -> 1088.4083 | G28: =IFERROR(AVERAGEIFS(Customer_Rating,Order_Date,">="&$A28,Order_Date,"<"&EDATE($A28,1),Year,cYear,Region,cRegion,Sales_Channel,cChannel,Category,cCat),0) -> 3.9902913 | H28: =IFERROR(SUMIFS(Returned,Order_Date,">="&$A28,Order_Date,"<"&EDATE($A28,1),Year,cYear,Region,cRegion,Sales_Channel,cChannel,Category,cCat)/COUNTIFS(Order_Date,">="&$A28,Order_Date,"<"&EDATE($A28,1),Year,cYear,Region,cRegion,Sales_Channel,cChannel,Category,cCat),0) -> 0.13768116 | I28: =IFERROR(AVERAGEIFS(Delivery_Days,Order_Date,">="&$A28,Order_Date,"<"&EDATE($A28,1),Year,cYear,Region,cRegion,Sales_Channel,cChannel,Category,cCat),0) -> 3.1811594 | J28: =SUMIFS(Quantity,Order_Date,">="&$A28,Order_Date,"<"&EDATE($A28,1),Year,cYear,Region,cRegion,Sales_Channel,cChannel,Category,cCat) -> 220 | K28: =SUMIFS(Ad_Spend,Ad_Month,">="&$A28,Ad_Month,"<"&EDATE($A28,1),Ad_Year,cYear,Ad_Region,cRegion) -> 32350
A29: =EDATE(A28,1) -> 45383 | B29: =SUMIFS(Net_Revenue,Order_Date,">="&$A29,Order_Date,"<"&EDATE($A29,1),Year,cYear,Region,cRegion,Sales_Channel,cChannel,Category,cCat) -> 160817.2 | C29: =SUMIFS(Profit,Order_Date,">="&$A29,Order_Date,"<"&EDATE($A29,1),Year,cYear,Region,cRegion,Sales_Channel,cChannel,Category,cCat) -> 67672.2 | D29: =IFERROR(C29/B29,0) -> 0.420802 | E29: =COUNTIFS(Order_Date,">="&$A29,Order_Date,"<"&EDATE($A29,1),Year,cYear,Region,cRegion,Sales_Channel,cChannel,Category,cCat) -> 146 | F29: =IFERROR(B29/E29,0) -> 1101.4877 | G29: =IFERROR(AVERAGEIFS(Customer_Rating,Order_Date,">="&$A29,Order_Date,"<"&EDATE($A29,1),Year,cYear,Region,cRegion,Sales_Channel,cChannel,Category,cCat),0) -> 4.0291262 | H29: =IFERROR(SUMIFS(Returned,Order_Date,">="&$A29,Order_Date,"<"&EDATE($A29,1),Year,cYear,Region,cRegion,Sales_Channel,cChannel,Category,cCat)/COUNTIFS(Order_Date,">="&$A29,Order_Date,"<"&EDATE($A29,1),Year,cYear,Region,cRegion,Sales_Channel,cChannel,Category,cCat),0) -> 0.089041096 | I29: =IFERROR(AVERAGEIFS(Delivery_Days,Order_Date,">="&$A29,Order_Date,"<"&EDATE($A29,1),Year,cYear,Region,cRegion,Sales_Channel,cChannel,Category,cCat),0) -> 3.2191781 | J29: =SUMIFS(Quantity,Order_Date,">="&$A29,Order_Date,"<"&EDATE($A29,1),Year,cYear,Region,cRegion,Sales_Channel,cChannel,Category,cCat) -> 226 | K29: =SUMIFS(Ad_Spend,Ad_Month,">="&$A29,Ad_Month,"<"&EDATE($A29,1),Ad_Year,cYear,Ad_Region,cRegion) -> 32260
A30: =EDATE(A29,1) -> 45413 | B30: =SUMIFS(Net_Revenue,Order_Date,">="&$A30,Order_Date,"<"&EDATE($A30,1),Year,cYear,Region,cRegion,Sales_Channel,cChannel,Category,cCat) -> 174244.5 | C30: =SUMIFS(Profit,Order_Date,">="&$A30,Order_Date,"<"&EDATE($A30,1),Year,cYear,Region,cRegion,Sales_Channel,cChannel,Category,cCat) -> 73698.5 | D30: =IFERROR(C30/B30,0) -> 0.42296027 | E30: =COUNTIFS(Order_Date,">="&$A30,Order_Date,"<"&EDATE($A30,1),Year,cYear,Region,cRegion,Sales_Channel,cChannel,Category,cCat) -> 155 | F30: =IFERROR(B30/E30,0) -> 1124.1581 | G30: =IFERROR(AVERAGEIFS(Customer_Rating,Order_Date,">="&$A30,Order_Date,"<"&EDATE($A30,1),Year,cYear,Region,cRegion,Sales_Channel,cChannel,Category,cCat),0) -> 4.05 | H30: =IFERROR(SUMIFS(Returned,Order_Date,">="&$A30,Order_Date,"<"&EDATE($A30,1),Year,cYear,Region,cRegion,Sales_Channel,cChannel,Category,cCat)/COUNTIFS(Order_Date,">="&$A30,Order_Date,"<"&EDATE($A30,1),Year,cYear,Region,cRegion,Sales_Channel,cChannel,Category,cCat),0) -> 0.077419355 | I30: =IFERROR(AVERAGEIFS(Delivery_Days,Order_Date,">="&$A30,Order_Date,"<"&EDATE($A30,1),Year,cYear,Region,cRegion,Sales_Channel,cChannel,Category,cCat),0) -> 3.1612903 | J30: =SUMIFS(Quantity,Order_Date,">="&$A30,Order_Date,"<"&EDATE($A30,1),Year,cYear,Region,cRegion,Sales_Channel,cChannel,Category,cCat) -> 242 | K30: =SUMIFS(Ad_Spend,Ad_Month,">="&$A30,Ad_Month,"<"&EDATE($A30,1),Ad_Year,cYear,Ad_Region,cRegion) -> 34050
A31: =EDATE(A30,1) -> 45444 | B31: =SUMIFS(Net_Revenue,Order_Date,">="&$A31,Order_Date,"<"&EDATE($A31,1),Year,cYear,Region,cRegion,Sales_Channel,cChannel,Category,cCat) -> 161054 | C31: =SUMIFS(Profit,Order_Date,">="&$A31,Order_Date,"<"&EDATE($A31,1),Year,cYear,Region,cRegion,Sales_Channel,cChannel,Category,cCat) -> 67487 | D31: =IFERROR(C31/B31,0) -> 0.41903337 | E31: =COUNTIFS(Order_Date,">="&$A31,Order_Date,"<"&EDATE($A31,1),Year,cYear,Region,cRegion,Sales_Channel,cChannel,Category,cCat) -> 153 | F31: =IFERROR(B31/E31,0) -> 1052.6405 | G31: =IFERROR(AVERAGEIFS(Customer_Rating,Order_Date,">="&$A31,Order_Date,"<"&EDATE($A31,1),Year,cYear,Region,cRegion,Sales_Channel,cChannel,Category,cCat),0) -> 3.8672566 | H31: =IFERROR(SUMIFS(Returned,Order_Date,">="&$A31,Order_Date,"<"&EDATE($A31,1),Year,cYear,Region,cRegion,Sales_Channel,cChannel,Category,cCat)/COUNTIFS(Order_Date,">="&$A31,Order_Date,"<"&EDATE($A31,1),Year,cYear,Region,cRegion,Sales_Channel,cChannel,Category,cCat),0) -> 0.11111111 | I31: =IFERROR(AVERAGEIFS(Delivery_Days,Order_Date,">="&$A31,Order_Date,"<"&EDATE($A31,1),Year,cYear,Region,cRegion,Sales_Channel,cChannel,Category,cCat),0) -> 3.2418301 | J31: =SUMIFS(Quantity,Order_Date,">="&$A31,Order_Date,"<"&EDATE($A31,1),Year,cYear,Region,cRegion,Sales_Channel,cChannel,Category,cCat) -> 236 | K31: =SUMIFS(Ad_Spend,Ad_Month,">="&$A31,Ad_Month,"<"&EDATE($A31,1),Ad_Year,cYear,Ad_Region,cRegion) -> 32060
A32: =EDATE(A31,1) -> 45474 | B32: =SUMIFS(Net_Revenue,Order_Date,">="&$A32,Order_Date,"<"&EDATE($A32,1),Year,cYear,Region,cRegion,Sales_Channel,cChannel,Category,cCat) -> 171014.2 | C32: =SUMIFS(Profit,Order_Date,">="&$A32,Order_Date,"<"&EDATE($A32,1),Year,cYear,Region,cRegion,Sales_Channel,cChannel,Category,cCat) -> 73967.2 | D32: =IFERROR(C32/B32,0) -> 0.43252081 | E32: =COUNTIFS(Order_Date,">="&$A32,Order_Date,"<"&EDATE($A32,1),Year,cYear,Region,cRegion,Sales_Channel,cChannel,Category,cCat) -> 172 | F32: =IFERROR(B32/E32,0) -> 994.2686 | G32: =IFERROR(AVERAGEIFS(Customer_Rating,Order_Date,">="&$A32,Order_Date,"<"&EDATE($A32,1),Year,cYear,Region,cRegion,Sales_Channel,cChannel,Category,cCat),0) -> 3.9016393 | H32: =IFERROR(SUMIFS(Returned,Order_Date,">="&$A32,Order_Date,"<"&EDATE($A32,1),Year,cYear,Region,cRegion,Sales_Channel,cChannel,Category,cCat)/COUNTIFS(Order_Date,">="&$A32,Order_Date,"<"&EDATE($A32,1),Year,cYear,Region,cRegion,Sales_Channel,cChannel,Category,cCat),0) -> 0.10465116 | I32: =IFERROR(AVERAGEIFS(Delivery_Days,Order_Date,">="&$A32,Order_Date,"<"&EDATE($A32,1),Year,cYear,Region,cRegion,Sales_Channel,cChannel,Category,cCat),0) -> 3.2674419 | J32: =SUMIFS(Quantity,Order_Date,">="&$A32,Order_Date,"<"&EDATE($A32,1),Year,cYear,Region,cRegion,Sales_Channel,cChannel,Category,cCat) -> 243 | K32: =SUMIFS(Ad_Spend,Ad_Month,">="&$A32,Ad_Month,"<"&EDATE($A32,1),Ad_Year,cYear,Ad_Region,cRegion) -> 37030
A33: =EDATE(A32,1) -> 45505 | B33: =SUMIFS(Net_Revenue,Order_Date,">="&$A33,Order_Date,"<"&EDATE($A33,1),Year,cYear,Region,cRegion,Sales_Channel,cChannel,Category,cCat) -> 154762.2 | C33: =SUMIFS(Profit,Order_Date,">="&$A33,Order_Date,"<"&EDATE($A33,1),Year,cYear,Region,cRegion,Sales_Channel,cChannel,Category,cCat) -> 64085.2 | D33: =IFERROR(C33/B33,0) -> 0.41408819 | E33: =COUNTIFS(Order_Date,">="&$A33,Order_Date,"<"&EDATE($A33,1),Year,cYear,Region,cRegion,Sales_Channel,cChannel,Category,cCat) -> 144 | F33: =IFERROR(B33/E33,0) -> 1074.7375 | G33: =IFERROR(AVERAGEIFS(Customer_Rating,Order_Date,">="&$A33,Order_Date,"<"&EDATE($A33,1),Year,cYear,Region,cRegion,Sales_Channel,cChannel,Category,cCat),0) -> 4.010101 | H33: =IFERROR(SUMIFS(Returned,Order_Date,">="&$A33,Order_Date,"<"&EDATE($A33,1),Year,cYear,Region,cRegion,Sales_Channel,cChannel,Category,cCat)/COUNTIFS(Order_Date,">="&$A33,Order_Date,"<"&EDATE($A33,1),Year,cYear,Region,cRegion,Sales_Channel,cChannel,Category,cCat),0) -> 0.11805556 | I33: =IFERROR(AVERAGEIFS(Delivery_Days,Order_Date,">="&$A33,Order_Date,"<"&EDATE($A33,1),Year,cYear,Region,cRegion,Sales_Channel,cChannel,Category,cCat),0) -> 3.0763889 | J33: =SUMIFS(Quantity,Order_Date,">="&$A33,Order_Date,"<"&EDATE($A33,1),Year,cYear,Region,cRegion,Sales_Channel,cChannel,Category,cCat) -> 214 | K33: =SUMIFS(Ad_Spend,Ad_Month,">="&$A33,Ad_Month,"<"&EDATE($A33,1),Ad_Year,cYear,Ad_Region,cRegion) -> 34130
A34: =EDATE(A33,1) -> 45536 | B34: =SUMIFS(Net_Revenue,Order_Date,">="&$A34,Order_Date,"<"&EDATE($A34,1),Year,cYear,Region,cRegion,Sales_Channel,cChannel,Category,cCat) -> 210860.25 | C34: =SUMIFS(Profit,Order_Date,">="&$A34,Order_Date,"<"&EDATE($A34,1),Year,cYear,Region,cRegion,Sales_Channel,cChannel,Category,cCat) -> 88211.25 | D34: =IFERROR(C34/B34,0) -> 0.41833987 | E34: =COUNTIFS(Order_Date,">="&$A34,Order_Date,"<"&EDATE($A34,1),Year,cYear,Region,cRegion,Sales_Channel,cChannel,Category,cCat) -> 189 | F34: =IFERROR(B34/E34,0) -> 1115.6627 | G34: =IFERROR(AVERAGEIFS(Customer_Rating,Order_Date,">="&$A34,Order_Date,"<"&EDATE($A34,1),Year,cYear,Region,cRegion,Sales_Channel,cChannel,Category,cCat),0) -> 3.9477612 | H34: =IFERROR(SUMIFS(Returned,Order_Date,">="&$A34,Order_Date,"<"&EDATE($A34,1),Year,cYear,Region,cRegion,Sales_Channel,cChannel,Category,cCat)/COUNTIFS(Order_Date,">="&$A34,Order_Date,"<"&EDATE($A34,1),Year,cYear,Region,cRegion,Sales_Channel,cChannel,Category,cCat),0) -> 0.095238095 | I34: =IFERROR(AVERAGEIFS(Delivery_Days,Order_Date,">="&$A34,Order_Date,"<"&EDATE($A34,1),Year,cYear,Region,cRegion,Sales_Channel,cChannel,Category,cCat),0) -> 3.1904762 | J34: =SUMIFS(Quantity,Order_Date,">="&$A34,Order_Date,"<"&EDATE($A34,1),Year,cYear,Region,cRegion,Sales_Channel,cChannel,Category,cCat) -> 286 | K34: =SUMIFS(Ad_Spend,Ad_Month,">="&$A34,Ad_Month,"<"&EDATE($A34,1),Ad_Year,cYear,Ad_Region,cRegion) -> 41190
A35: =EDATE(A34,1) -> 45566 | B35: =SUMIFS(Net_Revenue,Order_Date,">="&$A35,Order_Date,"<"&EDATE($A35,1),Year,cYear,Region,cRegion,Sales_Channel,cChannel,Category,cCat) -> 274168.75 | C35: =SUMIFS(Profit,Order_Date,">="&$A35,Order_Date,"<"&EDATE($A35,1),Year,cYear,Region,cRegion,Sales_Channel,cChannel,Category,cCat) -> 89216.75 | D35: =IFERROR(C35/B35,0) -> 0.32540817 | E35: =COUNTIFS(Order_Date,">="&$A35,Order_Date,"<"&EDATE($A35,1),Year,cYear,Region,cRegion,Sales_Channel,cChannel,Category,cCat) -> 286 | F35: =IFERROR(B35/E35,0) -> 958.63199 | G35: =IFERROR(AVERAGEIFS(Customer_Rating,Order_Date,">="&$A35,Order_Date,"<"&EDATE($A35,1),Year,cYear,Region,cRegion,Sales_Channel,cChannel,Category,cCat),0) -> 3.725 | H35: =IFERROR(SUMIFS(Returned,Order_Date,">="&$A35,Order_Date,"<"&EDATE($A35,1),Year,cYear,Region,cRegion,Sales_Channel,cChannel,Category,cCat)/COUNTIFS(Order_Date,">="&$A35,Order_Date,"<"&EDATE($A35,1),Year,cYear,Region,cRegion,Sales_Channel,cChannel,Category,cCat),0) -> 0.11538462 | I35: =IFERROR(AVERAGEIFS(Delivery_Days,Order_Date,">="&$A35,Order_Date,"<"&EDATE($A35,1),Year,cYear,Region,cRegion,Sales_Channel,cChannel,Category,cCat),0) -> 3.7377622 | J35: =SUMIFS(Quantity,Order_Date,">="&$A35,Order_Date,"<"&EDATE($A35,1),Year,cYear,Region,cRegion,Sales_Channel,cChannel,Category,cCat) -> 451 | K35: =SUMIFS(Ad_Spend,Ad_Month,">="&$A35,Ad_Month,"<"&EDATE($A35,1),Ad_Year,cYear,Ad_Region,cRegion) -> 55090
A36: =EDATE(A35,1) -> 45597 | B36: =SUMIFS(Net_Revenue,Order_Date,">="&$A36,Order_Date,"<"&EDATE($A36,1),Year,cYear,Region,cRegion,Sales_Channel,cChannel,Category,cCat) -> 252007.25 | C36: =SUMIFS(Profit,Order_Date,">="&$A36,Order_Date,"<"&EDATE($A36,1),Year,cYear,Region,cRegion,Sales_Channel,cChannel,Category,cCat) -> 79336.25 | D36: =IFERROR(C36/B36,0) -> 0.31481733 | E36: =COUNTIFS(Order_Date,">="&$A36,Order_Date,"<"&EDATE($A36,1),Year,cYear,Region,cRegion,Sales_Channel,cChannel,Category,cCat) -> 233 | F36: =IFERROR(B36/E36,0) -> 1081.5762 | G36: =IFERROR(AVERAGEIFS(Customer_Rating,Order_Date,">="&$A36,Order_Date,"<"&EDATE($A36,1),Year,cYear,Region,cRegion,Sales_Channel,cChannel,Category,cCat),0) -> 3.8466258 | H36: =IFERROR(SUMIFS(Returned,Order_Date,">="&$A36,Order_Date,"<"&EDATE($A36,1),Year,cYear,Region,cRegion,Sales_Channel,cChannel,Category,cCat)/COUNTIFS(Order_Date,">="&$A36,Order_Date,"<"&EDATE($A36,1),Year,cYear,Region,cRegion,Sales_Channel,cChannel,Category,cCat),0) -> 0.12446352 | I36: =IFERROR(AVERAGEIFS(Delivery_Days,Order_Date,">="&$A36,Order_Date,"<"&EDATE($A36,1),Year,cYear,Region,cRegion,Sales_Channel,cChannel,Category,cCat),0) -> 3.7682403 | J36: =SUMIFS(Quantity,Order_Date,">="&$A36,Order_Date,"<"&EDATE($A36,1),Year,cYear,Region,cRegion,Sales_Channel,cChannel,Category,cCat) -> 394 | K36: =SUMIFS(Ad_Spend,Ad_Month,">="&$A36,Ad_Month,"<"&EDATE($A36,1),Ad_Year,cYear,Ad_Region,cRegion) -> 54530
A37: =EDATE(A36,1) -> 45627 | B37: =SUMIFS(Net_Revenue,Order_Date,">="&$A37,Order_Date,"<"&EDATE($A37,1),Year,cYear,Region,cRegion,Sales_Channel,cChannel,Category,cCat) -> 229843.4 | C37: =SUMIFS(Profit,Order_Date,">="&$A37,Order_Date,"<"&EDATE($A37,1),Year,cYear,Region,cRegion,Sales_Channel,cChannel,Category,cCat) -> 98163.4 | D37: =IFERROR(C37/B37,0) -> 0.42708818 | E37: =COUNTIFS(Order_Date,">="&$A37,Order_Date,"<"&EDATE($A37,1),Year,cYear,Region,cRegion,Sales_Channel,cChannel,Category,cCat) -> 219 | F37: =IFERROR(B37/E37,0) -> 1049.5132 | G37: =IFERROR(AVERAGEIFS(Customer_Rating,Order_Date,">="&$A37,Order_Date,"<"&EDATE($A37,1),Year,cYear,Region,cRegion,Sales_Channel,cChannel,Category,cCat),0) -> 3.9735099 | H37: =IFERROR(SUMIFS(Returned,Order_Date,">="&$A37,Order_Date,"<"&EDATE($A37,1),Year,cYear,Region,cRegion,Sales_Channel,cChannel,Category,cCat)/COUNTIFS(Order_Date,">="&$A37,Order_Date,"<"&EDATE($A37,1),Year,cYear,Region,cRegion,Sales_Channel,cChannel,Category,cCat),0) -> 0.095890411 | I37: =IFERROR(AVERAGEIFS(Delivery_Days,Order_Date,">="&$A37,Order_Date,"<"&EDATE($A37,1),Year,cYear,Region,cRegion,Sales_Channel,cChannel,Category,cCat),0) -> 3.173516 | J37: =SUMIFS(Quantity,Order_Date,">="&$A37,Order_Date,"<"&EDATE($A37,1),Year,cYear,Region,cRegion,Sales_Channel,cChannel,Category,cCat) -> 339 | K37: =SUMIFS(Ad_Spend,Ad_Month,">="&$A37,Ad_Month,"<"&EDATE($A37,1),Ad_Year,cYear,Ad_Region,cRegion) -> 42120
A38: =EDATE(A37,1) -> 45658 | B38: =SUMIFS(Net_Revenue,Order_Date,">="&$A38,Order_Date,"<"&EDATE($A38,1),Year,cYear,Region,cRegion,Sales_Channel,cChannel,Category,cCat) -> 251689.1 | C38: =SUMIFS(Profit,Order_Date,">="&$A38,Order_Date,"<"&EDATE($A38,1),Year,cYear,Region,cRegion,Sales_Channel,cChannel,Category,cCat) -> 106402.1 | D38: =IFERROR(C38/B38,0) -> 0.42275212 | E38: =COUNTIFS(Order_Date,">="&$A38,Order_Date,"<"&EDATE($A38,1),Year,cYear,Region,cRegion,Sales_Channel,cChannel,Category,cCat) -> 216 | F38: =IFERROR(B38/E38,0) -> 1165.2273 | G38: =IFERROR(AVERAGEIFS(Customer_Rating,Order_Date,">="&$A38,Order_Date,"<"&EDATE($A38,1),Year,cYear,Region,cRegion,Sales_Channel,cChannel,Category,cCat),0) -> 3.82 | H38: =IFERROR(SUMIFS(Returned,Order_Date,">="&$A38,Order_Date,"<"&EDATE($A38,1),Year,cYear,Region,cRegion,Sales_Channel,cChannel,Category,cCat)/COUNTIFS(Order_Date,">="&$A38,Order_Date,"<"&EDATE($A38,1),Year,cYear,Region,cRegion,Sales_Channel,cChannel,Category,cCat),0) -> 0.11111111 | I38: =IFERROR(AVERAGEIFS(Delivery_Days,Order_Date,">="&$A38,Order_Date,"<"&EDATE($A38,1),Year,cYear,Region,cRegion,Sales_Channel,cChannel,Category,cCat),0) -> 3.2407407 | J38: =SUMIFS(Quantity,Order_Date,">="&$A38,Order_Date,"<"&EDATE($A38,1),Year,cYear,Region,cRegion,Sales_Channel,cChannel,Category,cCat) -> 339 | K38: =SUMIFS(Ad_Spend,Ad_Month,">="&$A38,Ad_Month,"<"&EDATE($A38,1),Ad_Year,cYear,Ad_Region,cRegion) -> 48100
... A49: =EDATE(A48,1) -> 45992 | B49: =SUMIFS(Net_Revenue,Order_Date,">="&$A49,Order_Date,"<"&EDATE($A49,1),Year,cYear,Region,cRegion,Sales_Channel,cChannel,Category,cCat) -> 214490.8 | C49: =SUMIFS(Profit,Order_Date,">="&$A49,Order_Date,"<"&EDATE($A49,1),Year,cYear,Region,cRegion,Sales_Channel,cChannel,Category,cCat) -> 90854.8 | D49: =IFERROR(C49/B49,0) -> 0.42358367 | E49: =COUNTIFS(Order_Date,">="&$A49,Order_Date,"<"&EDATE($A49,1),Year,cYear,Region,cRegion,Sales_Channel,cChannel,Category,cCat) -> 201 | F49: =IFERROR(B49/E49,0) -> 1067.1184 | G49: =IFERROR(AVERAGEIFS(Customer_Rating,Order_Date,">="&$A49,Order_Date,"<"&EDATE($A49,1),Year,cYear,Region,cRegion,Sales_Channel,cChannel,Category,cCat),0) -> 3.9130435 | H49: =IFERROR(SUMIFS(Returned,Order_Date,">="&$A49,Order_Date,"<"&EDATE($A49,1),Year,cYear,Region,cRegion,Sales_Channel,cChannel,Category,cCat)/COUNTIFS(Order_Date,">="&$A49,Order_Date,"<"&EDATE($A49,1),Year,cYear,Region,cRegion,Sales_Channel,cChannel,Category,cCat),0) -> 0.094527363 | I49: =IFERROR(AVERAGEIFS(Delivery_Days,Order_Date,">="&$A49,Order_Date,"<"&EDATE($A49,1),Year,cYear,Region,cRegion,Sales_Channel,cChannel,Category,cCat),0) -> 3.4228856 | J49: =SUMIFS(Quantity,Order_Date,">="&$A49,Order_Date,"<"&EDATE($A49,1),Year,cYear,Region,cRegion,Sales_Channel,cChannel,Category,cCat) -> 303 | K49: =SUMIFS(Ad_Spend,Ad_Month,">="&$A49,Ad_Month,"<"&EDATE($A49,1),Ad_Year,cYear,Ad_Region,cRegion) -> 49620
A51: 2024 vs 2025
A52: Month | B52: 2024 Revenue | C52: 2025 Revenue | D52: Growth %
A53: Jan | B53: =SUMIFS(Net_Revenue,Order_Date,">="&DATE(2024,ROWS($A$53:A53),1),Order_Date,"<"&EDATE(DATE(2024,ROWS($A$53:A53),1),1),Region,cRegion,Sales_Channel,cChannel,Category,cCat) -> 219793.3 | C53: =SUMIFS(Net_Revenue,Order_Date,">="&DATE(2025,ROWS($A$53:A53),1),Order_Date,"<"&EDATE(DATE(2025,ROWS($A$53:A53),1),1),Region,cRegion,Sales_Channel,cChannel,Category,cCat) -> 251689.1 | D53: =IF(B53=0,"",C53/B53-1) -> 0.14511725
A54: Feb | B54: =SUMIFS(Net_Revenue,Order_Date,">="&DATE(2024,ROWS($A$53:A54),1),Order_Date,"<"&EDATE(DATE(2024,ROWS($A$53:A54),1),1),Region,cRegion,Sales_Channel,cChannel,Category,cCat) -> 97871.1 | C54: =SUMIFS(Net_Revenue,Order_Date,">="&DATE(2025,ROWS($A$53:A54),1),Order_Date,"<"&EDATE(DATE(2025,ROWS($A$53:A54),1),1),Region,cRegion,Sales_Channel,cChannel,Category,cCat) -> 190110 | D54: =IF(B54=0,"",C54/B54-1) -> 0.94245288
A55: Mar | B55: =SUMIFS(Net_Revenue,Order_Date,">="&DATE(2024,ROWS($A$53:A55),1),Order_Date,"<"&EDATE(DATE(2024,ROWS($A$53:A55),1),1),Region,cRegion,Sales_Channel,cChannel,Category,cCat) -> 150200.35 | C55: =SUMIFS(Net_Revenue,Order_Date,">="&DATE(2025,ROWS($A$53:A55),1),Order_Date,"<"&EDATE(DATE(2025,ROWS($A$53:A55),1),1),Region,cRegion,Sales_Channel,cChannel,Category,cCat) -> 264242.35 | D55: =IF(B55=0,"",C55/B55-1) -> 0.75926587
A56: Apr | B56: =SUMIFS(Net_Revenue,Order_Date,">="&DATE(2024,ROWS($A$53:A56),1),Order_Date,"<"&EDATE(DATE(2024,ROWS($A$53:A56),1),1),Region,cRegion,Sales_Channel,cChannel,Category,cCat) -> 160817.2 | C56: =SUMIFS(Net_Revenue,Order_Date,">="&DATE(2025,ROWS($A$53:A56),1),Order_Date,"<"&EDATE(DATE(2025,ROWS($A$53:A56),1),1),Region,cRegion,Sales_Channel,cChannel,Category,cCat) -> 253045.2 | D56: =IF(B56=0,"",C56/B56-1) -> 0.57349587
A57: May | B57: =SUMIFS(Net_Revenue,Order_Date,">="&DATE(2024,ROWS($A$53:A57),1),Order_Date,"<"&EDATE(DATE(2024,ROWS($A$53:A57),1),1),Region,cRegion,Sales_Channel,cChannel,Category,cCat) -> 174244.5 | C57: =SUMIFS(Net_Revenue,Order_Date,">="&DATE(2025,ROWS($A$53:A57),1),Order_Date,"<"&EDATE(DATE(2025,ROWS($A$53:A57),1),1),Region,cRegion,Sales_Channel,cChannel,Category,cCat) -> 167565.1 | D57: =IF(B57=0,"",C57/B57-1) -> -0.038333491
A58: Jun | B58: =SUMIFS(Net_Revenue,Order_Date,">="&DATE(2024,ROWS($A$53:A58),1),Order_Date,"<"&EDATE(DATE(2024,ROWS($A$53:A58),1),1),Region,cRegion,Sales_Channel,cChannel,Category,cCat) -> 161054 | C58: =SUMIFS(Net_Revenue,Order_Date,">="&DATE(2025,ROWS($A$53:A58),1),Order_Date,"<"&EDATE(DATE(2025,ROWS($A$53:A58),1),1),Region,cRegion,Sales_Channel,cChannel,Category,cCat) -> 230474.25 | D58: =IF(B58=0,"",C58/B58-1) -> 0.43103711
A59: Jul | B59: =SUMIFS(Net_Revenue,Order_Date,">="&DATE(2024,ROWS($A$53:A59),1),Order_Date,"<"&EDATE(DATE(2024,ROWS($A$53:A59),1),1),Region,cRegion,Sales_Channel,cChannel,Category,cCat) -> 171014.2 | C59: =SUMIFS(Net_Revenue,Order_Date,">="&DATE(2025,ROWS($A$53:A59),1),Order_Date,"<"&EDATE(DATE(2025,ROWS($A$53:A59),1),1),Region,cRegion,Sales_Channel,cChannel,Category,cCat) -> 190477.15 | D59: =IF(B59=0,"",C59/B59-1) -> 0.11380897
A60: Aug | B60: =SUMIFS(Net_Revenue,Order_Date,">="&DATE(2024,ROWS($A$53:A60),1),Order_Date,"<"&EDATE(DATE(2024,ROWS($A$53:A60),1),1),Region,cRegion,Sales_Channel,cChannel,Category,cCat) -> 154762.2 | C60: =SUMIFS(Net_Revenue,Order_Date,">="&DATE(2025,ROWS($A$53:A60),1),Order_Date,"<"&EDATE(DATE(2025,ROWS($A$53:A60),1),1),Region,cRegion,Sales_Channel,cChannel,Category,cCat) -> 224313.95 | D60: =IF(B60=0,"",C60/B60-1) -> 0.44941045
A61: Sep | B61: =SUMIFS(Net_Revenue,Order_Date,">="&DATE(2024,ROWS($A$53:A61),1),Order_Date,"<"&EDATE(DATE(2024,ROWS($A$53:A61),1),1),Region,cRegion,Sales_Channel,cChannel,Category,cCat) -> 210860.25 | C61: =SUMIFS(Net_Revenue,Order_Date,">="&DATE(2025,ROWS($A$53:A61),1),Order_Date,"<"&EDATE(DATE(2025,ROWS($A$53:A61),1),1),Region,cRegion,Sales_Channel,cChannel,Category,cCat) -> 224466.7 | D61: =IF(B61=0,"",C61/B61-1) -> 0.064528284
A62: Oct | B62: =SUMIFS(Net_Revenue,Order_Date,">="&DATE(2024,ROWS($A$53:A62),1),Order_Date,"<"&EDATE(DATE(2024,ROWS($A$53:A62),1),1),Region,cRegion,Sales_Channel,cChannel,Category,cCat) -> 274168.75 | C62: =SUMIFS(Net_Revenue,Order_Date,">="&DATE(2025,ROWS($A$53:A62),1),Order_Date,"<"&EDATE(DATE(2025,ROWS($A$53:A62),1),1),Region,cRegion,Sales_Channel,cChannel,Category,cCat) -> 352690.5 | D62: =IF(B62=0,"",C62/B62-1) -> 0.28639934
A63: Nov | B63: =SUMIFS(Net_Revenue,Order_Date,">="&DATE(2024,ROWS($A$53:A63),1),Order_Date,"<"&EDATE(DATE(2024,ROWS($A$53:A63),1),1),Region,cRegion,Sales_Channel,cChannel,Category,cCat) -> 252007.25 | C63: =SUMIFS(Net_Revenue,Order_Date,">="&DATE(2025,ROWS($A$53:A63),1),Order_Date,"<"&EDATE(DATE(2025,ROWS($A$53:A63),1),1),Region,cRegion,Sales_Channel,cChannel,Category,cCat) -> 335940.85 | D63: =IF(B63=0,"",C63/B63-1) -> 0.33306026
A64: Dec | B64: =SUMIFS(Net_Revenue,Order_Date,">="&DATE(2024,ROWS($A$53:A64),1),Order_Date,"<"&EDATE(DATE(2024,ROWS($A$53:A64),1),1),Region,cRegion,Sales_Channel,cChannel,Category,cCat) -> 229843.4 | C64: =SUMIFS(Net_Revenue,Order_Date,">="&DATE(2025,ROWS($A$53:A64),1),Order_Date,"<"&EDATE(DATE(2025,ROWS($A$53:A64),1),1),Region,cRegion,Sales_Channel,cChannel,Category,cCat) -> 214490.8 | D64: =IF(B64=0,"",C64/B64-1) -> -0.066795914
A67: By Category
A68: Category | B68: Revenue | C68: Profit | D68: Margin % | E68: Orders | F68: Return Rate | G68: Avg Rating | H68: Share %
A69: Skincare | B69: =SUMIFS(Net_Revenue,Year,cYear,Region,cRegion,Sales_Channel,cChannel,Category,cCat,Category,A69) -> 635906.9 | C69: =SUMIFS(Profit,Year,cYear,Region,cRegion,Sales_Channel,cChannel,Category,cCat,Category,A69) -> 348934.9 | D69: =IFERROR(C69/B69,0) -> 0.5487201 | E69: =COUNTIFS(Year,cYear,Region,cRegion,Sales_Channel,cChannel,Category,cCat,Category,A69) -> 1014 | F69: =IFERROR(SUMIFS(Returned,Year,cYear,Region,cRegion,Sales_Channel,cChannel,Category,cCat,Category,$A69)/E69,0) -> 0.08974359 | G69: =IFERROR(AVERAGEIFS(Customer_Rating,Year,cYear,Region,cRegion,Sales_Channel,cChannel,Category,cCat,Category,A69),0) -> 3.9170068 | H69: =IFERROR(B69/$B$11,0) -> 0.12332997
A70: Haircare | B70: =SUMIFS(Net_Revenue,Year,cYear,Region,cRegion,Sales_Channel,cChannel,Category,cCat,Category,A70) -> 418120.7 | C70: =SUMIFS(Profit,Year,cYear,Region,cRegion,Sales_Channel,cChannel,Category,cCat,Category,A70) -> 183751.7 | D70: =IFERROR(C70/B70,0) -> 0.43947047 | E70: =COUNTIFS(Year,cYear,Region,cRegion,Sales_Channel,cChannel,Category,cCat,Category,A70) -> 806 | F70: =IFERROR(SUMIFS(Returned,Year,cYear,Region,cRegion,Sales_Channel,cChannel,Category,cCat,Category,$A70)/E70,0) -> 0.076923077 | G70: =IFERROR(AVERAGEIFS(Customer_Rating,Year,cYear,Region,cRegion,Sales_Channel,cChannel,Category,cCat,Category,A70),0) -> 3.8619469 | H70: =IFERROR(B70/$B$11,0) -> 0.081091767
A71: Apparel | B71: =SUMIFS(Net_Revenue,Year,cYear,Region,cRegion,Sales_Channel,cChannel,Category,cCat,Category,A71) -> 1433238 | C71: =SUMIFS(Profit,Year,cYear,Region,cRegion,Sales_Channel,cChannel,Category,cCat,Category,A71) -> 635168.95 | D71: =IFERROR(C71/B71,0) -> 0.44317062 | E71: =COUNTIFS(Year,cYear,Region,cRegion,Sales_Channel,cChannel,Category,cCat,Category,A71) -> 801 | F71: =IFERROR(SUMIFS(Returned,Year,cYear,Region,cRegion,Sales_Channel,cChannel,Category,cCat,Category,$A71)/E71,0) -> 0.15480649 | G71: =IFERROR(AVERAGEIFS(Customer_Rating,Year,cYear,Region,cRegion,Sales_Channel,cChannel,Category,cCat,Category,A71),0) -> 3.9320557 | H71: =IFERROR(B71/$B$11,0) -> 0.2779671
A72: Footwear | B72: =SUMIFS(Net_Revenue,Year,cYear,Region,cRegion,Sales_Channel,cChannel,Category,cCat,Category,A72) -> 968884.25 | C72: =SUMIFS(Profit,Year,cYear,Region,cRegion,Sales_Channel,cChannel,Category,cCat,Category,A72) -> 379840.25 | D72: =IFERROR(C72/B72,0) -> 0.39203883 | E72: =COUNTIFS(Year,cYear,Region,cRegion,Sales_Channel,cChannel,Category,cCat,Category,A72) -> 706 | F72: =IFERROR(SUMIFS(Returned,Year,cYear,Region,cRegion,Sales_Channel,cChannel,Category,cCat,Category,$A72)/E72,0) -> 0.16713881 | G72: =IFERROR(AVERAGEIFS(Customer_Rating,Year,cYear,Region,cRegion,Sales_Channel,cChannel,Category,cCat,Category,A72),0) -> 3.9541109 | H72: =IFERROR(B72/$B$11,0) -> 0.18790874
A73: Home & Kitchen | B73: =SUMIFS(Net_Revenue,Year,cYear,Region,cRegion,Sales_Channel,cChannel,Category,cCat,Category,A73) -> 603725.2 | C73: =SUMIFS(Profit,Year,cYear,Region,cRegion,Sales_Channel,cChannel,Category,cCat,Category,A73) -> 247922.2 | D73: =IFERROR(C73/B73,0) -> 0.41065405 | E73: =COUNTIFS(Year,cYear,Region,cRegion,Sales_Channel,cChannel,Category,cCat,Category,A73) -> 424 | F73: =IFERROR(SUMIFS(Returned,Year,cYear,Region,cRegion,Sales_Channel,cChannel,Category,cCat,Category,$A73)/E73,0) -> 0.080188679 | G73: =IFERROR(AVERAGEIFS(Customer_Rating,Year,cYear,Region,cRegion,Sales_Channel,cChannel,Category,cCat,Category,A73),0) -> 3.9133574 | H73: =IFERROR(B73/$B$11,0) -> 0.11708854
A74: Electronics | B74: =SUMIFS(Net_Revenue,Year,cYear,Region,cRegion,Sales_Channel,cChannel,Category,cCat,Category,A74) -> 455520.2 | C74: =SUMIFS(Profit,Year,cYear,Region,cRegion,Sales_Channel,cChannel,Category,cCat,Category,A74) -> 68540.2 | D74: =IFERROR(C74/B74,0) -> 0.15046578 | E74: =COUNTIFS(Year,cYear,Region,cRegion,Sales_Channel,cChannel,Category,cCat,Category,A74) -> 366 | F74: =IFERROR(SUMIFS(Returned,Year,cYear,Region,cRegion,Sales_Channel,cChannel,Category,cCat,Category,$A74)/E74,0) -> 0.06010929 | G74: =IFERROR(AVERAGEIFS(Customer_Rating,Year,cYear,Region,cRegion,Sales_Channel,cChannel,Category,cCat,Category,A74),0) -> 3.9027237 | H74: =IFERROR(B74/$B$11,0) -> 0.088345154
A75: Wellness | B75: =SUMIFS(Net_Revenue,Year,cYear,Region,cRegion,Sales_Channel,cChannel,Category,cCat,Category,A75) -> 640747.25 | C75: =SUMIFS(Profit,Year,cYear,Region,cRegion,Sales_Channel,cChannel,Category,cCat,Category,A75) -> 219096.25 | D75: =IFERROR(C75/B75,0) -> 0.34193865 | E75: =COUNTIFS(Year,cYear,Region,cRegion,Sales_Channel,cChannel,Category,cCat,Category,A75) -> 716 | F75: =IFERROR(SUMIFS(Returned,Year,cYear,Region,cRegion,Sales_Channel,cChannel,Category,cCat,Category,$A75)/E75,0) -> 0.072625698 | G75: =IFERROR(AVERAGEIFS(Customer_Rating,Year,cYear,Region,cRegion,Sales_Channel,cChannel,Category,cCat,Category,A75),0) -> 3.9150198 | H75: =IFERROR(B75/$B$11,0) -> 0.12426873
A78: By Channel
A79: Channel | B79: Revenue | C79: Profit | D79: Margin % | E79: Orders | F79: Return Rate | G79: Avg Rating | H79: Share % | I79: Avg Discount %
A80: Amazon | B80: =SUMIFS(Net_Revenue,Year,cYear,Region,cRegion,Sales_Channel,cChannel,Category,cCat,Sales_Channel,$A80) -> 1447389.7 | C80: =SUMIFS(Profit,Year,cYear,Region,cRegion,Sales_Channel,cChannel,Category,cCat,Sales_Channel,$A80) -> 551536.7 | D80: =IFERROR(C80/B80,0) -> 0.38105612 | E80: =COUNTIFS(Year,cYear,Region,cRegion,Sales_Channel,cChannel,Category,cCat,Sales_Channel,$A80) -> 1436 | F80: =IFERROR(SUMIFS(Returned,Year,cYear,Region,cRegion,Sales_Channel,cChannel,Category,cCat,Sales_Channel,$A80)/E80,0) -> 0.11072423 | G80: =IFERROR(AVERAGEIFS(Customer_Rating,Year,cYear,Region,cRegion,Sales_Channel,cChannel,Category,cCat,Sales_Channel,$A80),0) -> 3.9414683 | H80: =IFERROR(B80/$B$11,0) -> 0.28071174 | I80: =IFERROR(SUMIFS(Discount_Amount,Year,cYear,Region,cRegion,Sales_Channel,cChannel,Category,cCat,Sales_Channel,$A80)/SUMIFS(Gross_Sale,Year,cYear,Region,cRegion,Sales_Channel,cChannel,Category,cCat,Sales_Channel,$A80),0) -> 0.23660599
A81: Flipkart | B81: =SUMIFS(Net_Revenue,Year,cYear,Region,cRegion,Sales_Channel,cChannel,Category,cCat,Sales_Channel,$A81) -> 1180727.3 | C81: =SUMIFS(Profit,Year,cYear,Region,cRegion,Sales_Channel,cChannel,Category,cCat,Sales_Channel,$A81) -> 460775.35 | D81: =IFERROR(C81/B81,0) -> 0.39024704 | E81: =COUNTIFS(Year,cYear,Region,cRegion,Sales_Channel,cChannel,Category,cCat,Sales_Channel,$A81) -> 1144 | F81: =IFERROR(SUMIFS(Returned,Year,cYear,Region,cRegion,Sales_Channel,cChannel,Category,cCat,Sales_Channel,$A81)/E81,0) -> 0.094405594 | G81: =IFERROR(AVERAGEIFS(Customer_Rating,Year,cYear,Region,cRegion,Sales_Channel,cChannel,Category,cCat,Sales_Channel,$A81),0) -> 3.9167658 | H81: =IFERROR(B81/$B$11,0) -> 0.22899432 | I81: =IFERROR(SUMIFS(Discount_Amount,Year,cYear,Region,cRegion,Sales_Channel,cChannel,Category,cCat,Sales_Channel,$A81)/SUMIFS(Gross_Sale,Year,cYear,Region,cRegion,Sales_Channel,cChannel,Category,cCat,Sales_Channel,$A81),0) -> 0.22718366
A82: Website | B82: =SUMIFS(Net_Revenue,Year,cYear,Region,cRegion,Sales_Channel,cChannel,Category,cCat,Sales_Channel,$A82) -> 914734.45 | C82: =SUMIFS(Profit,Year,cYear,Region,cRegion,Sales_Channel,cChannel,Category,cCat,Sales_Channel,$A82) -> 387341.45 | D82: =IFERROR(C82/B82,0) -> 0.42344688 | E82: =COUNTIFS(Year,cYear,Region,cRegion,Sales_Channel,cChannel,Category,cCat,Sales_Channel,$A82) -> 832 | F82: =IFERROR(SUMIFS(Returned,Year,cYear,Region,cRegion,Sales_Channel,cChannel,Category,cCat,Sales_Channel,$A82)/E82,0) -> 0.094951923 | G82: =IFERROR(AVERAGEIFS(Customer_Rating,Year,cYear,Region,cRegion,Sales_Channel,cChannel,Category,cCat,Sales_Channel,$A82),0) -> 3.8010471 | H82: =IFERROR(B82/$B$11,0) -> 0.17740675 | I82: =IFERROR(SUMIFS(Discount_Amount,Year,cYear,Region,cRegion,Sales_Channel,cChannel,Category,cCat,Sales_Channel,$A82)/SUMIFS(Gross_Sale,Year,cYear,Region,cRegion,Sales_Channel,cChannel,Category,cCat,Sales_Channel,$A82),0) -> 0.17940355
A83: Myntra | B83: =SUMIFS(Net_Revenue,Year,cYear,Region,cRegion,Sales_Channel,cChannel,Category,cCat,Sales_Channel,$A83) -> 1162695.9 | C83: =SUMIFS(Profit,Year,cYear,Region,cRegion,Sales_Channel,cChannel,Category,cCat,Sales_Channel,$A83) -> 485389.85 | D83: =IFERROR(C83/B83,0) -> 0.41746932 | E83: =COUNTIFS(Year,cYear,Region,cRegion,Sales_Channel,cChannel,Category,cCat,Sales_Channel,$A83) -> 726 | F83: =IFERROR(SUMIFS(Returned,Year,cYear,Region,cRegion,Sales_Channel,cChannel,Category,cCat,Sales_Channel,$A83)/E83,0) -> 0.14049587 | G83: =IFERROR(AVERAGEIFS(Customer_Rating,Year,cYear,Region,cRegion,Sales_Channel,cChannel,Category,cCat,Sales_Channel,$A83),0) -> 4 | H83: =IFERROR(B83/$B$11,0) -> 0.22549723 | I83: =IFERROR(SUMIFS(Discount_Amount,Year,cYear,Region,cRegion,Sales_Channel,cChannel,Category,cCat,Sales_Channel,$A83)/SUMIFS(Gross_Sale,Year,cYear,Region,cRegion,Sales_Channel,cChannel,Category,cCat,Sales_Channel,$A83),0) -> 0.1975935
A84: Nykaa | B84: =SUMIFS(Net_Revenue,Year,cYear,Region,cRegion,Sales_Channel,cChannel,Category,cCat,Sales_Channel,$A84) -> 450595.1 | C84: =SUMIFS(Profit,Year,cYear,Region,cRegion,Sales_Channel,cChannel,Category,cCat,Sales_Channel,$A84) -> 198211.1 | D84: =IFERROR(C84/B84,0) -> 0.43988738 | E84: =COUNTIFS(Year,cYear,Region,cRegion,Sales_Channel,cChannel,Category,cCat,Sales_Channel,$A84) -> 695 | F84: =IFERROR(SUMIFS(Returned,Year,cYear,Region,cRegion,Sales_Channel,cChannel,Category,cCat,Sales_Channel,$A84)/E84,0) -> 0.079136691 | G84: =IFERROR(AVERAGEIFS(Customer_Rating,Year,cYear,Region,cRegion,Sales_Channel,cChannel,Category,cCat,Sales_Channel,$A84),0) -> 3.8969697 | H84: =IFERROR(B84/$B$11,0) -> 0.087389963 | I84: =IFERROR(SUMIFS(Discount_Amount,Year,cYear,Region,cRegion,Sales_Channel,cChannel,Category,cCat,Sales_Channel,$A84)/SUMIFS(Gross_Sale,Year,cYear,Region,cRegion,Sales_Channel,cChannel,Category,cCat,Sales_Channel,$A84),0) -> 0.24173387
A87: Payment mode by Region
A88: Region | B88: UPI | C88: COD | D88: Credit Card | E88: Debit Card | F88: Wallet
A89: North | B89: =COUNTIFS(Year,cYear,Region,cRegion,Sales_Channel,cChannel,Category,cCat,Region,$A89,Payment_Method,B$88) -> 680 | C89: =COUNTIFS(Year,cYear,Region,cRegion,Sales_Channel,cChannel,Category,cCat,Region,$A89,Payment_Method,C$88) -> 343 | D89: =COUNTIFS(Year,cYear,Region,cRegion,Sales_Channel,cChannel,Category,cCat,Region,$A89,Payment_Method,D$88) -> 199 | E89: =COUNTIFS(Year,cYear,Region,cRegion,Sales_Channel,cChannel,Category,cCat,Region,$A89,Payment_Method,E$88) -> 137 | F89: =COUNTIFS(Year,cYear,Region,cRegion,Sales_Channel,cChannel,Category,cCat,Region,$A89,Payment_Method,F$88) -> 116
A90: South | B90: =COUNTIFS(Year,cYear,Region,cRegion,Sales_Channel,cChannel,Category,cCat,Region,$A90,Payment_Method,B$88) -> 646 | C90: =COUNTIFS(Year,cYear,Region,cRegion,Sales_Channel,cChannel,Category,cCat,Region,$A90,Payment_Method,C$88) -> 296 | D90: =COUNTIFS(Year,cYear,Region,cRegion,Sales_Channel,cChannel,Category,cCat,Region,$A90,Payment_Method,D$88) -> 199 | E90: =COUNTIFS(Year,cYear,Region,cRegion,Sales_Channel,cChannel,Category,cCat,Region,$A90,Payment_Method,E$88) -> 130 | F90: =COUNTIFS(Year,cYear,Region,cRegion,Sales_Channel,cChannel,Category,cCat,Region,$A90,Payment_Method,F$88) -> 114
A91: East | B91: =COUNTIFS(Year,cYear,Region,cRegion,Sales_Channel,cChannel,Category,cCat,Region,$A91,Payment_Method,B$88) -> 380 | C91: =COUNTIFS(Year,cYear,Region,cRegion,Sales_Channel,cChannel,Category,cCat,Region,$A91,Payment_Method,C$88) -> 170 | D91: =COUNTIFS(Year,cYear,Region,cRegion,Sales_Channel,cChannel,Category,cCat,Region,$A91,Payment_Method,D$88) -> 124 | E91: =COUNTIFS(Year,cYear,Region,cRegion,Sales_Channel,cChannel,Category,cCat,Region,$A91,Payment_Method,E$88) -> 78 | F91: =COUNTIFS(Year,cYear,Region,cRegion,Sales_Channel,cChannel,Category,cCat,Region,$A91,Payment_Method,F$88) -> 51
A92: West | B92: =COUNTIFS(Year,cYear,Region,cRegion,Sales_Channel,cChannel,Category,cCat,Region,$A92,Payment_Method,B$88) -> 550 | C92: =COUNTIFS(Year,cYear,Region,cRegion,Sales_Channel,cChannel,Category,cCat,Region,$A92,Payment_Method,C$88) -> 245 | D92: =COUNTIFS(Year,cYear,Region,cRegion,Sales_Channel,cChannel,Category,cCat,Region,$A92,Payment_Method,D$88) -> 174 | E92: =COUNTIFS(Year,cYear,Region,cRegion,Sales_Channel,cChannel,Category,cCat,Region,$A92,Payment_Method,E$88) -> 112 | F92: =COUNTIFS(Year,cYear,Region,cRegion,Sales_Channel,cChannel,Category,cCat,Region,$A92,Payment_Method,F$88) -> 89
A94: Revenue by Category & Month
A95: Category | B95: Jan | C95: Feb | D95: Mar | E95: Apr | F95: May | G95: Jun | H95: Jul | I95: Aug | J95: Sep | K95: Oct | L95: Nov | M95: Dec | N95: Total
A96: Skincare | B96: =SUMIFS(Net_Revenue,Year,cYear,Region,cRegion,Sales_Channel,cChannel,Category,cCat,Category,$A96,Month_No,COLUMN()-COLUMN($B$95)+1) -> 56494.2 | C96: =SUMIFS(Net_Revenue,Year,cYear,Region,cRegion,Sales_Channel,cChannel,Category,cCat,Category,$A96,Month_No,COLUMN()-COLUMN($B$95)+1) -> 44310.05 | D96: =SUMIFS(Net_Revenue,Year,cYear,Region,cRegion,Sales_Channel,cChannel,Category,cCat,Category,$A96,Month_No,COLUMN()-COLUMN($B$95)+1) -> 43426.05 | E96: =SUMIFS(Net_Revenue,Year,cYear,Region,cRegion,Sales_Channel,cChannel,Category,cCat,Category,$A96,Month_No,COLUMN()-COLUMN($B$95)+1) -> 56952.45 | F96: =SUMIFS(Net_Revenue,Year,cYear,Region,cRegion,Sales_Channel,cChannel,Category,cCat,Category,$A96,Month_No,COLUMN()-COLUMN($B$95)+1) -> 40215.3 | G96: =SUMIFS(Net_Revenue,Year,cYear,Region,cRegion,Sales_Channel,cChannel,Category,cCat,Category,$A96,Month_No,COLUMN()-COLUMN($B$95)+1) -> 42008.25 | H96: =SUMIFS(Net_Revenue,Year,cYear,Region,cRegion,Sales_Channel,cChannel,Category,cCat,Category,$A96,Month_No,COLUMN()-COLUMN($B$95)+1) -> 45046.95 | I96: =SUMIFS(Net_Revenue,Year,cYear,Region,cRegion,Sales_Channel,cChannel,Category,cCat,Category,$A96,Month_No,COLUMN()-COLUMN($B$95)+1) -> 47870 | ... M96: =SUMIFS(Net_Revenue,Year,cYear,Region,cRegion,Sales_Channel,cChannel,Category,cCat,Category,$A96,Month_No,COLUMN()-COLUMN($B$95)+1) -> 51003.35 | N96: =SUM(B96:M96) -> 635906.9
A97: Haircare | B97: =SUMIFS(Net_Revenue,Year,cYear,Region,cRegion,Sales_Channel,cChannel,Category,cCat,Category,$A97,Month_No,COLUMN()-COLUMN($B$95)+1) -> 24364.15 | C97: =SUMIFS(Net_Revenue,Year,cYear,Region,cRegion,Sales_Channel,cChannel,Category,cCat,Category,$A97,Month_No,COLUMN()-COLUMN($B$95)+1) -> 27617.2 | D97: =SUMIFS(Net_Revenue,Year,cYear,Region,cRegion,Sales_Channel,cChannel,Category,cCat,Category,$A97,Month_No,COLUMN()-COLUMN($B$95)+1) -> 25422.3 | E97: =SUMIFS(Net_Revenue,Year,cYear,Region,cRegion,Sales_Channel,cChannel,Category,cCat,Category,$A97,Month_No,COLUMN()-COLUMN($B$95)+1) -> 34087.5 | F97: =SUMIFS(Net_Revenue,Year,cYear,Region,cRegion,Sales_Channel,cChannel,Category,cCat,Category,$A97,Month_No,COLUMN()-COLUMN($B$95)+1) -> 27512.8 | G97: =SUMIFS(Net_Revenue,Year,cYear,Region,cRegion,Sales_Channel,cChannel,Category,cCat,Category,$A97,Month_No,COLUMN()-COLUMN($B$95)+1) -> 32450.4 | H97: =SUMIFS(Net_Revenue,Year,cYear,Region,cRegion,Sales_Channel,cChannel,Category,cCat,Category,$A97,Month_No,COLUMN()-COLUMN($B$95)+1) -> 30616.3 | I97: =SUMIFS(Net_Revenue,Year,cYear,Region,cRegion,Sales_Channel,cChannel,Category,cCat,Category,$A97,Month_No,COLUMN()-COLUMN($B$95)+1) -> 38731.9 | ... M97: =SUMIFS(Net_Revenue,Year,cYear,Region,cRegion,Sales_Channel,cChannel,Category,cCat,Category,$A97,Month_No,COLUMN()-COLUMN($B$95)+1) -> 45629.8 | N97: =SUM(B97:M97) -> 418120.7
A98: Apparel | B98: =SUMIFS(Net_Revenue,Year,cYear,Region,cRegion,Sales_Channel,cChannel,Category,cCat,Category,$A98,Month_No,COLUMN()-COLUMN($B$95)+1) -> 136340 | C98: =SUMIFS(Net_Revenue,Year,cYear,Region,cRegion,Sales_Channel,cChannel,Category,cCat,Category,$A98,Month_No,COLUMN()-COLUMN($B$95)+1) -> 86478.95 | D98: =SUMIFS(Net_Revenue,Year,cYear,Region,cRegion,Sales_Channel,cChannel,Category,cCat,Category,$A98,Month_No,COLUMN()-COLUMN($B$95)+1) -> 140923.35 | E98: =SUMIFS(Net_Revenue,Year,cYear,Region,cRegion,Sales_Channel,cChannel,Category,cCat,Category,$A98,Month_No,COLUMN()-COLUMN($B$95)+1) -> 115921.2 | F98: =SUMIFS(Net_Revenue,Year,cYear,Region,cRegion,Sales_Channel,cChannel,Category,cCat,Category,$A98,Month_No,COLUMN()-COLUMN($B$95)+1) -> 98493.35 | G98: =SUMIFS(Net_Revenue,Year,cYear,Region,cRegion,Sales_Channel,cChannel,Category,cCat,Category,$A98,Month_No,COLUMN()-COLUMN($B$95)+1) -> 117220.7 | H98: =SUMIFS(Net_Revenue,Year,cYear,Region,cRegion,Sales_Channel,cChannel,Category,cCat,Category,$A98,Month_No,COLUMN()-COLUMN($B$95)+1) -> 99421.05 | I98: =SUMIFS(Net_Revenue,Year,cYear,Region,cRegion,Sales_Channel,cChannel,Category,cCat,Category,$A98,Month_No,COLUMN()-COLUMN($B$95)+1) -> 82505.7 | ... M98: =SUMIFS(Net_Revenue,Year,cYear,Region,cRegion,Sales_Channel,cChannel,Category,cCat,Category,$A98,Month_No,COLUMN()-COLUMN($B$95)+1) -> 117284.95 | N98: =SUM(B98:M98) -> 1433237.9
A99: Footwear | B99: =SUMIFS(Net_Revenue,Year,cYear,Region,cRegion,Sales_Channel,cChannel,Category,cCat,Category,$A99,Month_No,COLUMN()-COLUMN($B$95)+1) -> 93629.8 | C99: =SUMIFS(Net_Revenue,Year,cYear,Region,cRegion,Sales_Channel,cChannel,Category,cCat,Category,$A99,Month_No,COLUMN()-COLUMN($B$95)+1) -> 52408 | D99: =SUMIFS(Net_Revenue,Year,cYear,Region,cRegion,Sales_Channel,cChannel,Category,cCat,Category,$A99,Month_No,COLUMN()-COLUMN($B$95)+1) -> 68164.9 | E99: =SUMIFS(Net_Revenue,Year,cYear,Region,cRegion,Sales_Channel,cChannel,Category,cCat,Category,$A99,Month_No,COLUMN()-COLUMN($B$95)+1) -> 62253.4 | F99: =SUMIFS(Net_Revenue,Year,cYear,Region,cRegion,Sales_Channel,cChannel,Category,cCat,Category,$A99,Month_No,COLUMN()-COLUMN($B$95)+1) -> 64323.8 | G99: =SUMIFS(Net_Revenue,Year,cYear,Region,cRegion,Sales_Channel,cChannel,Category,cCat,Category,$A99,Month_No,COLUMN()-COLUMN($B$95)+1) -> 73525.15 | H99: =SUMIFS(Net_Revenue,Year,cYear,Region,cRegion,Sales_Channel,cChannel,Category,cCat,Category,$A99,Month_No,COLUMN()-COLUMN($B$95)+1) -> 70950.35 | I99: =SUMIFS(Net_Revenue,Year,cYear,Region,cRegion,Sales_Channel,cChannel,Category,cCat,Category,$A99,Month_No,COLUMN()-COLUMN($B$95)+1) -> 76241 | ... M99: =SUMIFS(Net_Revenue,Year,cYear,Region,cRegion,Sales_Channel,cChannel,Category,cCat,Category,$A99,Month_No,COLUMN()-COLUMN($B$95)+1) -> 91036.95 | N99: =SUM(B99:M99) -> 968884.25
A100: Home & Kitchen | B100: =SUMIFS(Net_Revenue,Year,cYear,Region,cRegion,Sales_Channel,cChannel,Category,cCat,Category,$A100,Month_No,COLUMN()-COLUMN($B$95)+1) -> 57522.55 | C100: =SUMIFS(Net_Revenue,Year,cYear,Region,cRegion,Sales_Channel,cChannel,Category,cCat,Category,$A100,Month_No,COLUMN()-COLUMN($B$95)+1) -> 35114.3 | D100: =SUMIFS(Net_Revenue,Year,cYear,Region,cRegion,Sales_Channel,cChannel,Category,cCat,Category,$A100,Month_No,COLUMN()-COLUMN($B$95)+1) -> 57594.35 | E100: =SUMIFS(Net_Revenue,Year,cYear,Region,cRegion,Sales_Channel,cChannel,Category,cCat,Category,$A100,Month_No,COLUMN()-COLUMN($B$95)+1) -> 61113.65 | F100: =SUMIFS(Net_Revenue,Year,cYear,Region,cRegion,Sales_Channel,cChannel,Category,cCat,Category,$A100,Month_No,COLUMN()-COLUMN($B$95)+1) -> 41554 | G100: =SUMIFS(Net_Revenue,Year,cYear,Region,cRegion,Sales_Channel,cChannel,Category,cCat,Category,$A100,Month_No,COLUMN()-COLUMN($B$95)+1) -> 34798.3 | H100: =SUMIFS(Net_Revenue,Year,cYear,Region,cRegion,Sales_Channel,cChannel,Category,cCat,Category,$A100,Month_No,COLUMN()-COLUMN($B$95)+1) -> 29631.65 | I100: =SUMIFS(Net_Revenue,Year,cYear,Region,cRegion,Sales_Channel,cChannel,Category,cCat,Category,$A100,Month_No,COLUMN()-COLUMN($B$95)+1) -> 36695.1 | ... M100: =SUMIFS(Net_Revenue,Year,cYear,Region,cRegion,Sales_Channel,cChannel,Category,cCat,Category,$A100,Month_No,COLUMN()-COLUMN($B$95)+1) -> 42850.7 | N100: =SUM(B100:M100) -> 603725.2
A101: Electronics | B101: =SUMIFS(Net_Revenue,Year,cYear,Region,cRegion,Sales_Channel,cChannel,Category,cCat,Category,$A101,Month_No,COLUMN()-COLUMN($B$95)+1) -> 41145.15 | C101: =SUMIFS(Net_Revenue,Year,cYear,Region,cRegion,Sales_Channel,cChannel,Category,cCat,Category,$A101,Month_No,COLUMN()-COLUMN($B$95)+1) -> 20743.45 | D101: =SUMIFS(Net_Revenue,Year,cYear,Region,cRegion,Sales_Channel,cChannel,Category,cCat,Category,$A101,Month_No,COLUMN()-COLUMN($B$95)+1) -> 30318.35 | E101: =SUMIFS(Net_Revenue,Year,cYear,Region,cRegion,Sales_Channel,cChannel,Category,cCat,Category,$A101,Month_No,COLUMN()-COLUMN($B$95)+1) -> 26749.7 | F101: =SUMIFS(Net_Revenue,Year,cYear,Region,cRegion,Sales_Channel,cChannel,Category,cCat,Category,$A101,Month_No,COLUMN()-COLUMN($B$95)+1) -> 32747.55 | G101: =SUMIFS(Net_Revenue,Year,cYear,Region,cRegion,Sales_Channel,cChannel,Category,cCat,Category,$A101,Month_No,COLUMN()-COLUMN($B$95)+1) -> 36285.25 | H101: =SUMIFS(Net_Revenue,Year,cYear,Region,cRegion,Sales_Channel,cChannel,Category,cCat,Category,$A101,Month_No,COLUMN()-COLUMN($B$95)+1) -> 39309.75 | I101: =SUMIFS(Net_Revenue,Year,cYear,Region,cRegion,Sales_Channel,cChannel,Category,cCat,Category,$A101,Month_No,COLUMN()-COLUMN($B$95)+1) -> 46878.75 | ... M101: =SUMIFS(Net_Revenue,Year,cYear,Region,cRegion,Sales_Channel,cChannel,Category,cCat,Category,$A101,Month_No,COLUMN()-COLUMN($B$95)+1) -> 28466.5 | N101: =SUM(B101:M101) -> 455520.2
A102: Wellness | B102: =SUMIFS(Net_Revenue,Year,cYear,Region,cRegion,Sales_Channel,cChannel,Category,cCat,Category,$A102,Month_No,COLUMN()-COLUMN($B$95)+1) -> 61986.55 | C102: =SUMIFS(Net_Revenue,Year,cYear,Region,cRegion,Sales_Channel,cChannel,Category,cCat,Category,$A102,Month_No,COLUMN()-COLUMN($B$95)+1) -> 21309.15 | D102: =SUMIFS(Net_Revenue,Year,cYear,Region,cRegion,Sales_Channel,cChannel,Category,cCat,Category,$A102,Month_No,COLUMN()-COLUMN($B$95)+1) -> 48593.4 | E102: =SUMIFS(Net_Revenue,Year,cYear,Region,cRegion,Sales_Channel,cChannel,Category,cCat,Category,$A102,Month_No,COLUMN()-COLUMN($B$95)+1) -> 56784.5 | F102: =SUMIFS(Net_Revenue,Year,cYear,Region,cRegion,Sales_Channel,cChannel,Category,cCat,Category,$A102,Month_No,COLUMN()-COLUMN($B$95)+1) -> 36962.8 | G102: =SUMIFS(Net_Revenue,Year,cYear,Region,cRegion,Sales_Channel,cChannel,Category,cCat,Category,$A102,Month_No,COLUMN()-COLUMN($B$95)+1) -> 55240.2 | H102: =SUMIFS(Net_Revenue,Year,cYear,Region,cRegion,Sales_Channel,cChannel,Category,cCat,Category,$A102,Month_No,COLUMN()-COLUMN($B$95)+1) -> 46515.3 | I102: =SUMIFS(Net_Revenue,Year,cYear,Region,cRegion,Sales_Channel,cChannel,Category,cCat,Category,$A102,Month_No,COLUMN()-COLUMN($B$95)+1) -> 50153.7 | ... M102: =SUMIFS(Net_Revenue,Year,cYear,Region,cRegion,Sales_Channel,cChannel,Category,cCat,Category,$A102,Month_No,COLUMN()-COLUMN($B$95)+1) -> 68061.95 | N102: =SUM(B102:M102) -> 640747.25
A104: Delivery days distribution
A105: Delivery Days | B105: Orders | C105: Avg Rating | D105: Return Rate
A106: 1 day | B106: =COUNTIFS(Year,cYear,Region,cRegion,Sales_Channel,cChannel,Category,cCat,Delivery_Days,VALUE(LEFT($A106,1))) -> 533 | C106: =IFERROR(AVERAGEIFS(Customer_Rating,Year,cYear,Region,cRegion,Sales_Channel,cChannel,Category,cCat,Delivery_Days,VALUE(LEFT($A106,1))),0) -> 4.4005168 | D106: =IFERROR(SUMIFS(Returned,Year,cYear,Region,cRegion,Sales_Channel,cChannel,Category,cCat,Delivery_Days,VALUE(LEFT($A106,1)))/B106,0) -> 0.10318949
A107: 2 days | B107: =COUNTIFS(Year,cYear,Region,cRegion,Sales_Channel,cChannel,Category,cCat,Delivery_Days,VALUE(LEFT($A107,1))) -> 942 | C107: =IFERROR(AVERAGEIFS(Customer_Rating,Year,cYear,Region,cRegion,Sales_Channel,cChannel,Category,cCat,Delivery_Days,VALUE(LEFT($A107,1))),0) -> 4.2204142 | D107: =IFERROR(SUMIFS(Returned,Year,cYear,Region,cRegion,Sales_Channel,cChannel,Category,cCat,Delivery_Days,VALUE(LEFT($A107,1)))/B107,0) -> 0.099787686
A108: 3 days | B108: =COUNTIFS(Year,cYear,Region,cRegion,Sales_Channel,cChannel,Category,cCat,Delivery_Days,VALUE(LEFT($A108,1))) -> 1250 | C108: =IFERROR(AVERAGEIFS(Customer_Rating,Year,cYear,Region,cRegion,Sales_Channel,cChannel,Category,cCat,Delivery_Days,VALUE(LEFT($A108,1))),0) -> 3.9660633 | D108: =IFERROR(SUMIFS(Returned,Year,cYear,Region,cRegion,Sales_Channel,cChannel,Category,cCat,Delivery_Days,VALUE(LEFT($A108,1)))/B108,0) -> 0.0952
A109: 4 days | B109: =COUNTIFS(Year,cYear,Region,cRegion,Sales_Channel,cChannel,Category,cCat,Delivery_Days,VALUE(LEFT($A109,1))) -> 1103 | C109: =IFERROR(AVERAGEIFS(Customer_Rating,Year,cYear,Region,cRegion,Sales_Channel,cChannel,Category,cCat,Delivery_Days,VALUE(LEFT($A109,1))),0) -> 3.7713178 | D109: =IFERROR(SUMIFS(Returned,Year,cYear,Region,cRegion,Sales_Channel,cChannel,Category,cCat,Delivery_Days,VALUE(LEFT($A109,1)))/B109,0) -> 0.097914778
A110: 5 days | B110: =COUNTIFS(Year,cYear,Region,cRegion,Sales_Channel,cChannel,Category,cCat,Delivery_Days,VALUE(LEFT($A110,1))) -> 642 | C110: =IFERROR(AVERAGEIFS(Customer_Rating,Year,cYear,Region,cRegion,Sales_Channel,cChannel,Category,cCat,Delivery_Days,VALUE(LEFT($A110,1))),0) -> 3.5347826 | D110: =IFERROR(SUMIFS(Returned,Year,cYear,Region,cRegion,Sales_Channel,cChannel,Category,cCat,Delivery_Days,VALUE(LEFT($A110,1)))/B110,0) -> 0.12305296
A111: 6 days | B111: =COUNTIFS(Year,cYear,Region,cRegion,Sales_Channel,cChannel,Category,cCat,Delivery_Days,VALUE(LEFT($A111,1))) -> 268 | C111: =IFERROR(AVERAGEIFS(Customer_Rating,Year,cYear,Region,cRegion,Sales_Channel,cChannel,Category,cCat,Delivery_Days,VALUE(LEFT($A111,1))),0) -> 3.4064171 | D111: =IFERROR(SUMIFS(Returned,Year,cYear,Region,cRegion,Sales_Channel,cChannel,Category,cCat,Delivery_Days,VALUE(LEFT($A111,1)))/B111,0) -> 0.1380597
A112: 7 days | B112: =COUNTIFS(Year,cYear,Region,cRegion,Sales_Channel,cChannel,Category,cCat,Delivery_Days,VALUE(LEFT($A112,1))) -> 75 | C112: =IFERROR(AVERAGEIFS(Customer_Rating,Year,cYear,Region,cRegion,Sales_Channel,cChannel,Category,cCat,Delivery_Days,VALUE(LEFT($A112,1))),0) -> 3.1346154 | D112: =IFERROR(SUMIFS(Returned,Year,cYear,Region,cRegion,Sales_Channel,cChannel,Category,cCat,Delivery_Days,VALUE(LEFT($A112,1)))/B112,0) -> 0.12
A113: 8+ days | B113: =COUNTIFS(Year,cYear,Region,cRegion,Sales_Channel,cChannel,Category,cCat,Delivery_Days,">=8") -> 20 | C113: =IFERROR(AVERAGEIFS(Customer_Rating,Year,cYear,Region,cRegion,Sales_Channel,cChannel,Category,cCat,Delivery_Days,">=8"),0) -> 2.7647059 | D113: =IFERROR(SUMIFS(Returned,Year,cYear,Region,cRegion,Sales_Channel,cChannel,Category,cCat,Delivery_Days,">=8")/B113,0) -> 0.1
A115: Delivery Speed | B115: Orders | C115: Avg Rating | D115: Return Rate
A116: Express (≤2d) | B116: =COUNTIFS(Year,cYear,Region,cRegion,Sales_Channel,cChannel,Category,cCat,Delivery_Days,">=1",Delivery_Days,"<=2") -> 1475 | C116: =IFERROR(AVERAGEIFS(Customer_Rating,Year,cYear,Region,cRegion,Sales_Channel,cChannel,Category,cCat,Delivery_Days,">=1",Delivery_Days,"<=2"),0) -> 4.2859831 | D116: =IFERROR(SUMIFS(Returned,Year,cYear,Region,cRegion,Sales_Channel,cChannel,Category,cCat,Delivery_Days,">=1",Delivery_Days,"<=2")/B116,0) -> 0.10101695
A117: Standard (3-4d) | B117: =COUNTIFS(Year,cYear,Region,cRegion,Sales_Channel,cChannel,Category,cCat,Delivery_Days,">=3",Delivery_Days,"<=4") -> 2353 | C117: =IFERROR(AVERAGEIFS(Customer_Rating,Year,cYear,Region,cRegion,Sales_Channel,cChannel,Category,cCat,Delivery_Days,">=3",Delivery_Days,"<=4"),0) -> 3.8751508 | D117: =IFERROR(SUMIFS(Returned,Year,cYear,Region,cRegion,Sales_Channel,cChannel,Category,cCat,Delivery_Days,">=3",Delivery_Days,"<=4")/B117,0) -> 0.096472588
A118: Delayed (5d+) | B118: =COUNTIFS(Year,cYear,Region,cRegion,Sales_Channel,cChannel,Category,cCat,Delivery_Days,">=5") -> 1005 | C118: =IFERROR(AVERAGEIFS(Customer_Rating,Year,cYear,Region,cRegion,Sales_Channel,cChannel,Category,cCat,Delivery_Days,">=5"),0) -> 3.4539106 | D118: =IFERROR(SUMIFS(Returned,Year,cYear,Region,cRegion,Sales_Channel,cChannel,Category,cCat,Delivery_Days,">=5")/B118,0) -> 0.12636816
A120: By State (Year/Channel/Category)
A121: State | B121: Code | C121: Region | D121: Revenue | E121: Profit | F121: Orders | G121: Avg Rating | H121: Return Rate | I121: Avg Delivery Days | J121: Ad Spend | K121: ROAS | L121: Map Value | M121: Revenue (₹ lakh) | N121: Ad Spend (₹ lakh)
A122: Jammu & Kashmir | B122: JK | C122: =INDEX(State!$C$2:$C$24,MATCH($A122,State!$A$2:$A$24,0)) -> North | D122: =SUMIFS(Net_Revenue,Year,cYear,Sales_Channel,cChannel,Category,cCat,State,$A122) -> 78172.75 | E122: =SUMIFS(Profit,Year,cYear,Sales_Channel,cChannel,Category,cCat,State,$A122) -> 29030.75 | F122: =COUNTIFS(Year,cYear,Sales_Channel,cChannel,Category,cCat,State,$A122) -> 64 | G122: =IFERROR(AVERAGEIFS(Customer_Rating,Year,cYear,Sales_Channel,cChannel,Category,cCat,State,$A122),0) -> 3.2272727 | H122: =IFERROR(SUMIFS(Returned,Year,cYear,Sales_Channel,cChannel,Category,cCat,State,$A122)/F122,0) -> 0.15625 | I122: =IFERROR(AVERAGEIFS(Delivery_Days,Year,cYear,Sales_Channel,cChannel,Category,cCat,State,$A122),0) -> 5.84375 | J122: =SUMIFS(Ad_Spend,Ad_Year,cYear,Ad_State,$A122) -> 15070 | K122: =IFERROR(D122/J122,0) -> 5.1873092 | L122: =CHOOSE(MATCH(selMetric,'Dropdown Lists'!$E$2:$E$8,0),D122/100000,E122/100000,F122,G122,H122*100,I122,K122) -> 15.625 | M122: =D122/100000 -> 0.7817275 | N122: =J122/100000 -> 0.1507
A123: Punjab | B123: PB | C123: =INDEX(State!$C$2:$C$24,MATCH($A123,State!$A$2:$A$24,0)) -> North | D123: =SUMIFS(Net_Revenue,Year,cYear,Sales_Channel,cChannel,Category,cCat,State,$A123) -> 138094.9 | E123: =SUMIFS(Profit,Year,cYear,Sales_Channel,cChannel,Category,cCat,State,$A123) -> 59868.9 | F123: =COUNTIFS(Year,cYear,Sales_Channel,cChannel,Category,cCat,State,$A123) -> 132 | G123: =IFERROR(AVERAGEIFS(Customer_Rating,Year,cYear,Sales_Channel,cChannel,Category,cCat,State,$A123),0) -> 3.9555556 | H123: =IFERROR(SUMIFS(Returned,Year,cYear,Sales_Channel,cChannel,Category,cCat,State,$A123)/F123,0) -> 0.11363636 | I123: =IFERROR(AVERAGEIFS(Delivery_Days,Year,cYear,Sales_Channel,cChannel,Category,cCat,State,$A123),0) -> 3.5378788 | J123: =SUMIFS(Ad_Spend,Ad_Year,cYear,Ad_State,$A123) -> 28070 | K123: =IFERROR(D123/J123,0) -> 4.9196616 | L123: =CHOOSE(MATCH(selMetric,'Dropdown Lists'!$E$2:$E$8,0),D123/100000,E123/100000,F123,G123,H123*100,I123,K123) -> 11.363636 | M123: =D123/100000 -> 1.380949 | N123: =J123/100000 -> 0.2807
A124: Himachal Pradesh | B124: HP | C124: =INDEX(State!$C$2:$C$24,MATCH($A124,State!$A$2:$A$24,0)) -> North | D124: =SUMIFS(Net_Revenue,Year,cYear,Sales_Channel,cChannel,Category,cCat,State,$A124) -> 57713.9 | E124: =SUMIFS(Profit,Year,cYear,Sales_Channel,cChannel,Category,cCat,State,$A124) -> 24148.9 | F124: =COUNTIFS(Year,cYear,Sales_Channel,cChannel,Category,cCat,State,$A124) -> 55 | G124: =IFERROR(AVERAGEIFS(Customer_Rating,Year,cYear,Sales_Channel,cChannel,Category,cCat,State,$A124),0) -> 3.6744186 | H124: =IFERROR(SUMIFS(Returned,Year,cYear,Sales_Channel,cChannel,Category,cCat,State,$A124)/F124,0) -> 0.2 | I124: =IFERROR(AVERAGEIFS(Delivery_Days,Year,cYear,Sales_Channel,cChannel,Category,cCat,State,$A124),0) -> 4.6909091 | J124: =SUMIFS(Ad_Spend,Ad_Year,cYear,Ad_State,$A124) -> 11810 | K124: =IFERROR(D124/J124,0) -> 4.8868671 | L124: =CHOOSE(MATCH(selMetric,'Dropdown Lists'!$E$2:$E$8,0),D124/100000,E124/100000,F124,G124,H124*100,I124,K124) -> 20 | M124: =D124/100000 -> 0.577139 | N124: =J124/100000 -> 0.1181
A125: Uttarakhand | B125: UK | C125: =INDEX(State!$C$2:$C$24,MATCH($A125,State!$A$2:$A$24,0)) -> North | D125: =SUMIFS(Net_Revenue,Year,cYear,Sales_Channel,cChannel,Category,cCat,State,$A125) -> 76231.35 | E125: =SUMIFS(Profit,Year,cYear,Sales_Channel,cChannel,Category,cCat,State,$A125) -> 31942.35 | F125: =COUNTIFS(Year,cYear,Sales_Channel,cChannel,Category,cCat,State,$A125) -> 66 | G125: =IFERROR(AVERAGEIFS(Customer_Rating,Year,cYear,Sales_Channel,cChannel,Category,cCat,State,$A125),0) -> 3.6521739 | H125: =IFERROR(SUMIFS(Returned,Year,cYear,Sales_Channel,cChannel,Category,cCat,State,$A125)/F125,0) -> 0.015151515 | I125: =IFERROR(AVERAGEIFS(Delivery_Days,Year,cYear,Sales_Channel,cChannel,Category,cCat,State,$A125),0) -> 4.2424242 | J125: =SUMIFS(Ad_Spend,Ad_Year,cYear,Ad_State,$A125) -> 15300 | K125: =IFERROR(D125/J125,0) -> 4.9824412 | L125: =CHOOSE(MATCH(selMetric,'Dropdown Lists'!$E$2:$E$8,0),D125/100000,E125/100000,F125,G125,H125*100,I125,K125) -> 1.5151515 | M125: =D125/100000 -> 0.7623135 | N125: =J125/100000 -> 0.153
...

Sheet Detail3
A3: Order ID | B3: Order Date | C3: Year | D3: Month | E3: Month No | F3: Customer ID | G3: Customer Type | H3: State | I3: State Code | J3: Region | K3: City | L3: Sales Channel | M3: Product ID | N3: Product Name | O3: Category | P3: Quantity | Q3: Unit Price | R3: Discount % | S3: Gross Sale | T3: Discount Amount | U3: Net Revenue | V3: Unit Cost | W3: COGS | X3: Shipping Cost | Y3: Profit | Z3: Margin % | AA3: Discount | AB3: Delivery Date | AC3: Delivery Days | AD3: Delivery Speed | AE3: Discount_Clean | AF3: Payment Method | AG3: Delivery Date2 | AH3: Customer Rating | AI3: Returned? | AJ3: Returned_Flag
A4: ORD-104774 | B4: 46014 | C4: 2025 | D4: 45992 | E4: 12 | F4: CUST-02742 | G4: Repeat | H4: Karnataka | I4: KA | J4: South | K4: Mysuru | L4: Amazon | M4: P504 | N4: Cotton Bedsheet | O4: Home & Kitchen | P4: 1 | Q4: 1299 | R4: 0.3 | S4: 1299 | T4: 389.7 | U4: 909.3 | V4: 585 | W4: 585 | X4: 60 | Y4: 264.3 | Z4: 0.29066315 | AA4: 0 | AB4: 45485 | AC4: -529 | AD4: Express (≤2d) | AE4: 0 | AF4: UPI | AG4: 46016 | AI4: 0 | AJ4: 0
A5: ORD-104756 | B5: 46010 | C5: 2025 | D5: 45992 | E5: 12 | F5: CUST-00979 | G5: Repeat | H5: Maharashtra | I5: MH | J5: West | K5: Nagpur | L5: Amazon | M5: P503 | N5: Scented Candle Set | O5: Home & Kitchen | P5: 1 | Q5: 699 | R5: 0.2 | S5: 699 | T5: 139.8 | U5: 559.2 | V5: 245 | W5: 245 | X5: 60 | Y5: 254.2 | Z5: 0.45457797 | AA5: 15 | AB5: 45644 | AC5: -366 | AD5: Express (≤2d) | AE5: 0.15 | AF5: COD | AG5: 46012 | AH5: 4 | AI5: 0 | AJ5: 0
A6: ORD-104740 | B6: 46008 | C6: 2025 | D6: 45992 | E6: 12 | F6: CUST-02357 | G6: New | H6: West Bengal | I6: WB | J6: East | K6: Kolkata | L6: Amazon | M6: P503 | N6: Scented Candle Set | O6: Home & Kitchen | P6: 1 | Q6: 699 | R6: 0.15 | S6: 699 | T6: 104.85 | U6: 594.15 | V6: 245 | W6: 245 | X6: 60 | Y6: 289.15 | Z6: 0.48666162 | AA6: 15 | AB6: 45486 | AC6: -522 | AD6: Express (≤2d) | AE6: 0.15 | AF6: UPI | AG6: 46012 | AI6: N | AJ6: 0
A7: ORD-104737 | B7: 46008 | C7: 2025 | D7: 45992 | E7: 12 | F7: CUST-00906 | G7: Repeat | H7: Madhya Pradesh | I7: MP | J7: West | K7: Bhopal | L7: Amazon | M7: P504 | N7: Cotton Bedsheet | O7: Home & Kitchen | P7: 1 | Q7: 1299 | R7: 0.05 | S7: 1299 | T7: 64.95 | U7: 1234.05 | V7: 585 | W7: 585 | X7: 60 | Y7: 589.05 | Z7: 0.47733074 | AA7: 0 | AB7: 45325 | AC7: -683 | AD7: Express (≤2d) | AE7: 0 | AF7: UPI | AG7: 46010 | AH7: 4 | AI7: No | AJ7: 0
A8: ORD-104725 | B8: 46005 | C8: 2025 | D8: 45992 | E8: 12 | F8: CUST-01348 | G8: Repeat | H8: Madhya Pradesh | I8: MP | J8: West | K8: Indore | L8: Amazon | M8: P503 | N8: Scented Candle Set | O8: Home & Kitchen | P8: 1 | Q8: 699 | R8: 0.2 | S8: 699 | T8: 139.8 | U8: 559.2 | V8: 245 | W8: 245 | X8: 60 | Y8: 254.2 | Z8: 0.45457797 | AA8: 0.2 | AB8: 45588 | AC8: -417 | AD8: Express (≤2d) | AE8: 0.2 | AF8: COD | AG8: 46009 | AH8: 3 | AI8: 0 | AJ8: 0
A9: ORD-104709 | B9: 46003 | C9: 2025 | D9: 45992 | E9: 12 | F9: CUST-00968 | G9: Repeat | H9: Maharashtra | I9: MH | J9: West | K9: Pune | L9: Amazon | M9: P503 | N9: Scented Candle Set | O9: Home & Kitchen | P9: 4 | Q9: 699 | R9: 0.25 | S9: 2796 | T9: 699 | U9: 2097 | V9: 245 | W9: 980 | X9: 60 | Y9: 1057 | Z9: 0.50405341 | AA9: 0.2 | AB9: 46011 | AC9: 8 | AD9: Delayed (5d+) | AE9: 0.2 | AF9: Credit Card | AG9: 46005 | AH9: 3 | AJ9: 0
A10: ORD-104670 | B10: 45997 | C10: 2025 | D10: 45992 | E10: 12 | F10: CUST-01867 | G10: New | H10: Maharashtra | I10: MH | J10: West | K10: Mumbai | L10: Amazon | M10: P501 | N10: Copper Water Bottle | O10: Home & Kitchen | P10: 1 | Q10: 899 | R10: 0.3 | S10: 899 | T10: 269.7 | U10: 629.3 | V10: 378 | W10: 378 | X10: 60 | Y10: 191.3 | Z10: 0.30398856 | AA10: 15 | AB10: 45764 | AC10: -233 | AD10: Express (≤2d) | AE10: 0.15 | AF10: Wallet | AG10: 46001 | AJ10: 0
A11: ORD-104656 | B11: 45994 | C11: 2025 | D11: 45992 | E11: 12 | F11: CUST-02634 | G11: New | H11: Tamil Nadu | I11: TN | J11: South | K11: Coimbatore | L11: Amazon | M11: P503 | N11: Scented Candle Set | O11: Home & Kitchen | P11: 2 | Q11: 699 | R11: 0.05 | S11: 1398 | T11: 69.9 | U11: 1328.1 | V11: 245 | W11: 490 | X11: 60 | Y11: 778.1 | Z11: 0.58587456 | AA11: 0.25 | AB11: 45925 | AC11: -69 | AD11: Express (≤2d) | AE11: 0.25 | AF11: UPI | AG11: 45998 | AI11: N | AJ11: 0
A12: ORD-104443 | B12: 45974 | C12: 2025 | D12: 45962 | E12: 11 | F12: CUST-00830 | G12: Repeat | H12: Karnataka | I12: KA | J12: South | K12: Mysuru | L12: Amazon | M12: P502 | N12: Ceramic Dinner Set | O12: Home & Kitchen | P12: 2 | Q12: 2499 | R12: 0.15 | S12: 4998 | T12: 749.7 | U12: 4248.3 | V12: 1250 | W12: 2500 | X12: 60 | Y12: 1688.3 | Z12: 0.39740602 | AA12: 0.4 | AB12: 45788 | AC12: -186 | AD12: Express (≤2d) | AE12: 0.4 | AF12: Wallet | AG12: 45976 | AH12: 3 | AI12: 0 | AJ12: 0
A13: ORD-104358 | B13: 45968 | C13: 2025 | D13: 45962 | E13: 11 | F13: CUST-00995 | G13: Repeat | H13: Jharkhand | I13: JH | J13: East | K13: Ranchi | L13: Amazon | M13: P503 | N13: Scented Candle Set | O13: Home & Kitchen | P13: 2 | Q13: 699 | R13: 0.05 | S13: 1398 | T13: 69.9 | U13: 1328.1 | V13: 245 | W13: 490 | X13: 60 | Y13: 778.1 | Z13: 0.58587456 | AA13: 35 | AB13: 45918 | AC13: -50 | AD13: Express (≤2d) | AE13: 0.35 | AF13: UPI | AG13: 45975 | AI13: N | AJ13: 0
A14: ORD-104351 | B14: 45967 | C14: 2025 | D14: 45962 | E14: 11 | F14: CUST-00934 | G14: Repeat | H14: Tamil Nadu | I14: TN | J14: South | K14: Chennai | L14: Amazon | M14: P503 | N14: Scented Candle Set | O14: Home & Kitchen | P14: 2 | Q14: 699 | R14: 0.1 | S14: 1398 | T14: 139.8 | U14: 1258.2 | V14: 245 | W14: 490 | X14: 60 | Y14: 708.2 | Z14: 0.56286759 | AA14: 0.45 | AB14: 45786 | AC14: -181 | AD14: Express (≤2d) | AE14: 0.45 | AF14: Wallet | AG14: 45971 | AH14: 3 | AJ14: 0
A15: ORD-104342 | B15: 45966 | C15: 2025 | D15: 45962 | E15: 11 | F15: CUST-01703 | G15: New | H15: Tamil Nadu | I15: TN | J15: South | K15: Coimbatore | L15: Amazon | M15: P504 | N15: Cotton Bedsheet | O15: Home & Kitchen | P15: 4 | Q15: 1299 | R15: 0.15 | S15: 5196 | T15: 779.4 | U15: 4416.6 | V15: 585 | W15: 2340 | X15: 60 | Y15: 2016.6 | Z15: 0.45659557 | AA15: 0.15 | AB15: 46010 | AC15: 44 | AD15: Delayed (5d+) | AE15: 0.15 | AF15: Credit Card | AG15: 45970 | AH15: 3 | AI15: N | AJ15: 0
A16: ORD-104328 | B16: 45965 | C16: 2025 | D16: 45962 | E16: 11 | F16: CUST-02187 | G16: Repeat | H16: Punjab | I16: PB | J16: North | K16: Ludhiana | L16: Amazon | M16: P501 | N16: Copper Water Bottle | O16: Home & Kitchen | P16: 1 | Q16: 899 | R16: 0.2 | S16: 899 | T16: 179.8 | U16: 719.2 | V16: 378 | W16: 378 | X16: 60 | Y16: 281.2 | Z16: 0.39098999 | AA16: 0.05 | AB16: 45757 | AC16: -208 | AD16: Express (≤2d) | AE16: 0.05 | AF16: Wallet | AG16: 45968 | AH16: 4 | AI16: No | AJ16: 0
A17: ORD-104311 | B17: 45963 | C17: 2025 | D17: 45962 | E17: 11 | F17: CUST-02821 | G17: New | H17: Rajasthan | I17: RJ | J17: North | K17: Jaipur | L17: Amazon | M17: P503 | N17: Scented Candle Set | O17: Home & Kitchen | P17: 4 | Q17: 699 | R17: 0.2 | S17: 2796 | T17: 559.2 | U17: 2236.8 | V17: 245 | W17: 980 | X17: 60 | Y17: 1196.8 | Z17: 0.53505007 | AA17: 0.35 | AB17: 46020 | AC17: 57 | AD17: Delayed (5d+) | AE17: 0.35 | AF17: UPI | AG17: 45966 | AH17: 4 | AI17: No | AJ17: 0
A18: ORD-104319 | B18: 45963 | C18: 2025 | D18: 45962 | E18: 11 | F18: CUST-01686 | G18: Repeat | H18: Andhra Pradesh | I18: AP | J18: South | K18: Visakhapatnam | L18: Amazon | M18: P501 | N18: Copper Water Bottle | O18: Home & Kitchen | P18: 1 | Q18: 899 | R18: 0.15 | S18: 899 | T18: 134.85 | U18: 764.15 | V18: 378 | W18: 378 | X18: 60 | Y18: 326.15 | Z18: 0.42681411 | AA18: 30 | AB18: 45706 | AC18: -257 | AD18: Express (≤2d) | AE18: 0.3 | AF18: Credit Card | AG18: 45967 | AH18: 5 | AI18: No | AJ18: 0
A19: ORD-104275 | B19: 45959 | C19: 2025 | D19: 45931 | E19: 10 | F19: CUST-01003 | G19: New | H19: Uttar Pradesh | I19: UP | J19: North | K19: Lucknow | L19: Amazon | M19: P504 | N19: Cotton Bedsheet | O19: Home & Kitchen | P19: 1 | Q19: 1299 | R19: 0.2 | S19: 1299 | T19: 259.8 | U19: 1039.2 | V19: 585 | W19: 585 | X19: 60 | Y19: 394.2 | Z19: 0.37933025 | AA19: 0.2 | AB19: 45679 | AC19: -280 | AD19: Express (≤2d) | AE19: 0.2 | AF19: Credit Card | AG19: 45965 | AJ19: 0
A20: ORD-104237 | B20: 45956 | C20: 2025 | D20: 45931 | E20: 10 | F20: CUST-00378 | G20: Repeat | H20: Delhi | I20: DL | J20: North | K20: New Delhi | L20: Amazon | M20: P504 | N20: Cotton Bedsheet | O20: Home & Kitchen | P20: 3 | Q20: 1299 | R20: 0.5 | S20: 3897 | T20: 1948.5 | U20: 1948.5 | V20: 585 | W20: 1755 | X20: 60 | Y20: 133.5 | Z20: 0.068514242 | AA20: 0.1 | AB20: 45980 | AC20: 24 | AD20: Delayed (5d+) | AE20: 0.1 | AF20: COD | AG20: 45958 | AH20: 4 | AI20: No | AJ20: 0
A21: ORD-104239 | B21: 45956 | C21: 2025 | D21: 45931 | E21: 10 | F21: CUST-02234 | G21: Repeat | H21: Telangana | I21: TG | J21: South | K21: Hyderabad | L21: Amazon | M21: P503 | N21: Scented Candle Set | O21: Home & Kitchen | P21: 2 | Q21: 699 | R21: 0.1 | S21: 1398 | T21: 139.8 | U21: 1258.2 | V21: 245 | W21: 490 | X21: 60 | Y21: 708.2 | Z21: 0.56286759 | AA21: 0.35 | AB21: 45941 | AC21: -15 | AD21: Express (≤2d) | AE21: 0.35 | AF21: UPI | AG21: 45959 | AH21: 4 | AI21: No | AJ21: 0
A22: ORD-104194 | B22: 45950 | C22: 2025 | D22: 45931 | E22: 10 | F22: CUST-00324 | G22: Repeat | H22: Maharashtra | I22: MH | J22: West | K22: Mumbai | L22: Amazon | M22: P504 | N22: Cotton Bedsheet | O22: Home & Kitchen | P22: 1 | Q22: 1299 | R22: 0.15 | S22: 1299 | T22: 194.85 | U22: 1104.15 | V22: 585 | W22: 585 | X22: 60 | Y22: 459.15 | Z22: 0.41584024 | AA22: 5 | AB22: 45377 | AC22: -573 | AD22: Express (≤2d) | AE22: 0.05 | AF22: UPI | AG22: 45952 | AH22: 4 | AI22: N | AJ22: 0
A23: ORD-104154 | B23: 45946 | C23: 2025 | D23: 45931 | E23: 10 | F23: CUST-01714 | G23: New | H23: Uttar Pradesh | I23: UP | J23: North | K23: Kanpur | L23: Amazon | M23: P501 | N23: Copper Water Bottle | O23: Home & Kitchen | P23: 2 | Q23: 899 | R23: 0.5 | S23: 1798 | T23: 899 | U23: 899 | V23: 378 | W23: 756 | X23: 60 | Y23: 83 | Z23: 0.092324805 | AA23: 0.3 | AB23: 45943 | AC23: -3 | AD23: Express (≤2d) | AE23: 0.3 | AF23: UPI | AG23: 45950 | AH23: 4 | AI23: No | AJ23: 0
A24: ORD-104157 | B24: 45946 | C24: 2025 | D24: 45931 | E24: 10 | F24: CUST-00576 | G24: Repeat | H24: Gujarat | I24: GJ | J24: West | K24: Surat | L24: Amazon | M24: P501 | N24: Copper Water Bottle | O24: Home & Kitchen | P24: 1 | Q24: 899 | R24: 0.2 | S24: 899 | T24: 179.8 | U24: 719.2 | V24: 378 | W24: 378 | X24: 60 | Y24: 281.2 | Z24: 0.39098999 | AA24: 0.1 | AB24: 45586 | AC24: -360 | AD24: Express (≤2d) | AE24: 0.1 | AF24: COD | AG24: 45952 | AH24: 3 | AI24: N | AJ24: 0
A25: ORD-104146 | B25: 45945 | C25: 2025 | D25: 45931 | E25: 10 | F25: CUST-02091 | G25: Repeat | H25: Uttar Pradesh | I25: UP | J25: North | K25: Lucknow | L25: Amazon | M25: P503 | N25: Scented Candle Set | O25: Home & Kitchen | P25: 4 | Q25: 699 | R25: 0.2 | S25: 2796 | T25: 559.2 | U25: 2236.8 | V25: 245 | W25: 980 | X25: 60 | Y25: 1196.8 | Z25: 0.53505007 | AA25: 0.3 | AB25: 46020 | AC25: 75 | AD25: Delayed (5d+) | AE25: 0.3 | AF25: UPI | AG25: 45949 | AH25: 4 | AI25: No | AJ25: 0
A26: ORD-104123 | B26: 45943 | C26: 2025 | D26: 45931 | E26: 10 | F26: CUST-02615 | G26: Repeat | H26: Rajasthan | I26: RJ | J26: North | K26: Jaipur | L26: Amazon | M26: P504 | N26: Cotton Bedsheet | O26: Home & Kitchen | P26: 1 | Q26: 1299 | R26: 0.2 | S26: 1299 | T26: 259.8 | U26: 1039.2 | V26: 585 | W26: 585 | X26: 60 | Y26: 394.2 | Z26: 0.37933025 | AA26: 0.2 | AB26: 45703 | AC26: -240 | AD26: Express (≤2d) | AE26: 0.2 | AF26: Credit Card | AG26: 45947 | AH26: 5 | AJ26: 0
A27: ORD-104108 | B27: 45942 | C27: 2025 | D27: 45931 | E27: 10 | F27: CUST-00988 | G27: Repeat | H27: Bihar | I27: BR | J27: East | K27: Patna | L27: Amazon | M27: P503 | N27: Scented Candle Set | O27: Home & Kitchen | P27: 2 | Q27: 699 | R27: 0.1 | S27: 1398 | T27: 139.8 | U27: 1258.2 | V27: 245 | W27: 490 | X27: 60 | Y27: 708.2 | Z27: 0.56286759 | AA27: 0.4 | AB27: 45833 | AC27: -109 | AD27: Express (≤2d) | AE27: 0.4 | AF27: Credit Card | AG27: 45945 | AH27: 4 | AI27: 0 | AJ27: 0
A28: ORD-104080 | B28: 45939 | C28: 2025 | D28: 45931 | E28: 10 | F28: CUST-00917 | G28: Repeat | H28: Madhya Pradesh | I28: MP | J28: West | K28: Bhopal | L28: Amazon | M28: P503 | N28: Scented Candle Set | O28: Home & Kitchen | P28: 3 | Q28: 699 | R28: 0.25 | S28: 2097 | T28: 524.25 | U28: 1572.75 | V28: 245 | W28: 735 | X28: 60 | Y28: 777.75 | Z28: 0.49451598 | AA28: 0.35 | AB28: 45974 | AC28: 35 | AD28: Delayed (5d+) | AE28: 0.35 | AF28: UPI | AG28: 45944 | AH28: 4 | AJ28: 0
A29: ORD-104035 | B29: 45935 | C29: 2025 | D29: 45931 | E29: 10 | F29: CUST-01727 | G29: Repeat | H29: Assam | I29: AS | J29: East | K29: Guwahati | L29: Amazon | M29: P503 | N29: Scented Candle Set | O29: Home & Kitchen | P29: 2 | Q29: 699 | R29: 0.1 | S29: 1398 | T29: 139.8 | U29: 1258.2 | V29: 245 | W29: 490 | X29: 60 | Y29: 708.2 | Z29: 0.56286759 | AA29: 0.4 | AB29: 45940 | AC29: 5 | AD29: Delayed (5d+) | AE29: 0.4 | AF29: UPI | AG29: 45940 | AH29: 4 | AI29: N | AJ29: 0
A30: ORD-104008 | B30: 45932 | C30: 2025 | D30: 45931 | E30: 10 | F30: CUST-00279 | G30: Repeat | H30: Maharashtra | I30: MH | J30: West | K30: Pune | L30: Amazon | M30: P503 | N30: Scented Candle Set | O30: Home & Kitchen | P30: 3 | Q30: 699 | R30: 0.45 | S30: 2097 | T30: 943.65 | U30: 1153.35 | V30: 245 | W30: 735 | X30: 60 | Y30: 358.35 | Z30: 0.3107036 | AA30: 0.35 | AB30: 45971 | AC30: 39 | AD30: Delayed (5d+) | AE30: 0.35 | AF30: UPI | AG30: 45934 | AH30: 5 | AI30: 0 | AJ30: 0
A31: ORD-103964 | B31: 45927 | C31: 2025 | D31: 45901 | E31: 9 | F31: CUST-00336 | G31: Repeat | H31: Tamil Nadu | I31: TN | J31: South | K31: Coimbatore | L31: Amazon | M31: P502 | N31: Ceramic Dinner Set | O31: Home & Kitchen | P31: 1 | Q31: 2499 | R31: 0.15 | S31: 2499 | T31: 374.85 | U31: 2124.15 | V31: 1250 | W31: 1250 | X31: 60 | Y31: 814.15 | Z31: 0.38328272 | AA31: 0.3 | AB31: 45775 | AC31: -152 | AD31: Express (≤2d) | AE31: 0.3 | AF31: Wallet | AG31: 45929 | AH31: 5 | AI31: N | AJ31: 0
A32: ORD-103936 | B32: 45923 | C32: 2025 | D32: 45901 | E32: 9 | F32: CUST-00853 | G32: Repeat | H32: Tamil Nadu | I32: TN | J32: South | K32: Coimbatore | L32: Amazon | M32: P503 | N32: Scented Candle Set | O32: Home & Kitchen | P32: 1 | Q32: 699 | R32: 0.25 | S32: 699 | T32: 174.75 | U32: 524.25 | V32: 245 | W32: 245 | X32: 60 | Y32: 219.25 | Z32: 0.4182165 | AA32: 0.2 | AB32: 45558 | AC32: -365 | AD32: Express (≤2d) | AE32: 0.2 | AF32: UPI | AG32: 45924 | AH32: 5 | AJ32: 0
A33: ORD-103923 | B33: 45922 | C33: 2025 | D33: 45901 | E33: 9 | F33: CUST-01161 | G33: Repeat | H33: Delhi | I33: DL | J33: North | K33: New Delhi | L33: Amazon | M33: P504 | N33: Cotton Bedsheet | O33: Home & Kitchen | P33: 1 | Q33: 1299 | R33: 0.05 | S33: 1299 | T33: 64.95 | U33: 1234.05 | V33: 585 | W33: 585 | X33: 60 | Y33: 589.05 | Z33: 0.47733074 | AA33: 0.05 | AB33: 45353 | AC33: -569 | AD33: Express (≤2d) | AE33: 0.05 | AF33: UPI | AG33: 45924 | AH33: 4 | AJ33: 0
A34: ORD-103913 | B34: 45921 | C34: 2025 | D34: 45901 | E34: 9 | F34: CUST-00080 | G34: Repeat | H34: Uttarakhand | I34: UK | J34: North | K34: Dehradun | L34: Amazon | M34: P502 | N34: Ceramic Dinner Set | O34: Home & Kitchen | P34: 1 | Q34: 2499 | R34: 0.1 | S34: 2499 | T34: 249.9 | U34: 2249.1 | V34: 1250 | W34: 1250 | X34: 60 | Y34: 939.1 | Z34: 0.4175448 | AA34: 0.25 | AB34: 45400 | AC34: -521 | AD34: Express (≤2d) | AE34: 0.25 | AF34: UPI | AG34: 45925 | AH34: 4 | AI34: 0 | AJ34: 0
A35: ORD-103910 | B35: 45920 | C35: 2025 | D35: 45901 | E35: 9 | F35: CUST-02120 | G35: Repeat | H35: Maharashtra | I35: MH | J35: West | K35: Mumbai | L35: Amazon | M35: P503 | N35: Scented Candle Set | O35: Home & Kitchen | P35: 4 | Q35: 699 | R35: 0 | S35: 2796 | T35: 0 | U35: 2796 | V35: 245 | W35: 980 | X35: 60 | Y35: 1756 | Z35: 0.62804006 | AA35: 0.2 | AB35: 46019 | AC35: 99 | AD35: Delayed (5d+) | AE35: 0.2 | AF35: UPI | AG35: 45923 | AH35: 4 | AJ35: 0
A36: ORD-103856 | B36: 45914 | C36: 2025 | D36: 45901 | E36: 9 | F36: CUST-02247 | G36: Repeat | H36: Telangana | I36: TG | J36: South | K36: Hyderabad | L36: Amazon | M36: P503 | N36: Scented Candle Set | O36: Home & Kitchen | P36: 1 | Q36: 699 | R36: 0.1 | S36: 699 | T36: 69.9 | U36: 629.1 | V36: 245 | W36: 245 | X36: 60 | Y36: 324.1 | Z36: 0.51518042 | AA36: 20 | AB36: 45352 | AC36: -562 | AD36: Express (≤2d) | AE36: 0.2 | AF36: UPI | AG36: 45916 | AH36: 4 | AJ36: 0
A37: ORD-103840 | B37: 45912 | C37: 2025 | D37: 45901 | E37: 9 | F37: CUST-02814 | G37: New | H37: Madhya Pradesh | I37: MP | J37: West | K37: Indore | L37: Amazon | M37: P504 | N37: Cotton Bedsheet | O37: Home & Kitchen | P37: 1 | Q37: 1299 | R37: 0.2 | S37: 1299 | T37: 259.8 | U37: 1039.2 | V37: 585 | W37: 585 | X37: 60 | Y37: 394.2 | Z37: 0.37933025 | AA37: 0 | AB37: 45316 | AC37: -596 | AD37: Express (≤2d) | AE37: 0 | AF37: UPI | AG37: 45914 | AH37: 4 | AI37: No | AJ37: 0
A38: ORD-103822 | B38: 45909 | C38: 2025 | D38: 45901 | E38: 9 | F38: CUST-00260 | G38: Repeat | H38: Delhi | I38: DL | J38: North | K38: New Delhi | L38: Amazon | M38: P503 | N38: Scented Candle Set | O38: Home & Kitchen | P38: 1 | Q38: 699 | R38: 0.05 | S38: 699 | T38: 34.95 | U38: 664.05 | V38: 245 | W38: 245 | X38: 60 | Y38: 359.05 | Z38: 0.54069724 | AA38: 15 | AB38: 45702 | AC38: -207 | AD38: Express (≤2d) | AE38: 0.15 | AF38: Credit Card | AG38: 45911 | AH38: 5 | AI38: No | AJ38: 0
A39: ORD-103815 | B39: 45908 | C39: 2025 | D39: 45901 | E39: 9 | F39: CUST-01937 | G39: New | H39: Haryana | I39: HR | J39: North | K39: Gurugram | L39: Amazon | M39: P501 | N39: Copper Water Bottle | O39: Home & Kitchen | P39: 3 | Q39: 899 | R39: 0.4 | S39: 2697 | T39: 1078.8 | U39: 1618.2 | V39: 378 | W39: 1134 | X39: 60 | Y39: 424.2 | Z39: 0.26214312 | AA39: 0 | AB39: 45993 | AC39: 85 | AD39: Delayed (5d+) | AE39: 0 | AF39: Debit Card | AG39: 45910 | AI39: 0 | AJ39: 0
A40: ORD-103779 | B40: 45901 | C40: 2025 | D40: 45901 | E40: 9 | F40: CUST-00336 | G40: Repeat | H40: Tamil Nadu | I40: TN | J40: South | K40: Chennai | L40: Amazon | M40: P504 | N40: Cotton Bedsheet | O40: Home & Kitchen | P40: 2 | Q40: 1299 | R40: 0.15 | S40: 2598 | T40: 389.7 | U40: 2208.3 | V40: 585 | W40: 1170 | X40: 60 | Y40: 978.3 | Z40: 0.44301046 | AA40: 0 | AB40: 45901 | AC40: 0 | AD40: Express (≤2d) | AE40: 0 | AF40: UPI | AG40: 45902 | AH40: 5 | AJ40: 0
A41: ORD-100036 | B41: 45297 | C41: 2024 | D41: 45292 | E41: 1 | F41: CUST-00456 | G41: New | H41: Maharashtra | I41: MH | J41: West | K41: Pune | L41: Amazon | M41: P503 | N41: Scented Candle Set | O41: Home & Kitchen | P41: 2 | Q41: 699 | R41: 0.35 | S41: 1398 | T41: 489.3 | U41: 908.7 | V41: 245 | W41: 490 | X41: 60 | Y41: 358.7 | Z41: 0.39473974 | AA41: 0.2 | AB41: 45816 | AC41: 519 | AD41: Delayed (5d+) | AE41: 0.2 | AF41: Credit Card | AG41: 45299 | AI41: No | AJ41: 0
A42: ORD-103772 | B42: 45901 | C42: 2025 | D42: 45901 | E42: 9 | F42: CUST-00011 | G42: Repeat | H42: Delhi | I42: DL | J42: North | K42: New Delhi | L42: Amazon | M42: P503 | N42: Scented Candle Set | O42: Home & Kitchen | P42: 1 | Q42: 699 | R42: 0.2 | S42: 699 | T42: 139.8 | U42: 559.2 | V42: 245 | W42: 245 | X42: 60 | Y42: 254.2 | Z42: 0.45457797 | AA42: 0.3 | AB42: 45717 | AC42: -184 | AD42: Express (≤2d) | AE42: 0.3 | AF42: Debit Card | AG42: 45902 | AH42: 5 | AJ42: 0
A43: ORD-103731 | B43: 45894 | C43: 2025 | D43: 45870 | E43: 8 | F43: CUST-02174 | G43: New | H43: Tamil Nadu | I43: TN | J43: South | K43: Coimbatore | L43: Amazon | M43: P503 | N43: Scented Candle Set | O43: Home & Kitchen | P43: 1 | Q43: 699 | R43: 0.15 | S43: 699 | T43: 104.85 | U43: 594.15 | V43: 245 | W43: 245 | X43: 60 | Y43: 289.15 | Z43: 0.48666162 | AA43: 0.15 | AB43: 45758 | AC43: -136 | AD43: Express (≤2d) | AE43: 0.15 | AF43: Wallet | AG43: 45898 | AH43: 4 | AI43: 0 | AJ43: 0
A44: ORD-103698 | B44: 45890 | C44: 2025 | D44: 45870 | E44: 8 | F44: CUST-00568 | G44: New | H44: West Bengal | I44: WB | J44: East | K44: Kolkata | L44: Amazon | M44: P503 | N44: Scented Candle Set | O44: Home & Kitchen | P44: 1 | Q44: 699 | R44: 0.1 | S44: 699 | T44: 69.9 | U44: 629.1 | V44: 245 | W44: 245 | X44: 60 | Y44: 324.1 | Z44: 0.51518042 | AA44: 20 | AB44: 45644 | AC44: -246 | AD44: Express (≤2d) | AE44: 0.2 | AF44: COD | AG44: 45893 | AH44: 4 | AI44: No | AJ44: 0
A45: ORD-103681 | B45: 45888 | C45: 2025 | D45: 45870 | E45: 8 | F45: CUST-02940 | G45: New | H45: Odisha | I45: OD | J45: East | K45: Bhubaneswar | L45: Amazon | M45: P501 | N45: Copper Water Bottle | O45: Home & Kitchen | P45: 1 | Q45: 899 | R45: 0.1 | S45: 899 | T45: 89.9 | U45: 809.1 | V45: 378 | W45: 378 | X45: 60 | Y45: 371.1 | Z45: 0.45865777 | AA45: 0.15 | AB45: 45603 | AC45: -285 | AD45: Express (≤2d) | AE45: 0.15 | AF45: COD | AG45: 45892 | AI45: N | AJ45: 0
A46: ORD-103674 | B46: 45887 | C46: 2025 | D46: 45870 | E46: 8 | F46: CUST-00823 | G46: Repeat | H46: West Bengal | I46: WB | J46: East | K46: Kolkata | L46: Amazon | M46: P503 | N46: Scented Candle Set | O46: Home & Kitchen | P46: 1 | Q46: 699 | R46: 0.1 | S46: 699 | T46: 69.9 | U46: 629.1 | V46: 245 | W46: 245 | X46: 60 | Y46: 324.1 | Z46: 0.51518042 | AA46: 0.2 | AB46: 45315 | AC46: -572 | AD46: Express (≤2d) | AE46: 0.2 | AF46: UPI | AG46: 45891 | AH46: 4 | AI46: No | AJ46: 0
A47: ORD-103640 | B47: 45882 | C47: 2025 | D47: 45870 | E47: 8 | F47: CUST-03138 | G47: Repeat | H47: Delhi | I47: DL | J47: North | K47: New Delhi | L47: Amazon | M47: P504 | N47: Cotton Bedsheet | O47: Home & Kitchen | P47: 1 | Q47: 1299 | R47: 0.15 | S47: 1299 | T47: 194.85 | U47: 1104.15 | V47: 585 | W47: 585 | X47: 60 | Y47: 459.15 | Z47: 0.41584024 | AA47: 0 | AB47: 45678 | AC47: -204 | AD47: Express (≤2d) | AE47: 0 | AF47: Credit Card | AG47: 45884 | AI47: 0 | AJ47: 0
A48: ORD-103644 | B48: 45882 | C48: 2025 | D48: 45870 | E48: 8 | F48: CUST-00774 | G48: Repeat | H48: West Bengal | I48: WB | J48: East | K48: Kolkata | L48: Amazon | M48: P501 | N48: Copper Water Bottle | O48: Home & Kitchen | P48: 1 | Q48: 899 | R48: 0.25 | S48: 899 | T48: 224.75 | U48: 674.25 | V48: 378 | W48: 378 | X48: 60 | Y48: 236.25 | Z48: 0.35038932 | AA48: 5 | AB48: 45643 | AC48: -239 | AD48: Express (≤2d) | AE48: 0.05 | AF48: COD | AG48: 45886 | AH48: 4 | AJ48: 0
A49: ORD-103583 | B49: 45876 | C49: 2025 | D49: 45870 | E49: 8 | F49: CUST-00879 | G49: Repeat | H49: Bihar | I49: BR | J49: East | K49: Patna | L49: Amazon | M49: P501 | N49: Copper Water Bottle | O49: Home & Kitchen | P49: 1 | Q49: 899 | R49: 0.45 | S49: 899 | T49: 404.55 | U49: 494.45 | V49: 378 | W49: 378 | X49: 60 | Y49: 56.45 | Z49: 0.11416726 | AA49: 15 | AB49: 45659 | AC49: -217 | AD49: Express (≤2d) | AE49: 0.15 | AF49: Credit Card | AG49: 45880 | AH49: 4 | AJ49: 0
A50: ORD-103569 | B50: 45874 | C50: 2025 | D50: 45870 | E50: 8 | F50: CUST-00844 | G50: Repeat | H50: Punjab | I50: PB | J50: North | K50: Ludhiana | L50: Amazon | M50: P504 | N50: Cotton Bedsheet | O50: Home & Kitchen | P50: 2 | Q50: 1299 | R50: 0 | S50: 2598 | T50: 0 | U50: 2598 | V50: 585 | W50: 1170 | X50: 60 | Y50: 1368 | Z50: 0.52655889 | AA50: 0 | AB50: 45859 | AC50: -15 | AD50: Express (≤2d) | AE50: 0 | AF50: COD | AG50: 45877 | AJ50: 0
A51: ORD-103509 | B51: 45866 | C51: 2025 | D51: 45839 | E51: 7 | F51: CUST-01312 | G51: New | H51: Maharashtra | I51: MH | J51: West | K51: Nagpur | L51: Amazon | M51: P501 | N51: Copper Water Bottle | O51: Home & Kitchen | P51: 1 | Q51: 899 | R51: 0.1 | S51: 899 | T51: 89.9 | U51: 809.1 | V51: 378 | W51: 378 | X51: 60 | Y51: 371.1 | Z51: 0.45865777 | AA51: 0.15 | AB51: 45658 | AC51: -208 | AD51: Express (≤2d) | AE51: 0.15 | AF51: Credit Card | AG51: 45869 | AH51: 4 | AI51: No | AJ51: 0
A52: ORD-103511 | B52: 45866 | C52: 2025 | D52: 45839 | E52: 7 | F52: CUST-00385 | G52: Repeat | H52: Odisha | I52: OD | J52: East | K52: Bhubaneswar | L52: Amazon | M52: P503 | N52: Scented Candle Set | O52: Home & Kitchen | P52: 1 | Q52: 699 | R52: 0.4 | S52: 699 | T52: 279.6 | U52: 419.4 | V52: 245 | W52: 245 | X52: 60 | Y52: 114.4 | Z52: 0.27277062 | AA52: 0.2 | AB52: 45607 | AC52: -259 | AD52: Express (≤2d) | AE52: 0.2 | AF52: COD | AG52: 45872 | AI52: 0 | AJ52: 0
A53: ORD-103483 | B53: 45861 | C53: 2025 | D53: 45839 | E53: 7 | F53: CUST-01691 | G53: New | H53: Madhya Pradesh | I53: MP | J53: West | K53: Indore | L53: Amazon | M53: P501 | N53: Copper Water Bottle | O53: Home & Kitchen | P53: 1 | Q53: 899 | R53: 0.3 | S53: 899 | T53: 269.7 | U53: 629.3 | V53: 378 | W53: 378 | X53: 60 | Y53: 191.3 | Z53: 0.30398856 | AA53: 5 | AB53: 45605 | AC53: -256 | AD53: Express (≤2d) | AE53: 0.05 | AF53: COD | AG53: 45864 | AI53: No | AJ53: 0
A54: ORD-103450 | B54: 45856 | C54: 2025 | D54: 45839 | E54: 7 | F54: CUST-01277 | G54: Repeat | H54: West Bengal | I54: WB | J54: East | K54: Kolkata | L54: Amazon | M54: P503 | N54: Scented Candle Set | O54: Home & Kitchen | P54: 1 | Q54: 699 | R54: 0.45 | S54: 699 | T54: 314.55 | U54: 384.45 | V54: 245 | W54: 245 | X54: 60 | Y54: 79.45 | Z54: 0.20665886 | AA54: 25 | AB54: 45606 | AC54: -250 | AD54: Express (≤2d) | AE54: 0.25 | AF54: COD | AG54: 45860 | AI54: No | AJ54: 0
A55: ORD-103442 | B55: 45855 | C55: 2025 | D55: 45839 | E55: 7 | F55: CUST-01051 | G55: Repeat | H55: Delhi | I55: DL | J55: North | K55: New Delhi | L55: Amazon | M55: P503 | N55: Scented Candle Set | O55: Home & Kitchen | P55: 1 | Q55: 699 | R55: 0.15 | S55: 699 | T55: 104.85 | U55: 594.15 | V55: 245 | W55: 245 | X55: 60 | Y55: 289.15 | Z55: 0.48666162 | AA55: 0.2 | AB55: 45705 | AC55: -150 | AD55: Express (≤2d) | AE55: 0.2 | AF55: Credit Card | AG55: 45856 | AH55: 5 | AJ55: 0
A56: ORD-103435 | B56: 45854 | C56: 2025 | D56: 45839 | E56: 7 | F56: CUST-02115 | G56: New | H56: Uttarakhand | I56: UK | J56: North | K56: Dehradun | L56: Amazon | M56: P504 | N56: Cotton Bedsheet | O56: Home & Kitchen | P56: 2 | Q56: 1299 | R56: 0.3 | S56: 2598 | T56: 779.4 | U56: 1818.6 | V56: 585 | W56: 1170 | X56: 60 | Y56: 588.6 | Z56: 0.32365556 | AA56: 0 | AB56: 45859 | AC56: 5 | AD56: Delayed (5d+) | AE56: 0 | AF56: COD | AG56: 45856 | AJ56: 0
A57: ORD-103394 | B57: 45845 | C57: 2025 | D57: 45839 | E57: 7 | F57: CUST-02696 | G57: New | H57: Karnataka | I57: KA | J57: South | K57: Mysuru | L57: Amazon | M57: P503 | N57: Scented Candle Set | O57: Home & Kitchen | P57: 2 | Q57: 699 | R57: 0.15 | S57: 1398 | T57: 209.7 | U57: 1188.3 | V57: 245 | W57: 490 | X57: 60 | Y57: 638.3 | Z57: 0.53715392 | AA57: 0.2 | AB57: 45806 | AC57: -39 | AD57: Express (≤2d) | AE57: 0.2 | AF57: Debit Card | AG57: 45847 | AH57: 5 | AI57: N | AJ57: 0
A58: ORD-103392 | B58: 45845 | C58: 2025 | D58: 45839 | E58: 7 | F58: CUST-01009 | G58: Repeat | H58: Delhi | I58: DL | J58: North | K58: New Delhi | L58: Amazon | M58: P501 | N58: Copper Water Bottle | O58: Home & Kitchen | P58: 1 | Q58: 899 | R58: 0.25 | S58: 899 | T58: 224.75 | U58: 674.25 | V58: 378 | W58: 378 | X58: 120 | Y58: 176.25 | Z58: 0.26140156 | AA58: 0.1 | AB58: 45575 | AC58: -270 | AD58: Express (≤2d) | AE58: 0.1 | AF58: COD | AG58: 45847 | AH58: 5 | AI58: Y | AJ58: 1
A59: ORD-103380 | B59: 45844 | C59: 2025 | D59: 45839 | E59: 7 | F59: CUST-01150 | G59: Repeat | H59: Uttarakhand | I59: UK | J59: North | K59: Dehradun | L59: Amazon | M59: P501 | N59: Copper Water Bottle | O59: Home & Kitchen | P59: 1 | Q59: 899 | R59: 0.1 | S59: 899 | T59: 89.9 | U59: 809.1 | V59: 378 | W59: 378 | X59: 60 | Y59: 371.1 | Z59: 0.45865777 | AA59: 0 | AB59: 45717 | AC59: -127 | AD59: Express (≤2d) | AE59: 0 | AF59: Debit Card | AG59: 45851 | AH59: 3 | AJ59: 0
A60: ORD-103308 | B60: 45834 | C60: 2025 | D60: 45809 | E60: 6 | F60: CUST-00174 | G60: Repeat | H60: Punjab | I60: PB | J60: North | K60: Amritsar | L60: Amazon | M60: P503 | N60: Scented Candle Set | O60: Home & Kitchen | P60: 1 | Q60: 699 | R60: 0.15 | S60: 699 | T60: 104.85 | U60: 594.15 | V60: 245 | W60: 245 | X60: 60 | Y60: 289.15 | Z60: 0.48666162 | AA60: 0.2 | AB60: 45481 | AC60: -353 | AD60: Express (≤2d) | AE60: 0.2 | AF60: UPI | AG60: 45840 | AJ60: 0
A61: ORD-103287 | B61: 45830 | C61: 2025 | D61: 45809 | E61: 6 | F61: CUST-00591 | G61: New | H61: Tamil Nadu | I61: TN | J61: South | K61: Coimbatore | L61: Amazon | M61: P504 | N61: Cotton Bedsheet | O61: Home & Kitchen | P61: 1 | Q61: 1299 | R61: 0.15 | S61: 1299 | T61: 194.85 | U61: 1104.15 | V61: 585 | W61: 585 | X61: 60 | Y61: 459.15 | Z61: 0.41584024 | AA61: 0 | AB61: 45378 | AC61: -452 | AD61: Express (≤2d) | AE61: 0 | AF61: UPI | AG61: 45833 | AH61: 4 | AI61: N | AJ61: 0
A62: ORD-103271 | B62: 45827 | C62: 2025 | D62: 45809 | E62: 6 | F62: CUST-00506 | G62: Repeat | H62: Tamil Nadu | I62: TN | J62: South | K62: Coimbatore | L62: Amazon | M62: P503 | N62: Scented Candle Set | O62: Home & Kitchen | P62: 1 | Q62: 699 | R62: 0 | S62: 699 | T62: 0 | U62: 699 | V62: 245 | W62: 245 | X62: 60 | Y62: 394 | Z62: 0.56366237 | AA62: 0.2 | AB62: 45479 | AC62: -348 | AD62: Express (≤2d) | AE62: 0.2 | AF62: UPI | AG62: 45830 | AI62: No | AJ62: 0
A63: ORD-103251 | B63: 45825 | C63: 2025 | D63: 45809 | E63: 6 | F63: CUST-03173 | G63: New | H63: Gujarat | I63: GJ | J63: West | K63: Ahmedabad | L63: Amazon | M63: P503 | N63: Scented Candle Set | O63: Home & Kitchen | P63: 1 | Q63: 699 | R63: 0.05 | S63: 699 | T63: 34.95 | U63: 664.05 | V63: 245 | W63: 245 | X63: 60 | Y63: 359.05 | Z63: 0.54069724 | AA63: 0.2 | AB63: 45716 | AC63: -109 | AD63: Express (≤2d) | AE63: 0.2 | AF63: Debit Card | AG63: 45827 | AH63: 5 | AI63: N | AJ63: 0
A64: ORD-103243 | B64: 45824 | C64: 2025 | D64: 45809 | E64: 6 | F64: CUST-00823 | G64: Repeat | H64: Himachal Pradesh | I64: HP | J64: North | K64: Shimla | L64: Amazon | M64: P504 | N64: Cotton Bedsheet | O64: Home & Kitchen | P64: 1 | Q64: 1299 | R64: 0.05 | S64: 1299 | T64: 64.95 | U64: 1234.05 | V64: 585 | W64: 585 | X64: 120 | Y64: 529.05 | Z64: 0.42871034 | AA64: 0 | AB64: 45642 | AC64: -182 | AD64: Express (≤2d) | AE64: 0 | AF64: COD | AG64: 45830 | AH64: 4 | AI64: TRUE | AJ64: 1
A65: ORD-103196 | B65: 45817 | C65: 2025 | D65: 45809 | E65: 6 | F65: CUST-00746 | G65: Repeat | H65: Rajasthan | I65: RJ | J65: North | K65: Udaipur | L65: Amazon | M65: P503 | N65: Scented Candle Set | O65: Home & Kitchen | P65: 4 | Q65: 699 | R65: 0.35 | S65: 2796 | T65: 978.6 | U65: 1817.4 | V65: 245 | W65: 980 | X65: 60 | Y65: 777.4 | Z65: 0.42775393 | AA65: 0.3 | AB65: 46003 | AC65: 186 | AD65: Delayed (5d+) | AE65: 0.3 | AF65: COD | AG65: 45823 | AH65: 4 | AJ65: 0
A66: ORD-103138 | B66: 45809 | C66: 2025 | D66: 45809 | E66: 6 | F66: CUST-00443 | G66: Repeat | H66: Delhi | I66: DL | J66: North | K66: New Delhi | L66: Amazon | M66: P504 | N66: Cotton Bedsheet | O66: Home & Kitchen | P66: 2 | Q66: 1299 | R66: 0.3 | S66: 2598 | T66: 779.4 | U66: 1818.6 | V66: 585 | W66: 1170 | X66: 60 | Y66: 588.6 | Z66: 0.32365556 | AA66: 0.1 | AB66: 45900 | AC66: 91 | AD66: Delayed (5d+) | AE66: 0.1 | AF66: UPI | AG66: 45810 | AH66: 5 | AI66: No | AJ66: 0
A67: ORD-103110 | B67: 45802 | C67: 2025 | D67: 45778 | E67: 5 | F67: CUST-01440 | G67: Repeat | H67: Odisha | I67: OD | J67: East | K67: Bhubaneswar | L67: Amazon | M67: P501 | N67: Copper Water Bottle | O67: Home & Kitchen | P67: 1 | Q67: 899 | R67: 0 | S67: 899 | T67: 0 | U67: 899 | V67: 378 | W67: 378 | X67: 60 | Y67: 461 | Z67: 0.51279199 | AA67: 5 | AB67: 45374 | AC67: -428 | AD67: Express (≤2d) | AE67: 0.05 | AF67: UPI | AG67: 45805 | AH67: 4 | AI67: N | AJ67: 0
A68: ORD-103057 | B68: 45793 | C68: 2025 | D68: 45778 | E68: 5 | F68: CUST-01614 | G68: Repeat | H68: Jammu & Kashmir | I68: JK | J68: North | K68: Srinagar | L68: Amazon | M68: P502 | N68: Ceramic Dinner Set | O68: Home & Kitchen | P68: 1 | Q68: 2499 | R68: 0.1 | S68: 2499 | T68: 249.9 | U68: 2249.1 | V68: 1250 | W68: 1250 | X68: 60 | Y68: 939.1 | Z68: 0.4175448 | AA68: 0.3 | AB68: 45562 | AC68: -231 | AD68: Express (≤2d) | AE68: 0.3 | AF68: UPI | AG68: 45799 | AH68: 2 | AI68: 0 | AJ68: 0
A69: ORD-103049 | B69: 45791 | C69: 2025 | D69: 45778 | E69: 5 | F69: CUST-00745 | G69: Repeat | H69: Delhi | I69: DL | J69: North | K69: New Delhi | L69: Amazon | M69: P504 | N69: Cotton Bedsheet | O69: Home & Kitchen | P69: 2 | Q69: 1299 | R69: 0.15 | S69: 2598 | T69: 389.7 | U69: 2208.3 | V69: 585 | W69: 1170 | X69: 60 | Y69: 978.3 | Z69: 0.44301046 | AA69: 0.05 | AB69: 45867 | AC69: 76 | AD69: Delayed (5d+) | AE69: 0.05 | AF69: COD | AG69: 45793 | AH69: 4 | AI69: No | AJ69: 0
A70: ORD-103036 | B70: 45788 | C70: 2025 | D70: 45778 | E70: 5 | F70: CUST-00117 | G70: Repeat | H70: Rajasthan | I70: RJ | J70: North | K70: Jaipur | L70: Amazon | M70: P502 | N70: Ceramic Dinner Set | O70: Home & Kitchen | P70: 2 | Q70: 2499 | R70: 0 | S70: 4998 | T70: 0 | U70: 4998 | V70: 1250 | W70: 2500 | X70: 60 | Y70: 2438 | Z70: 0.48779512 | AA70: 0.3 | AB70: 45888 | AC70: 100 | AD70: Delayed (5d+) | AE70: 0.3 | AF70: UPI | AG70: 45792 | AH70: 3 | AI70: No | AJ70: 0
A71: ORD-100072 | B71: 45302 | C71: 2024 | D71: 45292 | E71: 1 | F71: CUST-00378 | G71: New | H71: Karnataka | I71: KA | J71: South | K71: Mysuru | L71: Amazon | M71: P503 | N71: Scented Candle Set | O71: Home & Kitchen | P71: 1 | Q71: 699 | R71: 0 | S71: 699 | T71: 0 | U71: 699 | V71: 245 | W71: 245 | X71: 120 | Y71: 334 | Z71: 0.47782546 | AA71: 0.25 | AB71: 45636 | AC71: 334 | AD71: Delayed (5d+) | AE71: 0.25 | AF71: COD | AG71: 45305 | AH71: 4 | AI71: Yes | AJ71: 1
A72: ORD-103029 | B72: 45787 | C72: 2025 | D72: 45778 | E72: 5 | F72: CUST-00762 | G72: Repeat | H72: Delhi | I72: DL | J72: North | K72: New Delhi | L72: Amazon | M72: P501 | N72: Copper Water Bottle | O72: Home & Kitchen | P72: 2 | Q72: 899 | R72: 0.35 | S72: 1798 | T72: 629.3 | U72: 1168.7 | V72: 378 | W72: 756 | X72: 60 | Y72: 352.7 | Z72: 0.30178831 | AA72: 0.05 | AB72: 45938 | AC72: 151 | AD72: Delayed (5d+) | AE72: 0.05 | AF72: UPI | AG72: 45788 | AH72: 4 | AJ72: 0
A73: ORD-103021 | B73: 45785 | C73: 2025 | D73: 45778 | E73: 5 | F73: CUST-01832 | G73: Repeat | H73: Andhra Pradesh | I73: AP | J73: South | K73: Vijayawada | L73: Amazon | M73: P503 | N73: Scented Candle Set | O73: Home & Kitchen | P73: 4 | Q73: 699 | R73: 0.3 | S73: 2796 | T73: 838.8 | U73: 1957.2 | V73: 245 | W73: 980 | X73: 60 | Y73: 917.2 | Z73: 0.46862865 | AA73: 0.3 | AB73: 46016 | AC73: 231 | AD73: Delayed (5d+) | AE73: 0.3 | AF73: UPI | AG73: 45788 | AH73: 4 | AJ73: 0
A74: ORD-103011 | B74: 45784 | C74: 2025 | D74: 45778 | E74: 5 | F74: CUST-00321 | G74: Repeat | H74: Jharkhand | I74: JH | J74: East | K74: Ranchi | L74: Amazon | M74: P504 | N74: Cotton Bedsheet | O74: Home & Kitchen | P74: 1 | Q74: 1299 | R74: 0.6 | S74: 1299 | T74: 779.4 | U74: 519.6 | V74: 585 | W74: 585 | X74: 60 | Y74: -125.4 | Z74: -0.24133949 | AA74: 5 | AB74: 45603 | AC74: -181 | AD74: Express (≤2d) | AE74: 0.05 | AF74: COD | AG74: 45789 | AJ74: 0
A75: ORD-103003 | B75: 45783 | C75: 2025 | D75: 45778 | E75: 5 | F75: CUST-00807 | G75: New | H75: Delhi | I75: DL | J75: North | K75: New Delhi | L75: Amazon | M75: P503 | N75: Scented Candle Set | O75: Home & Kitchen | P75: 2 | Q75: 699 | R75: 0.05 | S75: 1398 | T75: 69.9 | U75: 1328.1 | V75: 245 | W75: 490 | X75: 60 | Y75: 778.1 | Z75: 0.58587456 | AA75: 30 | AB75: 45827 | AC75: 44 | AD75: Delayed (5d+) | AE75: 0.3 | AF75: Credit Card | AG75: 45785 | AH75: 5 | AJ75: 0
A76: ORD-102934 | B76: 45773 | C76: 2025 | D76: 45748 | E76: 4 | F76: CUST-00868 | G76: Repeat | H76: Uttar Pradesh | I76: UP | J76: North | K76: Kanpur | L76: Amazon | M76: P504 | N76: Cotton Bedsheet | O76: Home & Kitchen | P76: 1 | Q76: 1299 | R76: 0.15 | S76: 1299 | T76: 194.85 | U76: 1104.15 | V76: 585 | W76: 585 | X76: 120 | Y76: 399.15 | Z76: 0.3614998 | AA76: 0 | AB76: 45641 | AC76: -132 | AD76: Express (≤2d) | AE76: 0 | AF76: COD | AG76: 45777 | AH76: 4 | AI76: Yes | AJ76: 1
A77: ORD-102910 | B77: 45770 | C77: 2025 | D77: 45748 | E77: 4 | F77: CUST-00132 | G77: New | H77: West Bengal | I77: WB | J77: East | K77: Kolkata | L77: Amazon | M77: P501 | N77: Copper Water Bottle | O77: Home & Kitchen | P77: 2 | Q77: 899 | R77: 0.05 | S77: 1798 | T77: 89.9 | U77: 1708.1 | V77: 378 | W77: 756 | X77: 60 | Y77: 892.1 | Z77: 0.52227621 | AA77: 0.05 | AB77: 45828 | AC77: 58 | AD77: Delayed (5d+) | AE77: 0.05 | AF77: Credit Card | AG77: 45773 | AI77: No | AJ77: 0
A78: ORD-102859 | B78: 45765 | C78: 2025 | D78: 45748 | E78: 4 | F78: CUST-00237 | G78: Repeat | H78: Uttar Pradesh | I78: UP | J78: North | K78: Kanpur | L78: Amazon | M78: P504 | N78: Cotton Bedsheet | O78: Home & Kitchen | P78: 1 | Q78: 1299 | R78: 0.05 | S78: 1299 | T78: 64.95 | U78: 1234.05 | V78: 585 | W78: 585 | X78: 60 | Y78: 589.05 | Z78: 0.47733074 | AA78: 10 | AB78: 45772 | AC78: 7 | AD78: Delayed (5d+) | AE78: 0.1 | AF78: Wallet | AG78: 45769 | AH78: 3 | AJ78: 0
A79: ORD-102842 | B79: 45762 | C79: 2025 | D79: 45748 | E79: 4 | F79: CUST-00749 | G79: Repeat | H79: Telangana | I79: TG | J79: South | K79: Hyderabad | L79: Amazon | M79: P503 | N79: Scented Candle Set | O79: Home & Kitchen | P79: 4 | Q79: 699 | R79: 0 | S79: 2796 | T79: 0 | U79: 2796 | V79: 245 | W79: 980 | X79: 60 | Y79: 1756 | Z79: 0.62804006 | AA79: 0.3 | AB79: 46003 | AC79: 241 | AD79: Delayed (5d+) | AE79: 0.3 | AF79: COD | AG79: 45764 | AI79: No | AJ79: 0
A80: ORD-102817 | B80: 45758 | C80: 2025 | D80: 45748 | E80: 4 | F80: CUST-02657 | G80: Repeat | H80: Odisha | I80: OD | J80: East | K80: Bhubaneswar | L80: Amazon | M80: P503 | N80: Scented Candle Set | O80: Home & Kitchen | P80: 1 | Q80: 699 | R80: 0.1 | S80: 699 | T80: 69.9 | U80: 629.1 | V80: 245 | W80: 245 | X80: 60 | Y80: 324.1 | Z80: 0.51518042 | AA80: 0.15 | AB80: 45476 | AC80: -282 | AD80: Express (≤2d) | AE80: 0.15 | AF80: UPI | AG80: 45761 | AJ80: 0
A81: ORD-102783 | B81: 45754 | C81: 2025 | D81: 45748 | E81: 4 | F81: CUST-00976 | G81: Repeat | H81: Karnataka | I81: KA | J81: South | K81: Bengaluru | L81: Amazon | M81: P504 | N81: Cotton Bedsheet | O81: Home & Kitchen | P81: 1 | Q81: 1299 | R81: 0.35 | S81: 1299 | T81: 454.65 | U81: 844.35 | V81: 585 | W81: 585 | X81: 60 | Y81: 199.35 | Z81: 0.23609877 | AA81: 0 | AB81: 45742 | AC81: -12 | AD81: Express (≤2d) | AE81: 0 | AF81: Debit Card | AG81: 45756 | AH81: 4 | AJ81: 0
A82: ORD-102730 | B82: 45747 | C82: 2025 | D82: 45717 | E82: 3 | F82: CUST-02224 | G82: Repeat | H82: Gujarat | I82: GJ | J82: West | K82: Ahmedabad | L82: Amazon | M82: P501 | N82: Copper Water Bottle | O82: Home & Kitchen | P82: 1 | Q82: 899 | R82: 0.05 | S82: 899 | T82: 44.95 | U82: 854.05 | V82: 378 | W82: 378 | X82: 60 | Y82: 416.05 | Z82: 0.48714946 | AA82: 0.1 | AB82: 45477 | AC82: -270 | AD82: Express (≤2d) | AE82: 0.1 | AF82: UPI | AG82: 45749 | AI82: 0 | AJ82: 0
A83: ORD-102723 | B83: 45746 | C83: 2025 | D83: 45717 | E83: 3 | F83: CUST-00812 | G83: Repeat | H83: Karnataka | I83: KA | J83: South | K83: Bengaluru | L83: Amazon | M83: P501 | N83: Copper Water Bottle | O83: Home & Kitchen | P83: 3 | Q83: 899 | R83: 0.15 | S83: 2697 | T83: 404.55 | U83: 2292.45 | V83: 378 | W83: 1134 | X83: 60 | Y83: 1098.45 | Z83: 0.47915985 | AA83: 5 | AB83: 45979 | AC83: 233 | AD83: Delayed (5d+) | AE83: 0.05 | AF83: COD | AG83: 45749 | AH83: 4 | AJ83: 0
A84: ORD-102640 | B84: 45734 | C84: 2025 | D84: 45717 | E84: 3 | F84: CUST-00509 | G84: Repeat | H84: Karnataka | I84: KA | J84: South | K84: Bengaluru | L84: Amazon | M84: P503 | N84: Scented Candle Set | O84: Home & Kitchen | P84: 1 | Q84: 699 | R84: 0.15 | S84: 699 | T84: 104.85 | U84: 594.15 | V84: 245 | W84: 245 | X84: 60 | Y84: 289.15 | Z84: 0.48666162 | AA84: 0.2 | AB84: 45309 | AC84: -425 | AD84: Express (≤2d) | AE84: 0.2 | AF84: UPI | AG84: 45736 | AH84: 4 | AI84: No | AJ84: 0
A85: ORD-102631 | B85: 45733 | C85: 2025 | D85: 45717 | E85: 3 | F85: CUST-00466 | G85: New | H85: Maharashtra | I85: MH | J85: West | K85: Pune | L85: Amazon | M85: P504 | N85: Cotton Bedsheet | O85: Home & Kitchen | P85: 3 | Q85: 1299 | R85: 0.15 | S85: 3897 | T85: 584.55 | U85: 3312.45 | V85: 585 | W85: 1755 | X85: 60 | Y85: 1497.45 | Z85: 0.4520672 | AA85: 0 | AB85: 45971 | AC85: 238 | AD85: Delayed (5d+) | AE85: 0 | AF85: UPI | AG85: 45735 | AH85: 4 | AI85: No | AJ85: 0
A86: ORD-102614 | B86: 45731 | C86: 2025 | D86: 45717 | E86: 3 | F86: CUST-01260 | G86: Repeat | H86: Tamil Nadu | I86: TN | J86: South | K86: Coimbatore | L86: Amazon | M86: P503 | N86: Scented Candle Set | O86: Home & Kitchen | P86: 1 | Q86: 699 | R86: 0.3 | S86: 699 | T86: 209.7 | U86: 489.3 | V86: 245 | W86: 245 | X86: 60 | Y86: 184.3 | Z86: 0.37666054 | AA86: 0.2 | AB86: 45727 | AC86: -4 | AD86: Express (≤2d) | AE86: 0.2 | AF86: Debit Card | AG86: 45732 | AI86: No | AJ86: 0
A87: ORD-100083 | B87: 45305 | C87: 2024 | D87: 45292 | E87: 1 | F87: CUST-00517 | G87: New | H87: Rajasthan | I87: RJ | J87: North | K87: Jaipur | L87: Amazon | M87: P501 | N87: Copper Water Bottle | O87: Home & Kitchen | P87: 1 | Q87: 899 | R87: 0 | S87: 899 | T87: 0 | U87: 899 | V87: 378 | W87: 378 | X87: 60 | Y87: 461 | Z87: 0.51279199 | AA87: 15 | AB87: 45756 | AC87: 451 | AD87: Delayed (5d+) | AE87: 0.15 | AF87: Wallet | AG87: 45309 | AI87: No | AJ87: 0
A88: ORD-102558 | B88: 45723 | C88: 2025 | D88: 45717 | E88: 3 | F88: CUST-00318 | G88: Repeat | H88: Tamil Nadu | I88: TN | J88: South | K88: Coimbatore | L88: Amazon | M88: P503 | N88: Scented Candle Set | O88: Home & Kitchen | P88: 2 | Q88: 699 | R88: 0.1 | S88: 1398 | T88: 139.8 | U88: 1258.2 | V88: 245 | W88: 490 | X88: 60 | Y88: 708.2 | Z88: 0.56286759 | AA88: 0.3 | AB88: 45866 | AC88: 143 | AD88: Delayed (5d+) | AE88: 0.3 | AF88: COD | AG88: 45724 | AH88: 4 | AI88: 0 | AJ88: 0
A89: ORD-102535 | B89: 45720 | C89: 2025 | D89: 45717 | E89: 3 | F89: CUST-00353 | G89: Repeat | H89: Telangana | I89: TG | J89: South | K89: Hyderabad | L89: Amazon | M89: P503 | N89: Scented Candle Set | O89: Home & Kitchen | P89: 4 | Q89: 699 | R89: 0 | S89: 2796 | T89: 0 | U89: 2796 | V89: 245 | W89: 980 | X89: 60 | Y89: 1756 | Z89: 0.62804006 | AA89: 0.3 | AB89: 46017 | AC89: 297 | AD89: Delayed (5d+) | AE89: 0.3 | AF89: UPI | AG89: 45724 | AH89: 5 | AI89: N | AJ89: 0
A90: ORD-102528 | B90: 45719 | C90: 2025 | D90: 45717 | E90: 3 | F90: CUST-00715 | G90: Repeat | H90: Delhi | I90: DL | J90: North | K90: New Delhi | L90: Amazon | M90: P504 | N90: Cotton Bedsheet | O90: Home & Kitchen | P90: 1 | Q90: 1299 | R90: 0.2 | S90: 1299 | T90: 259.8 | U90: 1039.2 | V90: 585 | W90: 585 | X90: 60 | Y90: 394.2 | Z90: 0.37933025 | AA90: 0 | AB90: 45474 | AC90: -245 | AD90: Express (≤2d) | AE90: 0 | AF90: UPI | AG90: 45721 | AI90: No | AJ90: 0
A91: ORD-102511 | B91: 45716 | C91: 2025 | D91: 45689 | E91: 2 | F91: CUST-00201 | G91: Repeat | H91: Punjab | I91: PB | J91: North | K91: Amritsar | L91: Amazon | M91: P504 | N91: Cotton Bedsheet | O91: Home & Kitchen | P91: 2 | Q91: 1299 | R91: 0.2 | S91: 2598 | T91: 519.6 | U91: 2078.4 | V91: 585 | W91: 1170 | X91: 60 | Y91: 848.4 | Z91: 0.40819861 | AA91: 0.1 | AB91: 45868 | AC91: 152 | AD91: Delayed (5d+) | AE91: 0.1 | AF91: COD | AG91: 45720 | AH91: 4 | AI91: No | AJ91: 0
A92: ORD-102514 | B92: 45716 | C92: 2025 | D92: 45689 | E92: 2 | F92: CUST-00247 | G92: Repeat | H92: Uttar Pradesh | I92: UP | J92: North | K92: Kanpur | L92: Amazon | M92: P504 | N92: Cotton Bedsheet | O92: Home & Kitchen | P92: 1 | Q92: 1299 | R92: 0 | S92: 1299 | T92: 0 | U92: 1299 | V92: 585 | W92: 585 | X92: 60 | Y92: 654 | Z92: 0.5034642 | AA92: 0 | AB92: 45655 | AC92: -61 | AD92: Express (≤2d) | AE92: 0 | AF92: Credit Card | AG92: 45721 | AH92: 4 | AI92: No | AJ92: 0
A93: ORD-100087 | B93: 45306 | C93: 2024 | D93: 45292 | E93: 1 | F93: CUST-01094 | G93: New | H93: Bihar | I93: BR | J93: East | K93: Patna | L93: Amazon | M93: P501 | N93: Copper Water Bottle | O93: Home & Kitchen | P93: 2 | Q93: 899 | R93: 0.05 | S93: 1798 | T93: 89.9 | U93: 1708.1 | V93: 378 | W93: 756 | X93: 60 | Y93: 892.1 | Z93: 0.52227621 | AA93: 0.05 | AB93: 45817 | AC93: 511 | AD93: Delayed (5d+) | AE93: 0.05 | AF93: Credit Card | AG93: 45309 | AH93: 4 | AJ93: 0
A94: ORD-102501 | B94: 45714 | C94: 2025 | D94: 45689 | E94: 2 | F94: CUST-02359 | G94: New | H94: Rajasthan | I94: RJ | J94: North | K94: Jaipur | L94: Amazon | M94: P504 | N94: Cotton Bedsheet | O94: Home & Kitchen | P94: 1 | Q94: 1299 | R94: 0.2 | S94: 1299 | T94: 259.8 | U94: 1039.2 | V94: 585 | W94: 585 | X94: 60 | Y94: 394.2 | Z94: 0.37933025 | AA94: 0 | AB94: 45604 | AC94: -110 | AD94: Express (≤2d) | AE94: 0 | AF94: COD | AG94: 45716 | AJ94: 0
A95: ORD-102488 | B95: 45712 | C95: 2025 | D95: 45689 | E95: 2 | F95: CUST-02626 | G95: New | H95: Bihar | I95: BR | J95: East | K95: Patna | L95: Amazon | M95: P503 | N95: Scented Candle Set | O95: Home & Kitchen | P95: 1 | Q95: 699 | R95: 0.2 | S95: 699 | T95: 139.8 | U95: 559.2 | V95: 245 | W95: 245 | X95: 60 | Y95: 254.2 | Z95: 0.45457797 | AA95: 0.2 | AB95: 45653 | AC95: -59 | AD95: Express (≤2d) | AE95: 0.2 | AF95: Credit Card | AG95: 45716 | AH95: 4 | AJ95: 0
A96: ORD-100094 | B96: 45307 | C96: 2024 | D96: 45292 | E96: 1 | F96: CUST-00617 | G96: New | H96: West Bengal | I96: WB | J96: East | K96: Kolkata | L96: Amazon | M96: P503 | N96: Scented Candle Set | O96: Home & Kitchen | P96: 1 | Q96: 699 | R96: 0.25 | S96: 699 | T96: 174.75 | U96: 524.25 | V96: 245 | W96: 245 | X96: 60 | Y96: 219.25 | Z96: 0.4182165 | AA96: 0.15 | AB96: 45462 | AC96: 155 | AD96: Delayed (5d+) | AE96: 0.15 | AF96: UPI | AG96: 45312 | AJ96: 0
A97: ORD-102476 | B97: 45709 | C97: 2025 | D97: 45689 | E97: 2 | F97: CUST-00059 | G97: New | H97: Jharkhand | I97: JH | J97: East | K97: Ranchi | L97: Amazon | M97: P503 | N97: Scented Candle Set | O97: Home & Kitchen | P97: 1 | Q97: 699 | R97: 0 | S97: 699 | T97: 0 | U97: 699 | V97: 245 | W97: 245 | X97: 60 | Y97: 394 | Z97: 0.56366237 | AA97: 25 | AB97: 45547 | AC97: -162 | AD97: Express (≤2d) | AE97: 0.25 | AF97: UPI | AG97: 45712 | AH97: 5 | AI97: 0 | AJ97: 0
A98: ORD-102445 | B98: 45705 | C98: 2025 | D98: 45689 | E98: 2 | F98: CUST-02193 | G98: Repeat | H98: Maharashtra | I98: MH | J98: West | K98: Mumbai | L98: Amazon | M98: P502 | N98: Ceramic Dinner Set | O98: Home & Kitchen | P98: 2 | Q98: 2499 | R98: 0.45 | S98: 4998 | T98: 2249.1 | U98: 2748.9 | V98: 1250 | W98: 2500 | X98: 60 | Y98: 188.9 | Z98: 0.068718396 | AA98: 0.3 | AB98: 45806 | AC98: 101 | AD98: Delayed (5d+) | AE98: 0.3 | AF98: Debit Card | AG98: 45707 | AH98: 4 | AJ98: 0
A99: ORD-102433 | B99: 45703 | C99: 2025 | D99: 45689 | E99: 2 | F99: CUST-02537 | G99: New | H99: Gujarat | I99: GJ | J99: West | K99: Surat | L99: Amazon | M99: P501 | N99: Copper Water Bottle | O99: Home & Kitchen | P99: 1 | Q99: 899 | R99: 0.2 | S99: 899 | T99: 179.8 | U99: 719.2 | V99: 378 | W99: 378 | X99: 60 | Y99: 281.2 | Z99: 0.39098999 | AA99: 15 | AB99: 45754 | AC99: 51 | AD99: Delayed (5d+) | AE99: 0.15 | AF99: Wallet | AG99: 45708 | AH99: 4 | AJ99: 0
A100: ORD-102427 | B100: 45702 | C100: 2025 | D100: 45689 | E100: 2 | F100: CUST-00592 | G100: New | H100: Assam | I100: AS | J100: East | K100: Guwahati | L100: Amazon | M100: P503 | N100: Scented Candle Set | O100: Home & Kitchen | P100: 1 | Q100: 699 | R100: 0 | S100: 699 | T100: 0 | U100: 699 | V100: 245 | W100: 245 | X100: 60 | Y100: 394 | Z100: 0.56366237 | AA100: 0.25 | AB100: 45687 | AC100: -15 | AD100: Express (≤2d) | AE100: 0.25 | AF100: Credit Card | AG100: 45709 | AH100: 3 | AJ100: 0
A101: ORD-102370 | B101: 45694 | C101: 2025 | D101: 45689 | E101: 2 | F101: CUST-00393 | G101: Repeat | H101: Punjab | I101: PB | J101: North | K101: Amritsar | L101: Amazon | M101: P503 | N101: Scented Candle Set | O101: Home & Kitchen | P101: 1 | Q101: 699 | R101: 0.05 | S101: 699 | T101: 34.95 | U101: 664.05 | V101: 245 | W101: 245 | X101: 60 | Y101: 359.05 | Z101: 0.54069724 | AA101: 0.2 | AB101: 45479 | AC101: -215 | AD101: Express (≤2d) | AE101: 0.2 | AF101: UPI | AG101: 45697 | AI101: No | AJ101: 0
A102: ORD-102362 | B102: 45692 | C102: 2025 | D102: 45689 | E102: 2 | F102: CUST-00229 | G102: New | H102: Uttarakhand | I102: UK | J102: North | K102: Dehradun | L102: Amazon | M102: P502 | N102: Ceramic Dinner Set | O102: Home & Kitchen | P102: 2 | Q102: 2499 | R102: 0 | S102: 4998 | T102: 0 | U102: 4998 | V102: 1250 | W102: 2500 | X102: 60 | Y102: 2438 | Z102: 0.48779512 | AA102: 0.4 | AB102: 45848 | AC102: 156 | AD102: Delayed (5d+) | AE102: 0.4 | AF102: COD | AG102: 45696 | AH102: 3 | AI102: N | AJ102: 0
...

Sheet Pivot_Analysis
A10: Revenue by Region & Year | B10: Year | F10: Profit each Channel | G10: Sales Channel
A11: State by Region | B11: 2024 | C11: 2025 | D11: Grand Total | F11: Product Category | G11: Amazon | H11: Flipkart | I11: Myntra | J11: Nykaa | K11: Website | L11: Grand Total
A12: East | B12: 406753.6 | C12: 461777.95 | D12: 868531.55 | F12: Apparel | G12: 125477.05 | H12: 105193.95 | I12: 305578.55 | K12: 98919.4 | L12: 635168.95
A13: Assam | B13: 38310 | C13: 39518.75 | D13: 77828.75 | F13: Electronics | G13: 23665.6 | H13: 22659.45 | K13: 22215.15 | L13: 68540.2
A14: Bihar | B14: 76953.3 | C14: 103134.45 | D14: 180087.75 | F14: Footwear | G14: 77701.35 | H14: 68360.5 | I14: 179811.3 | K14: 53967.1 | L14: 379840.25
A15: Chhattisgarh | B15: 31920.7 | C15: 43939.45 | D15: 75860.15 | F15: Haircare | G15: 52745.85 | H15: 47382.2 | J15: 49789.3 | K15: 33834.35 | L15: 183751.7
A16: Jharkhand | B16: 38098.6 | C16: 61499.15 | D16: 99597.75 | F16: Home & Kitchen | G16: 108915.05 | H16: 73718 | K16: 65289.15 | L16: 247922.2
A17: Odisha | B17: 53784.95 | C17: 54244.05 | D17: 108029 | F17: Skincare | G17: 105358.95 | H17: 95260.6 | J17: 88393.2 | K17: 59922.15 | L17: 348934.9
A18: West Bengal | B18: 167686.05 | C18: 159442.1 | D18: 327128.15 | F18: Wellness | G18: 57672.85 | H18: 48200.65 | J18: 60028.6 | K18: 53194.15 | L18: 219096.25
A19: North | B19: 666329.05 | C19: 909325.35 | D19: 1575654.4 | F19: Grand Total | G19: 551536.7 | H19: 460775.35 | I19: 485389.85 | J19: 198211.1 | K19: 387341.45 | L19: 2083254.4
A20: Delhi | B20: 126759.5 | C20: 275850.15 | D20: 402609.65
A21: Haryana | B21: 81540.65 | C21: 89968 | D21: 171508.65 | F21: Returned Rate | G21: Delivery Speed
A22: Himachal Pradesh | B22: 30547.35 | C22: 27166.55 | D22: 57713.9 | F22: Payment Mode | G22: Delayed (5d+) | H22: Express (≤2d) | I22: Standard (3-4d) | J22: Grand Total
A23: Jammu & Kashmir | B23: 23446.1 | C23: 54726.65 | D23: 78172.75 | F23: COD | G23: 35 | H23: 46 | I23: 88 | J23: 169
A24: Punjab | B24: 51962.2 | C24: 86132.7 | D24: 138094.9 | F24: Credit Card | G24: 16 | H24: 14 | I24: 33 | J24: 63
A25: Rajasthan | B25: 128421.9 | C25: 133323.55 | D25: 261745.45 | F25: Debit Card | G25: 16 | H25: 18 | I25: 11 | J25: 45
A26: Uttar Pradesh | B26: 181546.25 | C26: 208031.5 | D26: 389577.75 | F26: UPI | G26: 56 | H26: 67 | I26: 77 | J26: 200
A27: Uttarakhand | B27: 42105.1 | C27: 34126.25 | D27: 76231.35 | F27: Wallet | G27: 4 | H27: 4 | I27: 18 | J27: 26
A28: South | B28: 613236.5 | C28: 884455.95 | D28: 1497692.5 | F28: Grand Total | G28: 127 | H28: 149 | I28: 227 | J28: 503
A29: Andhra Pradesh | B29: 71368.55 | C29: 142052.7 | D29: 213421.25
A30: Karnataka | B30: 188827.7 | C30: 215781.9 | D30: 404609.6 | F30: Customer Type | G30: Sum of Net Revenue | H30: Count of Order ID
A31: Kerala | B31: 59706.75 | C31: 145342.45 | D31: 205049.2 | F31: New | G31: 2415017.3 | H31: 2223
A32: Tamil Nadu | B32: 166882.05 | C32: 218072.2 | D32: 384954.25 | F32: Repeat | G32: 2741125.2 | H32: 2610
A33: Telangana | B33: 126451.45 | C33: 163206.7 | D33: 289658.15 | F33: Grand Total | G33: 5156142.5 | H33: 4833
A34: West | B34: 570317.35 | C34: 643946.7 | D34: 1214264.1
A35: Goa | B35: 33272.25 | C35: 42625.3 | D35: 75897.55 | F35: Year / Month | G35: Sum of Net Revenue
A36: Gujarat | B36: 174041.8 | C36: 189736.3 | D36: 363778.1 | F36: 2024 | G36: 2256636.5
A37: Madhya Pradesh | B37: 132072.95 | C37: 129368.15 | D37: 261441.1 | F37: 2025 | G37: 2899506
A38: Maharashtra | B38: 230930.35 | C38: 282216.95 | D38: 513147.3 | F38: Grand Total | G38: 5156142.5
A39: Grand Total | B39: 2256636.5 | C39: 2899505.9 | D39: 5156142.5

Sheet Orders
A1: Order ID | B1: Order Date | C1: Year | D1: Month | E1: Month No | F1: Customer ID | G1: Customer Type | H1: State | I1: State Code | J1: Region | K1: City | L1: Sales Channel | M1: Product ID | N1: Product Name | O1: Category | P1: Quantity | Q1: Unit Price | R1: Discount_Clean2 | S1: Gross Sale | T1: Discount Amount | U1: Net Revenue | V1: Unit Cost | W1: COGS | X1: Shipping Cost | Y1: Profit | Z1: Margin % | AA1: Payment Method | AB1: Delivery Date | AC1: Delivery Days | AD1: Delivery Speed | AE1: Customer Rating | AF1: Returned
A2: ORD-100001 | B2: 45292 | C2: =YEAR(OrdersTable[[#This Row],[Order Date]]) -> 2024 | D2: =DATE(YEAR(OrdersTable[[#This Row],[Order Date]]),MONTH(OrdersTable[[#This Row],[Order Date]]),1) -> 45292 | E2: =MONTH(OrdersTable[[#This Row],[Order Date]]) -> 1 | F2: CUST-03155 | G2: =IF(OrdersTable[[#This Row],[Order Date]]=_xlfn.MINIFS(Order_Date, Customer_ID, OrdersTable[[#This Row],[Customer ID]]), "New", "Repeat") -> New | H2: Rajasthan | I2: =INDEX(State!B:B,MATCH(OrdersTable[[#This Row],[State]],State!A:A,0)) -> RJ | J2: =INDEX(State!C:C,MATCH(OrdersTable[[#This Row],[State Code]],State!B:B,0)) -> North | K2: Jaipur | L2: Amazon | M2: P703 | N2: =INDEX(Products!B:B,MATCH(OrdersTable[[#This Row],[Product ID]],Products!A:A,0)) -> Green Tea (100 bags) | O2: =INDEX(Products!C:C,MATCH(OrdersTable[[#This Row],[Product ID]],Products!A:A,0)) -> Wellness | P2: 1 | Q2: 399 | R2: 0.4 | S2: =OrdersTable[[#This Row],[Quantity]]*OrdersTable[[#This Row],[Unit Price]] -> 399 | T2: =OrdersTable[[#This Row],[Gross Sale]]*OrdersTable[[#This Row],[Discount_Clean2]] -> 159.6 | U2: =OrdersTable[[#This Row],[Gross Sale]]-OrdersTable[[#This Row],[Discount Amount]] -> 239.4 | V2: =INDEX(Products!E:E,MATCH(OrdersTable[[#This Row],[Product ID]],Products!A:A,0)) -> 128 | W2: =OrdersTable[[#This Row],[Quantity]]*OrdersTable[[#This Row],[Unit Cost]] -> 128 | X2: ='Dropdown Lists'!$I$2*(1+OrdersTable[[#This Row],[Returned]]) -> 60 | Y2: =OrdersTable[[#This Row],[Net Revenue]]-OrdersTable[[#This Row],[COGS]]-OrdersTable[[#This Row],[Shipping Cost]] -> 51.4 | Z2: =IFERROR(OrdersTable[[#This Row],[Profit]]/OrdersTable[[#This Row],[Net Revenue]],0) -> 0.21470343 | AA2: UPI | AB2: 45295 | AC2: =OrdersTable[[#This Row],[Delivery Date]]-OrdersTable[[#This Row],[Order Date]] -> 3 | AD2: =IF(OrdersTable[[#This Row],[Delivery Days]]<=2, "Express (≤2d)", IF(OrdersTable[[#This Row],[Delivery Days]]<=4, "Standard (3-4d)", "Delayed (5d+)")) -> Standard (3-4d) | AE2: 5 | AF2: 0
A3: ORD-100002 | B3: 45292 | C3: =YEAR(OrdersTable[[#This Row],[Order Date]]) -> 2024 | D3: =DATE(YEAR(OrdersTable[[#This Row],[Order Date]]),MONTH(OrdersTable[[#This Row],[Order Date]]),1) -> 45292 | E3: =MONTH(OrdersTable[[#This Row],[Order Date]]) -> 1 | F3: CUST-02589 | G3: =IF(OrdersTable[[#This Row],[Order Date]]=_xlfn.MINIFS(Order_Date, Customer_ID, OrdersTable[[#This Row],[Customer ID]]), "New", "Repeat") -> New | H3: Gujarat | I3: =INDEX(State!B:B,MATCH(OrdersTable[[#This Row],[State]],State!A:A,0)) -> GJ | J3: =INDEX(State!C:C,MATCH(OrdersTable[[#This Row],[State Code]],State!B:B,0)) -> West | K3: Surat | L3: Myntra | M3: P304 | N3: =INDEX(Products!B:B,MATCH(OrdersTable[[#This Row],[Product ID]],Products!A:A,0)) -> Denim Jacket | O3: =INDEX(Products!C:C,MATCH(OrdersTable[[#This Row],[Product ID]],Products!A:A,0)) -> Apparel | P3: 1 | Q3: 2499 | R3: 0 | S3: =OrdersTable[[#This Row],[Quantity]]*OrdersTable[[#This Row],[Unit Price]] -> 2499 | T3: =OrdersTable[[#This Row],[Gross Sale]]*OrdersTable[[#This Row],[Discount_Clean2]] -> 0 | U3: =OrdersTable[[#This Row],[Gross Sale]]-OrdersTable[[#This Row],[Discount Amount]] -> 2499 | V3: =INDEX(Products!E:E,MATCH(OrdersTable[[#This Row],[Product ID]],Products!A:A,0)) -> 1125 | W3: =OrdersTable[[#This Row],[Quantity]]*OrdersTable[[#This Row],[Unit Cost]] -> 1125 | X3: ='Dropdown Lists'!$I$2*(1+OrdersTable[[#This Row],[Returned]]) -> 120 | Y3: =OrdersTable[[#This Row],[Net Revenue]]-OrdersTable[[#This Row],[COGS]]-OrdersTable[[#This Row],[Shipping Cost]] -> 1254 | Z3: =IFERROR(OrdersTable[[#This Row],[Profit]]/OrdersTable[[#This Row],[Net Revenue]],0) -> 0.50180072 | AA3: Credit Card | AB3: 45296 | AC3: =OrdersTable[[#This Row],[Delivery Date]]-OrdersTable[[#This Row],[Order Date]] -> 4 | AD3: =IF(OrdersTable[[#This Row],[Delivery Days]]<=2, "Express (≤2d)", IF(OrdersTable[[#This Row],[Delivery Days]]<=4, "Standard (3-4d)", "Delayed (5d+)")) -> Standard (3-4d) | AF3: 1
